packs/spi-lab/src/spi_slave_loopback.v
// SPDX-License-Identifier: CC-BY-4.0
// Copyright (c) 2026 Ferrite Engineering
//
// Simple SPI mode-0 slave. Samples MOSI on the rising edge of SCLK and
// shifts the bits into an 8-bit receive register. When chip-select
// returns high, the most-recently-received byte is latched into
// `last_byte` — students inspect this in the waveform to verify that
// the wire-level decoding matches the byte the master sent.
//
// MISO is held inactive (low). A full loopback that drives MISO with
// the previous byte would muddle the pedagogy (mode-0 MISO timing is
// already covered by the `miso` lane in the waveform with the
// SPI decoder applied).

`timescale 1ns / 1ns

module spi_slave_loopback (
    input  wire sclk,
    input  wire mosi,
    output wire miso,
    input  wire cs_n,
    input  wire rst_n
);
    reg [7:0] rx_shift;
    reg [7:0] last_byte;

    assign miso = 1'b0;

    always @(posedge sclk or negedge rst_n) begin
        if (!rst_n)        rx_shift <= 8'h00;
        else if (!cs_n)    rx_shift <= {rx_shift[6:0], mosi};
    end

    always @(posedge cs_n or negedge rst_n) begin
        if (!rst_n) last_byte <= 8'h00;
        else        last_byte <= rx_shift;
    end
endmodule

packs/spi-lab/src/spi_master.v
// SPDX-License-Identifier: CC-BY-4.0
// Copyright (c) 2026 Ferrite Engineering
//
// SPI mode-0 master with an internal /10 clock divider that takes a
// 50 MHz system clock to a 5 MHz SCLK. After reset, the master walks
// through an internal 4-byte ROM and transmits 0x12, 0x34, 0x56, 0x78
// MSB-first, with a short CS_n high gap between each byte.
//
// Mode 0:
//   * CPOL = 0  -- SCLK idles low.
//   * CPHA = 0  -- master changes MOSI on the falling edge of SCLK;
//                  slave samples MOSI on the rising edge of SCLK.
//
// Cycle plan at 50 MHz (`clk`):
//   * Each SCLK half-period is 5 system cycles (100 ns).
//   * Each SCLK full period is 10 system cycles (200 ns), so SCLK is 5 MHz.
//   * Each byte takes 80 system cycles to clock out (8 * 200 / 20).
//   * Between bytes the master deasserts CS_n for 20 system cycles
//     (400 ns idle gap).

`timescale 1ns / 1ns

module spi_master (
    input  wire clk,
    input  wire rst_n,
    output reg  sclk,
    output reg  mosi,
    output reg  cs_n,
    input  wire miso
);
    // Transmit ROM: held in registers initialised on reset.
    reg [7:0] tx_byte0;
    reg [7:0] tx_byte1;
    reg [7:0] tx_byte2;
    reg [7:0] tx_byte3;

    // Sequencer states.
    localparam [3:0] S_IDLE    = 4'd0;
    localparam [3:0] S_SETUP   = 4'd1;   // cs_n driven low; one-cycle setup before SCLK
    localparam [3:0] S_BIT_LO  = 4'd2;   // SCLK low half (5 system cycles)
    localparam [3:0] S_BIT_HI  = 4'd3;   // SCLK high half (5 system cycles)
    localparam [3:0] S_GAP     = 4'd4;   // cs_n high between bytes (20 system cycles)
    localparam [3:0] S_DONE    = 4'd5;

    reg [3:0] state;
    reg [2:0] div;        // 0..4 within each half-period
    reg [2:0] bit_idx;    // 0..7 (counts down from 7 for MSB-first)
    reg [1:0] byte_idx;   // 0..3
    reg [4:0] gap_count;
    reg [7:0] shift;

    wire [7:0] current_byte =
        (byte_idx == 2'd0) ? tx_byte0 :
        (byte_idx == 2'd1) ? tx_byte1 :
        (byte_idx == 2'd2) ? tx_byte2 :
                             tx_byte3;

    always @(posedge clk or negedge rst_n) begin
        if (!rst_n) begin
            sclk      <= 1'b0;
            mosi      <= 1'b0;
            cs_n      <= 1'b1;
            tx_byte0  <= 8'h12;
            tx_byte1  <= 8'h34;
            tx_byte2  <= 8'h56;
            tx_byte3  <= 8'h78;
            state     <= S_IDLE;
            div       <= 3'd0;
            bit_idx   <= 3'd7;
            byte_idx  <= 2'd0;
            gap_count <= 5'd0;
            shift     <= 8'h00;
        end else begin
            case (state)
                S_IDLE: begin
                    cs_n  <= 1'b0;          // assert CS_n for the new byte
                    shift <= current_byte;
                    mosi  <= current_byte[7]; // MSB first
                    bit_idx <= 3'd7;
                    div   <= 3'd0;
                    state <= S_SETUP;
                end

                S_SETUP: begin
                    // Hold one cycle of CS-setup with SCLK low before the first bit.
                    state <= S_BIT_LO;
                    div   <= 3'd0;
                end

                S_BIT_LO: begin
                    sclk <= 1'b0;
                    if (div == 3'd4) begin
                        // Move to SCLK high.
                        sclk <= 1'b1;
                        div  <= 3'd0;
                        state <= S_BIT_HI;
                    end else begin
                        div <= div + 3'd1;
                    end
                end

                S_BIT_HI: begin
                    sclk <= 1'b1;
                    if (div == 3'd4) begin
                        // Bit complete. Shift to the next bit or move on.
                        div  <= 3'd0;
                        sclk <= 1'b0;
                        if (bit_idx == 3'd0) begin
                            // Byte complete.
                            cs_n      <= 1'b1;
                            mosi      <= 1'b0;
                            gap_count <= 5'd0;
                            if (byte_idx == 2'd3) state <= S_DONE;
                            else                  state <= S_GAP;
                        end else begin
                            // Next bit: present new MOSI on this falling edge.
                            bit_idx <= bit_idx - 3'd1;
                            mosi    <= shift[bit_idx - 1];
                            state   <= S_BIT_LO;
                        end
                    end else begin
                        div <= div + 3'd1;
                    end
                end

                S_GAP: begin
                    if (gap_count == 5'd19) begin
                        gap_count <= 5'd0;
                        byte_idx  <= byte_idx + 2'd1;
                        state     <= S_IDLE;
                    end else begin
                        gap_count <= gap_count + 5'd1;
                    end
                end

                S_DONE: begin
                    sclk <= 1'b0;
                    cs_n <= 1'b1;
                    mosi <= 1'b0;
                end

                default: state <= S_DONE;
            endcase
        end
    end
endmodule

packs/spi-lab/tb/tb_spi.v
// SPDX-License-Identifier: CC-BY-4.0
// Copyright (c) 2026 Ferrite Engineering
//
// SPI master + passive slave loopback test. 50 MHz system clock, SCLK
// divides down to 5 MHz, four bytes transmitted MSB-first.

`timescale 1ns / 1ns

module tb_spi;
    reg  clk;
    reg  rst_n;
    wire sclk;
    wire mosi;
    wire miso;
    wire cs_n;

    spi_master u_master (
        .clk  (clk),
        .rst_n(rst_n),
        .sclk (sclk),
        .mosi (mosi),
        .cs_n (cs_n),
        .miso (miso)
    );

    spi_slave_loopback u_slave (
        .sclk (sclk),
        .mosi (mosi),
        .miso (miso),
        .cs_n (cs_n),
        .rst_n(rst_n)
    );

    initial clk = 1'b1;
    always #10 clk = ~clk;       // 50 MHz, posedges at 20, 40, ...

    initial begin
        $dumpfile("fixtures/reference.vcd");
        $dumpvars(0, tb_spi);

        rst_n = 1'b0;
        #45;
        rst_n = 1'b1;

        #15000;                  // long enough for all 4 bytes + idle slack
        $finish;
    end
endmodule

packs/spi-lab/fixtures/reference.vcd
$date
	Sun May 31 14:43:16 2026
$end
$version
	Icarus Verilog
$end
$timescale
	1ns
$end
$scope module tb_spi $end
$var wire 1 ! miso $end
$var wire 1 " sclk $end
$var wire 1 # mosi $end
$var wire 1 $ cs_n $end
$var reg 1 % clk $end
$var reg 1 & rst_n $end
$scope module u_master $end
$var wire 1 % clk $end
$var wire 1 ! miso $end
$var wire 1 & rst_n $end
$var wire 8 ' current_byte [7:0] $end
$var parameter 4 ( S_BIT_HI $end
$var parameter 4 ) S_BIT_LO $end
$var parameter 4 * S_DONE $end
$var parameter 4 + S_GAP $end
$var parameter 4 , S_IDLE $end
$var parameter 4 - S_SETUP $end
$var reg 3 . bit_idx [2:0] $end
$var reg 2 / byte_idx [1:0] $end
$var reg 1 $ cs_n $end
$var reg 3 0 div [2:0] $end
$var reg 5 1 gap_count [4:0] $end
$var reg 1 # mosi $end
$var reg 1 " sclk $end
$var reg 8 2 shift [7:0] $end
$var reg 4 3 state [3:0] $end
$var reg 8 4 tx_byte0 [7:0] $end
$var reg 8 5 tx_byte1 [7:0] $end
$var reg 8 6 tx_byte2 [7:0] $end
$var reg 8 7 tx_byte3 [7:0] $end
$upscope $end
$scope module u_slave $end
$var wire 1 $ cs_n $end
$var wire 1 ! miso $end
$var wire 1 # mosi $end
$var wire 1 & rst_n $end
$var wire 1 " sclk $end
$var reg 8 8 last_byte [7:0] $end
$var reg 8 9 rx_shift [7:0] $end
$upscope $end
$upscope $end
$enddefinitions $end
$comment Show the parameter values. $end
$dumpall
b1 -
b0 ,
b100 +
b101 *
b10 )
b11 (
$end
#0
$dumpvars
b0 9
b0 8
b1111000 7
b1010110 6
b110100 5
b10010 4
b0 3
b0 2
b0 1
b0 0
b0 /
b111 .
b10010 '
0&
1%
1$
0#
0"
0!
$end
#10
0%
#20
1%
#30
0%
#40
1%
#45
1&
#50
0%
#60
b1 3
b10010 2
0$
1%
#70
0%
#80
b10 3
1%
#90
0%
#100
b1 0
1%
#110
0%
#120
b10 0
1%
#130
0%
#140
b11 0
1%
#150
0%
#160
b100 0
1%
#170
0%
#180
b11 3
b0 0
1"
1%
#190
0%
#200
b1 0
1%
#210
0%
#220
b10 0
1%
#230
0%
#240
b11 0
1%
#250
0%
#260
b100 0
1%
#270
0%
#280
b10 3
b110 .
0"
b0 0
1%
#290
0%
#300
b1 0
1%
#310
0%
#320
b10 0
1%
#330
0%
#340
b11 0
1%
#350
0%
#360
b100 0
1%
#370
0%
#380
b11 3
b0 0
1"
1%
#390
0%
#400
b1 0
1%
#410
0%
#420
b10 0
1%
#430
0%
#440
b11 0
1%
#450
0%
#460
b100 0
1%
#470
0%
#480
b10 3
b101 .
0"
b0 0
1%
#490
0%
#500
b1 0
1%
#510
0%
#520
b10 0
1%
#530
0%
#540
b11 0
1%
#550
0%
#560
b100 0
1%
#570
0%
#580
b11 3
b0 0
1"
1%
#590
0%
#600
b1 0
1%
#610
0%
#620
b10 0
1%
#630
0%
#640
b11 0
1%
#650
0%
#660
b100 0
1%
#670
0%
#680
b10 3
1#
b100 .
0"
b0 0
1%
#690
0%
#700
b1 0
1%
#710
0%
#720
b10 0
1%
#730
0%
#740
b11 0
1%
#750
0%
#760
b100 0
1%
#770
0%
#780
b1 9
b11 3
b0 0
1"
1%
#790
0%
#800
b1 0
1%
#810
0%
#820
b10 0
1%
#830
0%
#840
b11 0
1%
#850
0%
#860
b100 0
1%
#870
0%
#880
b10 3
0#
b11 .
0"
b0 0
1%
#890
0%
#900
b1 0
1%
#910
0%
#920
b10 0
1%
#930
0%
#940
b11 0
1%
#950
0%
#960
b100 0
1%
#970
0%
#980
b10 9
b11 3
b0 0
1"
1%
#990
0%
#1000
b1 0
1%
#1010
0%
#1020
b10 0
1%
#1030
0%
#1040
b11 0
1%
#1050
0%
#1060
b100 0
1%
#1070
0%
#1080
b10 3
b10 .
0"
b0 0
1%
#1090
0%
#1100
b1 0
1%
#1110
0%
#1120
b10 0
1%
#1130
0%
#1140
b11 0
1%
#1150
0%
#1160
b100 0
1%
#1170
0%
#1180
b100 9
b11 3
b0 0
1"
1%
#1190
0%
#1200
b1 0
1%
#1210
0%
#1220
b10 0
1%
#1230
0%
#1240
b11 0
1%
#1250
0%
#1260
b100 0
1%
#1270
0%
#1280
b10 3
1#
b1 .
0"
b0 0
1%
#1290
0%
#1300
b1 0
1%
#1310
0%
#1320
b10 0
1%
#1330
0%
#1340
b11 0
1%
#1350
0%
#1360
b100 0
1%
#1370
0%
#1380
b1001 9
b11 3
b0 0
1"
1%
#1390
0%
#1400
b1 0
1%
#1410
0%
#1420
b10 0
1%
#1430
0%
#1440
b11 0
1%
#1450
0%
#1460
b100 0
1%
#1470
0%
#1480
b10 3
0#
b0 .
0"
b0 0
1%
#1490
0%
#1500
b1 0
1%
#1510
0%
#1520
b10 0
1%
#1530
0%
#1540
b11 0
1%
#1550
0%
#1560
b100 0
1%
#1570
0%
#1580
b10010 9
b11 3
b0 0
1"
1%
#1590
0%
#1600
b1 0
1%
#1610
0%
#1620
b10 0
1%
#1630
0%
#1640
b11 0
1%
#1650
0%
#1660
b100 0
1%
#1670
0%
#1680
b10010 8
b100 3
1$
0"
b0 0
1%
#1690
0%
#1700
b1 1
1%
#1710
0%
#1720
b10 1
1%
#1730
0%
#1740
b11 1
1%
#1750
0%
#1760
b100 1
1%
#1770
0%
#1780
b101 1
1%
#1790
0%
#1800
b110 1
1%
#1810
0%
#1820
b111 1
1%
#1830
0%
#1840
b1000 1
1%
#1850
0%
#1860
b1001 1
1%
#1870
0%
#1880
b1010 1
1%
#1890
0%
#1900
b1011 1
1%
#1910
0%
#1920
b1100 1
1%
#1930
0%
#1940
b1101 1
1%
#1950
0%
#1960
b1110 1
1%
#1970
0%
#1980
b1111 1
1%
#1990
0%
#2000
b10000 1
1%
#2010
0%
#2020
b10001 1
1%
#2030
0%
#2040
b10010 1
1%
#2050
0%
#2060
b10011 1
1%
#2070
0%
#2080
b110100 '
b0 3
b1 /
b0 1
1%
#2090
0%
#2100
b1 3
b111 .
b110100 2
0$
1%
#2110
0%
#2120
b10 3
1%
#2130
0%
#2140
b1 0
1%
#2150
0%
#2160
b10 0
1%
#2170
0%
#2180
b11 0
1%
#2190
0%
#2200
b100 0
1%
#2210
0%
#2220
b100100 9
b11 3
b0 0
1"
1%
#2230
0%
#2240
b1 0
1%
#2250
0%
#2260
b10 0
1%
#2270
0%
#2280
b11 0
1%
#2290
0%
#2300
b100 0
1%
#2310
0%
#2320
b10 3
b110 .
0"
b0 0
1%
#2330
0%
#2340
b1 0
1%
#2350
0%
#2360
b10 0
1%
#2370
0%
#2380
b11 0
1%
#2390
0%
#2400
b100 0
1%
#2410
0%
#2420
b1001000 9
b11 3
b0 0
1"
1%
#2430
0%
#2440
b1 0
1%
#2450
0%
#2460
b10 0
1%
#2470
0%
#2480
b11 0
1%
#2490
0%
#2500
b100 0
1%
#2510
0%
#2520
b10 3
1#
b101 .
0"
b0 0
1%
#2530
0%
#2540
b1 0
1%
#2550
0%
#2560
b10 0
1%
#2570
0%
#2580
b11 0
1%
#2590
0%
#2600
b100 0
1%
#2610
0%
#2620
b10010001 9
b11 3
b0 0
1"
1%
#2630
0%
#2640
b1 0
1%
#2650
0%
#2660
b10 0
1%
#2670
0%
#2680
b11 0
1%
#2690
0%
#2700
b100 0
1%
#2710
0%
#2720
b10 3
b100 .
0"
b0 0
1%
#2730
0%
#2740
b1 0
1%
#2750
0%
#2760
b10 0
1%
#2770
0%
#2780
b11 0
1%
#2790
0%
#2800
b100 0
1%
#2810
0%
#2820
b100011 9
b11 3
b0 0
1"
1%
#2830
0%
#2840
b1 0
1%
#2850
0%
#2860
b10 0
1%
#2870
0%
#2880
b11 0
1%
#2890
0%
#2900
b100 0
1%
#2910
0%
#2920
b10 3
0#
b11 .
0"
b0 0
1%
#2930
0%
#2940
b1 0
1%
#2950
0%
#2960
b10 0
1%
#2970
0%
#2980
b11 0
1%
#2990
0%
#3000
b100 0
1%
#3010
0%
#3020
b1000110 9
b11 3
b0 0
1"
1%
#3030
0%
#3040
b1 0
1%
#3050
0%
#3060
b10 0
1%
#3070
0%
#3080
b11 0
1%
#3090
0%
#3100
b100 0
1%
#3110
0%
#3120
b10 3
1#
b10 .
0"
b0 0
1%
#3130
0%
#3140
b1 0
1%
#3150
0%
#3160
b10 0
1%
#3170
0%
#3180
b11 0
1%
#3190
0%
#3200
b100 0
1%
#3210
0%
#3220
b10001101 9
b11 3
b0 0
1"
1%
#3230
0%
#3240
b1 0
1%
#3250
0%
#3260
b10 0
1%
#3270
0%
#3280
b11 0
1%
#3290
0%
#3300
b100 0
1%
#3310
0%
#3320
b10 3
0#
b1 .
0"
b0 0
1%
#3330
0%
#3340
b1 0
1%
#3350
0%
#3360
b10 0
1%
#3370
0%
#3380
b11 0
1%
#3390
0%
#3400
b100 0
1%
#3410
0%
#3420
b11010 9
b11 3
b0 0
1"
1%
#3430
0%
#3440
b1 0
1%
#3450
0%
#3460
b10 0
1%
#3470
0%
#3480
b11 0
1%
#3490
0%
#3500
b100 0
1%
#3510
0%
#3520
b10 3
b0 .
0"
b0 0
1%
#3530
0%
#3540
b1 0
1%
#3550
0%
#3560
b10 0
1%
#3570
0%
#3580
b11 0
1%
#3590
0%
#3600
b100 0
1%
#3610
0%
#3620
b110100 9
b11 3
b0 0
1"
1%
#3630
0%
#3640
b1 0
1%
#3650
0%
#3660
b10 0
1%
#3670
0%
#3680
b11 0
1%
#3690
0%
#3700
b100 0
1%
#3710
0%
#3720
b110100 8
b100 3
1$
0"
b0 0
1%
#3730
0%
#3740
b1 1
1%
#3750
0%
#3760
b10 1
1%
#3770
0%
#3780
b11 1
1%
#3790
0%
#3800
b100 1
1%
#3810
0%
#3820
b101 1
1%
#3830
0%
#3840
b110 1
1%
#3850
0%
#3860
b111 1
1%
#3870
0%
#3880
b1000 1
1%
#3890
0%
#3900
b1001 1
1%
#3910
0%
#3920
b1010 1
1%
#3930
0%
#3940
b1011 1
1%
#3950
0%
#3960
b1100 1
1%
#3970
0%
#3980
b1101 1
1%
#3990
0%
#4000
b1110 1
1%
#4010
0%
#4020
b1111 1
1%
#4030
0%
#4040
b10000 1
1%
#4050
0%
#4060
b10001 1
1%
#4070
0%
#4080
b10010 1
1%
#4090
0%
#4100
b10011 1
1%
#4110
0%
#4120
b1010110 '
b0 3
b10 /
b0 1
1%
#4130
0%
#4140
b1 3
b111 .
b1010110 2
0$
1%
#4150
0%
#4160
b10 3
1%
#4170
0%
#4180
b1 0
1%
#4190
0%
#4200
b10 0
1%
#4210
0%
#4220
b11 0
1%
#4230
0%
#4240
b100 0
1%
#4250
0%
#4260
b1101000 9
b11 3
b0 0
1"
1%
#4270
0%
#4280
b1 0
1%
#4290
0%
#4300
b10 0
1%
#4310
0%
#4320
b11 0
1%
#4330
0%
#4340
b100 0
1%
#4350
0%
#4360
b10 3
1#
b110 .
0"
b0 0
1%
#4370
0%
#4380
b1 0
1%
#4390
0%
#4400
b10 0
1%
#4410
0%
#4420
b11 0
1%
#4430
0%
#4440
b100 0
1%
#4450
0%
#4460
b11010001 9
b11 3
b0 0
1"
1%
#4470
0%
#4480
b1 0
1%
#4490
0%
#4500
b10 0
1%
#4510
0%
#4520
b11 0
1%
#4530
0%
#4540
b100 0
1%
#4550
0%
#4560
b10 3
0#
b101 .
0"
b0 0
1%
#4570
0%
#4580
b1 0
1%
#4590
0%
#4600
b10 0
1%
#4610
0%
#4620
b11 0
1%
#4630
0%
#4640
b100 0
1%
#4650
0%
#4660
b10100010 9
b11 3
b0 0
1"
1%
#4670
0%
#4680
b1 0
1%
#4690
0%
#4700
b10 0
1%
#4710
0%
#4720
b11 0
1%
#4730
0%
#4740
b100 0
1%
#4750
0%
#4760
b10 3
1#
b100 .
0"
b0 0
1%
#4770
0%
#4780
b1 0
1%
#4790
0%
#4800
b10 0
1%
#4810
0%
#4820
b11 0
1%
#4830
0%
#4840
b100 0
1%
#4850
0%
#4860
b1000101 9
b11 3
b0 0
1"
1%
#4870
0%
#4880
b1 0
1%
#4890
0%
#4900
b10 0
1%
#4910
0%
#4920
b11 0
1%
#4930
0%
#4940
b100 0
1%
#4950
0%
#4960
b10 3
0#
b11 .
0"
b0 0
1%
#4970
0%
#4980
b1 0
1%
#4990
0%
#5000
b10 0
1%
#5010
0%
#5020
b11 0
1%
#5030
0%
#5040
b100 0
1%
#5050
0%
#5060
b10001010 9
b11 3
b0 0
1"
1%
#5070
0%
#5080
b1 0
1%
#5090
0%
#5100
b10 0
1%
#5110
0%
#5120
b11 0
1%
#5130
0%
#5140
b100 0
1%
#5150
0%
#5160
b10 3
1#
b10 .
0"
b0 0
1%
#5170
0%
#5180
b1 0
1%
#5190
0%
#5200
b10 0
1%
#5210
0%
#5220
b11 0
1%
#5230
0%
#5240
b100 0
1%
#5250
0%
#5260
b10101 9
b11 3
b0 0
1"
1%
#5270
0%
#5280
b1 0
1%
#5290
0%
#5300
b10 0
1%
#5310
0%
#5320
b11 0
1%
#5330
0%
#5340
b100 0
1%
#5350
0%
#5360
b10 3
b1 .
0"
b0 0
1%
#5370
0%
#5380
b1 0
1%
#5390
0%
#5400
b10 0
1%
#5410
0%
#5420
b11 0
1%
#5430
0%
#5440
b100 0
1%
#5450
0%
#5460
b101011 9
b11 3
b0 0
1"
1%
#5470
0%
#5480
b1 0
1%
#5490
0%
#5500
b10 0
1%
#5510
0%
#5520
b11 0
1%
#5530
0%
#5540
b100 0
1%
#5550
0%
#5560
b10 3
0#
b0 .
0"
b0 0
1%
#5570
0%
#5580
b1 0
1%
#5590
0%
#5600
b10 0
1%
#5610
0%
#5620
b11 0
1%
#5630
0%
#5640
b100 0
1%
#5650
0%
#5660
b1010110 9
b11 3
b0 0
1"
1%
#5670
0%
#5680
b1 0
1%
#5690
0%
#5700
b10 0
1%
#5710
0%
#5720
b11 0
1%
#5730
0%
#5740
b100 0
1%
#5750
0%
#5760
b1010110 8
b100 3
1$
0"
b0 0
1%
#5770
0%
#5780
b1 1
1%
#5790
0%
#5800
b10 1
1%
#5810
0%
#5820
b11 1
1%
#5830
0%
#5840
b100 1
1%
#5850
0%
#5860
b101 1
1%
#5870
0%
#5880
b110 1
1%
#5890
0%
#5900
b111 1
1%
#5910
0%
#5920
b1000 1
1%
#5930
0%
#5940
b1001 1
1%
#5950
0%
#5960
b1010 1
1%
#5970
0%
#5980
b1011 1
1%
#5990
0%
#6000
b1100 1
1%
#6010
0%
#6020
b1101 1
1%
#6030
0%
#6040
b1110 1
1%
#6050
0%
#6060
b1111 1
1%
#6070
0%
#6080
b10000 1
1%
#6090
0%
#6100
b10001 1
1%
#6110
0%
#6120
b10010 1
1%
#6130
0%
#6140
b10011 1
1%
#6150
0%
#6160
b1111000 '
b0 3
b11 /
b0 1
1%
#6170
0%
#6180
b1 3
b111 .
b1111000 2
0$
1%
#6190
0%
#6200
b10 3
1%
#6210
0%
#6220
b1 0
1%
#6230
0%
#6240
b10 0
1%
#6250
0%
#6260
b11 0
1%
#6270
0%
#6280
b100 0
1%
#6290
0%
#6300
b10101100 9
b11 3
b0 0
1"
1%
#6310
0%
#6320
b1 0
1%
#6330
0%
#6340
b10 0
1%
#6350
0%
#6360
b11 0
1%
#6370
0%
#6380
b100 0
1%
#6390
0%
#6400
b10 3
1#
b110 .
0"
b0 0
1%
#6410
0%
#6420
b1 0
1%
#6430
0%
#6440
b10 0
1%
#6450
0%
#6460
b11 0
1%
#6470
0%
#6480
b100 0
1%
#6490
0%
#6500
b1011001 9
b11 3
b0 0
1"
1%
#6510
0%
#6520
b1 0
1%
#6530
0%
#6540
b10 0
1%
#6550
0%
#6560
b11 0
1%
#6570
0%
#6580
b100 0
1%
#6590
0%
#6600
b10 3
b101 .
0"
b0 0
1%
#6610
0%
#6620
b1 0
1%
#6630
0%
#6640
b10 0
1%
#6650
0%
#6660
b11 0
1%
#6670
0%
#6680
b100 0
1%
#6690
0%
#6700
b10110011 9
b11 3
b0 0
1"
1%
#6710
0%
#6720
b1 0
1%
#6730
0%
#6740
b10 0
1%
#6750
0%
#6760
b11 0
1%
#6770
0%
#6780
b100 0
1%
#6790
0%
#6800
b10 3
b100 .
0"
b0 0
1%
#6810
0%
#6820
b1 0
1%
#6830
0%
#6840
b10 0
1%
#6850
0%
#6860
b11 0
1%
#6870
0%
#6880
b100 0
1%
#6890
0%
#6900
b1100111 9
b11 3
b0 0
1"
1%
#6910
0%
#6920
b1 0
1%
#6930
0%
#6940
b10 0
1%
#6950
0%
#6960
b11 0
1%
#6970
0%
#6980
b100 0
1%
#6990
0%
#7000
b10 3
b11 .
0"
b0 0
1%
#7010
0%
#7020
b1 0
1%
#7030
0%
#7040
b10 0
1%
#7050
0%
#7060
b11 0
1%
#7070
0%
#7080
b100 0
1%
#7090
0%
#7100
b11001111 9
b11 3
b0 0
1"
1%
#7110
0%
#7120
b1 0
1%
#7130
0%
#7140
b10 0
1%
#7150
0%
#7160
b11 0
1%
#7170
0%
#7180
b100 0
1%
#7190
0%
#7200
b10 3
0#
b10 .
0"
b0 0
1%
#7210
0%
#7220
b1 0
1%
#7230
0%
#7240
b10 0
1%
#7250
0%
#7260
b11 0
1%
#7270
0%
#7280
b100 0
1%
#7290
0%
#7300
b10011110 9
b11 3
b0 0
1"
1%
#7310
0%
#7320
b1 0
1%
#7330
0%
#7340
b10 0
1%
#7350
0%
#7360
b11 0
1%
#7370
0%
#7380
b100 0
1%
#7390
0%
#7400
b10 3
b1 .
0"
b0 0
1%
#7410
0%
#7420
b1 0
1%
#7430
0%
#7440
b10 0
1%
#7450
0%
#7460
b11 0
1%
#7470
0%
#7480
b100 0
1%
#7490
0%
#7500
b111100 9
b11 3
b0 0
1"
1%
#7510
0%
#7520
b1 0
1%
#7530
0%
#7540
b10 0
1%
#7550
0%
#7560
b11 0
1%
#7570
0%
#7580
b100 0
1%
#7590
0%
#7600
b10 3
b0 .
0"
b0 0
1%
#7610
0%
#7620
b1 0
1%
#7630
0%
#7640
b10 0
1%
#7650
0%
#7660
b11 0
1%
#7670
0%
#7680
b100 0
1%
#7690
0%
#7700
b1111000 9
b11 3
b0 0
1"
1%
#7710
0%
#7720
b1 0
1%
#7730
0%
#7740
b10 0
1%
#7750
0%
#7760
b11 0
1%
#7770
0%
#7780
b100 0
1%
#7790
0%
#7800
b1111000 8
b101 3
1$
0"
b0 0
1%
