packs/counter-lab/src/counter.v
// SPDX-License-Identifier: CC-BY-4.0
// Copyright (c) 2026 Ferrite Engineering
//
// 8-bit synchronous up-counter with active-low reset, clock enable, and
// combinational overflow strobe. Intended as the very first lab in the
// WaveCrux EDU Learning Pack catalog — minimal yet exercising every
// signal-display surface a student will use later.

`timescale 1ns / 1ns

module counter (
    input  wire       clk,
    input  wire       rst_n,
    input  wire       enable,
    output reg  [7:0] count,
    output wire       overflow
);
    always @(posedge clk or negedge rst_n) begin
        if (!rst_n)        count <= 8'd0;
        else if (enable)   count <= count + 8'd1;
    end

    // High for one clock cycle each time the counter is parked at 0xFF
    // with the enable asserted (i.e. the cycle in which it is about to
    // wrap to zero).
    assign overflow = enable && (count == 8'hFF);
endmodule

packs/counter-lab/tb/tb_counter.v
// SPDX-License-Identifier: CC-BY-4.0
// Copyright (c) 2026 Ferrite Engineering
//
// Testbench for the 8-bit synchronous counter.
//
// Clock convention: `clk` starts at 1 and toggles every 5 ns, so the
// first posedge is at t=10 ns and subsequent posedges land on every
// multiple of 10 ns (10, 20, 30, ...). This gives clean, pedagogical
// numbers in the waveform — students can read transition times directly
// off the cursor.
//
// Timing:
//   * Reset (`rst_n`) is held low from t=0 through t=22 ns. The posedge
//     at t=20 still sees rst_n=0, so the first increment happens at the
//     posedge at t=30. That places `count = 8'h01` at t=30, `count =
//     8'h80` at t=1300, `count = 8'hFF` at t=2570, and the rollover to
//     `count = 8'h00` at t=2580.
//   * Enable goes high at t=22 alongside reset release.
//   * Simulation finishes at t=3000 ns so the rollover and the
//     overflow strobe are clearly bracketed in the waveform.

`timescale 1ns / 1ns

module tb_counter;
    reg        clk;
    reg        rst_n;
    reg        enable;
    wire [7:0] count;
    wire       overflow;

    counter dut (
        .clk     (clk),
        .rst_n   (rst_n),
        .enable  (enable),
        .count   (count),
        .overflow(overflow)
    );

    // 100 MHz: 10 ns period, posedges at 10, 20, 30, ...
    initial clk = 1'b1;
    always #5 clk = ~clk;

    initial begin
        $dumpfile("fixtures/reference.vcd");
        $dumpvars(0, tb_counter);

        rst_n  = 1'b0;
        enable = 1'b0;

        #22;          // hold reset for 22 ns; reset releases at t=22
        rst_n  = 1'b1;
        enable = 1'b1;

        #2978;        // bring the total run length to 3000 ns
        $finish;
    end
endmodule

packs/counter-lab/fixtures/reference.vcd
$date
	Sun May 31 14:23:38 2026
$end
$version
	Icarus Verilog
$end
$timescale
	1ns
$end
$scope module tb_counter $end
$var wire 1 ! overflow $end
$var wire 8 " count [7:0] $end
$var reg 1 # clk $end
$var reg 1 $ enable $end
$var reg 1 % rst_n $end
$scope module dut $end
$var wire 1 # clk $end
$var wire 1 $ enable $end
$var wire 1 ! overflow $end
$var wire 1 % rst_n $end
$var reg 8 & count [7:0] $end
$upscope $end
$upscope $end
$enddefinitions $end
$comment Show the parameter values. $end
$dumpall
$end
#0
$dumpvars
b0 &
0%
0$
1#
b0 "
0!
$end
#5
0#
#10
1#
#15
0#
#20
1#
#22
1$
1%
#25
0#
#30
b1 "
b1 &
1#
#35
0#
#40
b10 "
b10 &
1#
#45
0#
#50
b11 "
b11 &
1#
#55
0#
#60
b100 "
b100 &
1#
#65
0#
#70
b101 "
b101 &
1#
#75
0#
#80
b110 "
b110 &
1#
#85
0#
#90
b111 "
b111 &
1#
#95
0#
#100
b1000 "
b1000 &
1#
#105
0#
#110
b1001 "
b1001 &
1#
#115
0#
#120
b1010 "
b1010 &
1#
#125
0#
#130
b1011 "
b1011 &
1#
#135
0#
#140
b1100 "
b1100 &
1#
#145
0#
#150
b1101 "
b1101 &
1#
#155
0#
#160
b1110 "
b1110 &
1#
#165
0#
#170
b1111 "
b1111 &
1#
#175
0#
#180
b10000 "
b10000 &
1#
#185
0#
#190
b10001 "
b10001 &
1#
#195
0#
#200
b10010 "
b10010 &
1#
#205
0#
#210
b10011 "
b10011 &
1#
#215
0#
#220
b10100 "
b10100 &
1#
#225
0#
#230
b10101 "
b10101 &
1#
#235
0#
#240
b10110 "
b10110 &
1#
#245
0#
#250
b10111 "
b10111 &
1#
#255
0#
#260
b11000 "
b11000 &
1#
#265
0#
#270
b11001 "
b11001 &
1#
#275
0#
#280
b11010 "
b11010 &
1#
#285
0#
#290
b11011 "
b11011 &
1#
#295
0#
#300
b11100 "
b11100 &
1#
#305
0#
#310
b11101 "
b11101 &
1#
#315
0#
#320
b11110 "
b11110 &
1#
#325
0#
#330
b11111 "
b11111 &
1#
#335
0#
#340
b100000 "
b100000 &
1#
#345
0#
#350
b100001 "
b100001 &
1#
#355
0#
#360
b100010 "
b100010 &
1#
#365
0#
#370
b100011 "
b100011 &
1#
#375
0#
#380
b100100 "
b100100 &
1#
#385
0#
#390
b100101 "
b100101 &
1#
#395
0#
#400
b100110 "
b100110 &
1#
#405
0#
#410
b100111 "
b100111 &
1#
#415
0#
#420
b101000 "
b101000 &
1#
#425
0#
#430
b101001 "
b101001 &
1#
#435
0#
#440
b101010 "
b101010 &
1#
#445
0#
#450
b101011 "
b101011 &
1#
#455
0#
#460
b101100 "
b101100 &
1#
#465
0#
#470
b101101 "
b101101 &
1#
#475
0#
#480
b101110 "
b101110 &
1#
#485
0#
#490
b101111 "
b101111 &
1#
#495
0#
#500
b110000 "
b110000 &
1#
#505
0#
#510
b110001 "
b110001 &
1#
#515
0#
#520
b110010 "
b110010 &
1#
#525
0#
#530
b110011 "
b110011 &
1#
#535
0#
#540
b110100 "
b110100 &
1#
#545
0#
#550
b110101 "
b110101 &
1#
#555
0#
#560
b110110 "
b110110 &
1#
#565
0#
#570
b110111 "
b110111 &
1#
#575
0#
#580
b111000 "
b111000 &
1#
#585
0#
#590
b111001 "
b111001 &
1#
#595
0#
#600
b111010 "
b111010 &
1#
#605
0#
#610
b111011 "
b111011 &
1#
#615
0#
#620
b111100 "
b111100 &
1#
#625
0#
#630
b111101 "
b111101 &
1#
#635
0#
#640
b111110 "
b111110 &
1#
#645
0#
#650
b111111 "
b111111 &
1#
#655
0#
#660
b1000000 "
b1000000 &
1#
#665
0#
#670
b1000001 "
b1000001 &
1#
#675
0#
#680
b1000010 "
b1000010 &
1#
#685
0#
#690
b1000011 "
b1000011 &
1#
#695
0#
#700
b1000100 "
b1000100 &
1#
#705
0#
#710
b1000101 "
b1000101 &
1#
#715
0#
#720
b1000110 "
b1000110 &
1#
#725
0#
#730
b1000111 "
b1000111 &
1#
#735
0#
#740
b1001000 "
b1001000 &
1#
#745
0#
#750
b1001001 "
b1001001 &
1#
#755
0#
#760
b1001010 "
b1001010 &
1#
#765
0#
#770
b1001011 "
b1001011 &
1#
#775
0#
#780
b1001100 "
b1001100 &
1#
#785
0#
#790
b1001101 "
b1001101 &
1#
#795
0#
#800
b1001110 "
b1001110 &
1#
#805
0#
#810
b1001111 "
b1001111 &
1#
#815
0#
#820
b1010000 "
b1010000 &
1#
#825
0#
#830
b1010001 "
b1010001 &
1#
#835
0#
#840
b1010010 "
b1010010 &
1#
#845
0#
#850
b1010011 "
b1010011 &
1#
#855
0#
#860
b1010100 "
b1010100 &
1#
#865
0#
#870
b1010101 "
b1010101 &
1#
#875
0#
#880
b1010110 "
b1010110 &
1#
#885
0#
#890
b1010111 "
b1010111 &
1#
#895
0#
#900
b1011000 "
b1011000 &
1#
#905
0#
#910
b1011001 "
b1011001 &
1#
#915
0#
#920
b1011010 "
b1011010 &
1#
#925
0#
#930
b1011011 "
b1011011 &
1#
#935
0#
#940
b1011100 "
b1011100 &
1#
#945
0#
#950
b1011101 "
b1011101 &
1#
#955
0#
#960
b1011110 "
b1011110 &
1#
#965
0#
#970
b1011111 "
b1011111 &
1#
#975
0#
#980
b1100000 "
b1100000 &
1#
#985
0#
#990
b1100001 "
b1100001 &
1#
#995
0#
#1000
b1100010 "
b1100010 &
1#
#1005
0#
#1010
b1100011 "
b1100011 &
1#
#1015
0#
#1020
b1100100 "
b1100100 &
1#
#1025
0#
#1030
b1100101 "
b1100101 &
1#
#1035
0#
#1040
b1100110 "
b1100110 &
1#
#1045
0#
#1050
b1100111 "
b1100111 &
1#
#1055
0#
#1060
b1101000 "
b1101000 &
1#
#1065
0#
#1070
b1101001 "
b1101001 &
1#
#1075
0#
#1080
b1101010 "
b1101010 &
1#
#1085
0#
#1090
b1101011 "
b1101011 &
1#
#1095
0#
#1100
b1101100 "
b1101100 &
1#
#1105
0#
#1110
b1101101 "
b1101101 &
1#
#1115
0#
#1120
b1101110 "
b1101110 &
1#
#1125
0#
#1130
b1101111 "
b1101111 &
1#
#1135
0#
#1140
b1110000 "
b1110000 &
1#
#1145
0#
#1150
b1110001 "
b1110001 &
1#
#1155
0#
#1160
b1110010 "
b1110010 &
1#
#1165
0#
#1170
b1110011 "
b1110011 &
1#
#1175
0#
#1180
b1110100 "
b1110100 &
1#
#1185
0#
#1190
b1110101 "
b1110101 &
1#
#1195
0#
#1200
b1110110 "
b1110110 &
1#
#1205
0#
#1210
b1110111 "
b1110111 &
1#
#1215
0#
#1220
b1111000 "
b1111000 &
1#
#1225
0#
#1230
b1111001 "
b1111001 &
1#
#1235
0#
#1240
b1111010 "
b1111010 &
1#
#1245
0#
#1250
b1111011 "
b1111011 &
1#
#1255
0#
#1260
b1111100 "
b1111100 &
1#
#1265
0#
#1270
b1111101 "
b1111101 &
1#
#1275
0#
#1280
b1111110 "
b1111110 &
1#
#1285
0#
#1290
b1111111 "
b1111111 &
1#
#1295
0#
#1300
b10000000 "
b10000000 &
1#
#1305
0#
#1310
b10000001 "
b10000001 &
1#
#1315
0#
#1320
b10000010 "
b10000010 &
1#
#1325
0#
#1330
b10000011 "
b10000011 &
1#
#1335
0#
#1340
b10000100 "
b10000100 &
1#
#1345
0#
#1350
b10000101 "
b10000101 &
1#
#1355
0#
#1360
b10000110 "
b10000110 &
1#
#1365
0#
#1370
b10000111 "
b10000111 &
1#
#1375
0#
#1380
b10001000 "
b10001000 &
1#
#1385
0#
#1390
b10001001 "
b10001001 &
1#
#1395
0#
#1400
b10001010 "
b10001010 &
1#
#1405
0#
#1410
b10001011 "
b10001011 &
1#
#1415
0#
#1420
b10001100 "
b10001100 &
1#
#1425
0#
#1430
b10001101 "
b10001101 &
1#
#1435
0#
#1440
b10001110 "
b10001110 &
1#
#1445
0#
#1450
b10001111 "
b10001111 &
1#
#1455
0#
#1460
b10010000 "
b10010000 &
1#
#1465
0#
#1470
b10010001 "
b10010001 &
1#
#1475
0#
#1480
b10010010 "
b10010010 &
1#
#1485
0#
#1490
b10010011 "
b10010011 &
1#
#1495
0#
#1500
b10010100 "
b10010100 &
1#
#1505
0#
#1510
b10010101 "
b10010101 &
1#
#1515
0#
#1520
b10010110 "
b10010110 &
1#
#1525
0#
#1530
b10010111 "
b10010111 &
1#
#1535
0#
#1540
b10011000 "
b10011000 &
1#
#1545
0#
#1550
b10011001 "
b10011001 &
1#
#1555
0#
#1560
b10011010 "
b10011010 &
1#
#1565
0#
#1570
b10011011 "
b10011011 &
1#
#1575
0#
#1580
b10011100 "
b10011100 &
1#
#1585
0#
#1590
b10011101 "
b10011101 &
1#
#1595
0#
#1600
b10011110 "
b10011110 &
1#
#1605
0#
#1610
b10011111 "
b10011111 &
1#
#1615
0#
#1620
b10100000 "
b10100000 &
1#
#1625
0#
#1630
b10100001 "
b10100001 &
1#
#1635
0#
#1640
b10100010 "
b10100010 &
1#
#1645
0#
#1650
b10100011 "
b10100011 &
1#
#1655
0#
#1660
b10100100 "
b10100100 &
1#
#1665
0#
#1670
b10100101 "
b10100101 &
1#
#1675
0#
#1680
b10100110 "
b10100110 &
1#
#1685
0#
#1690
b10100111 "
b10100111 &
1#
#1695
0#
#1700
b10101000 "
b10101000 &
1#
#1705
0#
#1710
b10101001 "
b10101001 &
1#
#1715
0#
#1720
b10101010 "
b10101010 &
1#
#1725
0#
#1730
b10101011 "
b10101011 &
1#
#1735
0#
#1740
b10101100 "
b10101100 &
1#
#1745
0#
#1750
b10101101 "
b10101101 &
1#
#1755
0#
#1760
b10101110 "
b10101110 &
1#
#1765
0#
#1770
b10101111 "
b10101111 &
1#
#1775
0#
#1780
b10110000 "
b10110000 &
1#
#1785
0#
#1790
b10110001 "
b10110001 &
1#
#1795
0#
#1800
b10110010 "
b10110010 &
1#
#1805
0#
#1810
b10110011 "
b10110011 &
1#
#1815
0#
#1820
b10110100 "
b10110100 &
1#
#1825
0#
#1830
b10110101 "
b10110101 &
1#
#1835
0#
#1840
b10110110 "
b10110110 &
1#
#1845
0#
#1850
b10110111 "
b10110111 &
1#
#1855
0#
#1860
b10111000 "
b10111000 &
1#
#1865
0#
#1870
b10111001 "
b10111001 &
1#
#1875
0#
#1880
b10111010 "
b10111010 &
1#
#1885
0#
#1890
b10111011 "
b10111011 &
1#
#1895
0#
#1900
b10111100 "
b10111100 &
1#
#1905
0#
#1910
b10111101 "
b10111101 &
1#
#1915
0#
#1920
b10111110 "
b10111110 &
1#
#1925
0#
#1930
b10111111 "
b10111111 &
1#
#1935
0#
#1940
b11000000 "
b11000000 &
1#
#1945
0#
#1950
b11000001 "
b11000001 &
1#
#1955
0#
#1960
b11000010 "
b11000010 &
1#
#1965
0#
#1970
b11000011 "
b11000011 &
1#
#1975
0#
#1980
b11000100 "
b11000100 &
1#
#1985
0#
#1990
b11000101 "
b11000101 &
1#
#1995
0#
#2000
b11000110 "
b11000110 &
1#
#2005
0#
#2010
b11000111 "
b11000111 &
1#
#2015
0#
#2020
b11001000 "
b11001000 &
1#
#2025
0#
#2030
b11001001 "
b11001001 &
1#
#2035
0#
#2040
b11001010 "
b11001010 &
1#
#2045
0#
#2050
b11001011 "
b11001011 &
1#
#2055
0#
#2060
b11001100 "
b11001100 &
1#
#2065
0#
#2070
b11001101 "
b11001101 &
1#
#2075
0#
#2080
b11001110 "
b11001110 &
1#
#2085
0#
#2090
b11001111 "
b11001111 &
1#
#2095
0#
#2100
b11010000 "
b11010000 &
1#
#2105
0#
#2110
b11010001 "
b11010001 &
1#
#2115
0#
#2120
b11010010 "
b11010010 &
1#
#2125
0#
#2130
b11010011 "
b11010011 &
1#
#2135
0#
#2140
b11010100 "
b11010100 &
1#
#2145
0#
#2150
b11010101 "
b11010101 &
1#
#2155
0#
#2160
b11010110 "
b11010110 &
1#
#2165
0#
#2170
b11010111 "
b11010111 &
1#
#2175
0#
#2180
b11011000 "
b11011000 &
1#
#2185
0#
#2190
b11011001 "
b11011001 &
1#
#2195
0#
#2200
b11011010 "
b11011010 &
1#
#2205
0#
#2210
b11011011 "
b11011011 &
1#
#2215
0#
#2220
b11011100 "
b11011100 &
1#
#2225
0#
#2230
b11011101 "
b11011101 &
1#
#2235
0#
#2240
b11011110 "
b11011110 &
1#
#2245
0#
#2250
b11011111 "
b11011111 &
1#
#2255
0#
#2260
b11100000 "
b11100000 &
1#
#2265
0#
#2270
b11100001 "
b11100001 &
1#
#2275
0#
#2280
b11100010 "
b11100010 &
1#
#2285
0#
#2290
b11100011 "
b11100011 &
1#
#2295
0#
#2300
b11100100 "
b11100100 &
1#
#2305
0#
#2310
b11100101 "
b11100101 &
1#
#2315
0#
#2320
b11100110 "
b11100110 &
1#
#2325
0#
#2330
b11100111 "
b11100111 &
1#
#2335
0#
#2340
b11101000 "
b11101000 &
1#
#2345
0#
#2350
b11101001 "
b11101001 &
1#
#2355
0#
#2360
b11101010 "
b11101010 &
1#
#2365
0#
#2370
b11101011 "
b11101011 &
1#
#2375
0#
#2380
b11101100 "
b11101100 &
1#
#2385
0#
#2390
b11101101 "
b11101101 &
1#
#2395
0#
#2400
b11101110 "
b11101110 &
1#
#2405
0#
#2410
b11101111 "
b11101111 &
1#
#2415
0#
#2420
b11110000 "
b11110000 &
1#
#2425
0#
#2430
b11110001 "
b11110001 &
1#
#2435
0#
#2440
b11110010 "
b11110010 &
1#
#2445
0#
#2450
b11110011 "
b11110011 &
1#
#2455
0#
#2460
b11110100 "
b11110100 &
1#
#2465
0#
#2470
b11110101 "
b11110101 &
1#
#2475
0#
#2480
b11110110 "
b11110110 &
1#
#2485
0#
#2490
b11110111 "
b11110111 &
1#
#2495
0#
#2500
b11111000 "
b11111000 &
1#
#2505
0#
#2510
b11111001 "
b11111001 &
1#
#2515
0#
#2520
b11111010 "
b11111010 &
1#
#2525
0#
#2530
b11111011 "
b11111011 &
1#
#2535
0#
#2540
b11111100 "
b11111100 &
1#
#2545
0#
#2550
b11111101 "
b11111101 &
1#
#2555
0#
#2560
b11111110 "
b11111110 &
1#
#2565
0#
#2570
1!
b11111111 "
b11111111 &
1#
#2575
0#
#2580
0!
b0 "
b0 &
1#
#2585
0#
#2590
b1 "
b1 &
1#
#2595
0#
#2600
b10 "
b10 &
1#
#2605
0#
#2610
b11 "
b11 &
1#
#2615
0#
#2620
b100 "
b100 &
1#
#2625
0#
#2630
b101 "
b101 &
1#
#2635
0#
#2640
b110 "
b110 &
1#
#2645
0#
#2650
b111 "
b111 &
1#
#2655
0#
#2660
b1000 "
b1000 &
1#
#2665
0#
#2670
b1001 "
b1001 &
1#
#2675
0#
#2680
b1010 "
b1010 &
1#
#2685
0#
#2690
b1011 "
b1011 &
1#
#2695
0#
#2700
b1100 "
b1100 &
1#
#2705
0#
#2710
b1101 "
b1101 &
1#
#2715
0#
#2720
b1110 "
b1110 &
1#
#2725
0#
#2730
b1111 "
b1111 &
1#
#2735
0#
#2740
b10000 "
b10000 &
1#
#2745
0#
#2750
b10001 "
b10001 &
1#
#2755
0#
#2760
b10010 "
b10010 &
1#
#2765
0#
#2770
b10011 "
b10011 &
1#
#2775
0#
#2780
b10100 "
b10100 &
1#
#2785
0#
#2790
b10101 "
b10101 &
1#
#2795
0#
#2800
b10110 "
b10110 &
1#
#2805
0#
#2810
b10111 "
b10111 &
1#
#2815
0#
#2820
b11000 "
b11000 &
1#
#2825
0#
#2830
b11001 "
b11001 &
1#
#2835
0#
#2840
b11010 "
b11010 &
1#
#2845
0#
#2850
b11011 "
b11011 &
1#
#2855
0#
#2860
b11100 "
b11100 &
1#
#2865
0#
#2870
b11101 "
b11101 &
1#
#2875
0#
#2880
b11110 "
b11110 &
1#
#2885
0#
#2890
b11111 "
b11111 &
1#
#2895
0#
#2900
b100000 "
b100000 &
1#
#2905
0#
#2910
b100001 "
b100001 &
1#
#2915
0#
#2920
b100010 "
b100010 &
1#
#2925
0#
#2930
b100011 "
b100011 &
1#
#2935
0#
#2940
b100100 "
b100100 &
1#
#2945
0#
#2950
b100101 "
b100101 &
1#
#2955
0#
#2960
b100110 "
b100110 &
1#
#2965
0#
#2970
b100111 "
b100111 &
1#
#2975
0#
#2980
b101000 "
b101000 &
1#
#2985
0#
#2990
b101001 "
b101001 &
1#
#2995
0#
#3000
b101010 "
b101010 &
1#
