packs/single-cycle-cpu/src/regfile.v
// SPDX-License-Identifier: CC-BY-4.0
// Copyright (c) 2026 Ferrite Engineering
//
// 32-entry x 32-bit register file with two asynchronous read ports
// and one synchronous write port. Register x0 is hard-wired to zero.

`timescale 1ns / 1ns

module regfile (
    input  wire        clk,
    input  wire        we,
    input  wire [ 4:0] rd_addr,
    input  wire [31:0] rd_data,
    input  wire [ 4:0] rs1_addr,
    output wire [31:0] rs1_data,
    input  wire [ 4:0] rs2_addr,
    output wire [31:0] rs2_data
);
    reg [31:0] regs [0:31];

    assign rs1_data = (rs1_addr == 5'd0) ? 32'h0 : regs[rs1_addr];
    assign rs2_data = (rs2_addr == 5'd0) ? 32'h0 : regs[rs2_addr];

    integer i;
    initial for (i = 0; i < 32; i = i + 1) regs[i] = 32'h0;

    always @(posedge clk) begin
        if (we && rd_addr != 5'd0) begin
            regs[rd_addr] <= rd_data;
        end
    end
endmodule

packs/single-cycle-cpu/src/imem.v
// SPDX-License-Identifier: CC-BY-4.0
// Copyright (c) 2026 Ferrite Engineering
//
// Read-only instruction memory. 64 words deep (256 bytes); contents
// loaded from `program.hex` at simulation start. Address is byte-
// addressed but only word-aligned access is honoured (lower two bits
// ignored).

`timescale 1ns / 1ns

module imem (
    input  wire [31:0] addr,
    output wire [31:0] instr
);
    reg [31:0] mem [0:63];
    initial $readmemh("src/program.hex", mem);
    assign instr = mem[addr[7:2]];
endmodule

packs/single-cycle-cpu/src/rv32_cpu.v
// SPDX-License-Identifier: CC-BY-4.0
// Copyright (c) 2026 Ferrite Engineering
//
// Single-cycle RV32I core. Supported instructions:
//   * ADDI, ADD, SUB   -- arithmetic / register ops
//   * LW,   SW         -- 32-bit word load / store
//   * BEQ              -- conditional branch
//   * JAL              -- unconditional jump-and-link
//
// All other opcodes execute as NOPs (no register write, PC advances by
// 4). Intended for visualization, not synthesis.

`timescale 1ns / 1ns

module rv32_cpu (
    input  wire        clk,
    input  wire        rst,
    output reg  [31:0] pc,
    output wire [31:0] instr
);
    // ── Instruction fetch ────────────────────────────────────────────
    imem u_imem (.addr(pc), .instr(instr));

    // ── Decode ──────────────────────────────────────────────────────
    wire [ 6:0] opcode = instr[ 6: 0];
    wire [ 4:0] rd     = instr[11: 7];
    wire [ 2:0] funct3 = instr[14:12];
    wire [ 4:0] rs1    = instr[19:15];
    wire [ 4:0] rs2    = instr[24:20];
    wire [ 6:0] funct7 = instr[31:25];

    localparam [6:0] OP_RTYPE  = 7'b0110011;
    localparam [6:0] OP_ITYPE  = 7'b0010011;
    localparam [6:0] OP_LOAD   = 7'b0000011;
    localparam [6:0] OP_STORE  = 7'b0100011;
    localparam [6:0] OP_BRANCH = 7'b1100011;
    localparam [6:0] OP_JAL    = 7'b1101111;

    wire [31:0] imm_i = {{20{instr[31]}}, instr[31:20]};
    wire [31:0] imm_s = {{20{instr[31]}}, instr[31:25], instr[11:7]};
    wire [31:0] imm_b = {{19{instr[31]}}, instr[31], instr[7],
                         instr[30:25], instr[11:8], 1'b0};
    wire [31:0] imm_j = {{11{instr[31]}}, instr[31], instr[19:12],
                         instr[20], instr[30:21], 1'b0};

    // ── Register file ────────────────────────────────────────────────
    wire [31:0] rs1_val;
    wire [31:0] rs2_val;
    reg         rf_we;
    reg  [31:0] rf_wdata;

    regfile u_regfile (
        .clk     (clk),
        .we      (rf_we),
        .rd_addr (rd),
        .rd_data (rf_wdata),
        .rs1_addr(rs1),
        .rs1_data(rs1_val),
        .rs2_addr(rs2),
        .rs2_data(rs2_val)
    );

    // ── ALU ──────────────────────────────────────────────────────────
    reg [31:0] alu_out;
    always @(*) begin
        case (opcode)
            OP_RTYPE: alu_out = funct7[5] ? (rs1_val - rs2_val)
                                          : (rs1_val + rs2_val);
            OP_ITYPE: alu_out = rs1_val + imm_i;
            OP_LOAD:  alu_out = rs1_val + imm_i;
            OP_STORE: alu_out = rs1_val + imm_s;
            default:  alu_out = 32'h0;
        endcase
    end

    // ── Data memory ─────────────────────────────────────────────────
    reg [31:0] dmem [0:31];
    wire [4:0] dmem_idx = alu_out[6:2];

    // ── Branch / next-PC ────────────────────────────────────────────
    wire branch_taken = (opcode == OP_BRANCH) &&
                        (funct3 == 3'b000) &&
                        (rs1_val == rs2_val);

    wire [31:0] pc_next = (opcode == OP_JAL) ? (pc + imm_j) :
                          branch_taken       ? (pc + imm_b) :
                                               (pc + 32'd4);

    // ── Writeback control ───────────────────────────────────────────
    always @(*) begin
        rf_we    = 1'b0;
        rf_wdata = 32'h0;
        case (opcode)
            OP_RTYPE, OP_ITYPE: begin
                rf_we    = 1'b1;
                rf_wdata = alu_out;
            end
            OP_LOAD: begin
                rf_we    = 1'b1;
                rf_wdata = dmem[dmem_idx];
            end
            OP_JAL: begin
                rf_we    = 1'b1;
                rf_wdata = pc + 32'd4;
            end
            default: ;
        endcase
    end

    // ── Sequential: PC, store ───────────────────────────────────────
    integer i;
    always @(posedge clk) begin
        if (rst) begin
            pc <= 32'h0;
            for (i = 0; i < 32; i = i + 1) dmem[i] <= 32'h0;
        end else begin
            pc <= pc_next;
            if (opcode == OP_STORE && funct3 == 3'b010) begin
                dmem[dmem_idx] <= rs2_val;
            end
        end
    end
endmodule

packs/single-cycle-cpu/tb/tb_rv32_cpu.v
// SPDX-License-Identifier: CC-BY-4.0
// Copyright (c) 2026 Ferrite Engineering
//
// Runs the single-cycle CPU through its 15-instruction program. 100
// MHz clock; 500 ns simulation gives ~50 instruction cycles, more
// than enough to settle into the JAL self-loop at the end of the
// program.

`timescale 1ns / 1ns

module tb_rv32_cpu;
    reg         clk;
    reg         rst;
    wire [31:0] pc;
    wire [31:0] instr;

    rv32_cpu dut (
        .clk  (clk),
        .rst  (rst),
        .pc   (pc),
        .instr(instr)
    );

    integer dump_i;

    initial clk = 1'b1;
    always #5 clk = ~clk;

    initial begin
        $dumpfile("fixtures/reference.vcd");
        $dumpvars(0, tb_rv32_cpu);
        // Array elements are NOT covered by $dumpvars(0, ...) — the VCD format
        // has no array type, so Icarus only emits a memory word when it is
        // named explicitly. The lab's checkpoints inspect architectural
        // register and data-memory state, so every word the handout refers to
        // has to be listed here or it simply will not be in the waveform the
        // student opens.
        for (dump_i = 1; dump_i <= 11; dump_i = dump_i + 1)
            $dumpvars(0, dut.u_regfile.regs[dump_i]);
        $dumpvars(0, dut.dmem[0]);
        $dumpvars(0, dut.dmem[1]);

        rst = 1'b1;
        #22;
        rst = 1'b0;
        #478;
        $finish;
    end
endmodule

packs/single-cycle-cpu/fixtures/reference.vcd
$date
	Fri Jul 24 11:42:52 2026
$end
$version
	Icarus Verilog
$end
$timescale
	1ns
$end
$scope module tb_rv32_cpu $end
$var wire 32 ! pc [31:0] $end
$var wire 32 " instr [31:0] $end
$var reg 1 # clk $end
$var reg 1 $ rst $end
$var integer 32 % dump_i [31:0] $end
$scope module dut $end
$var wire 1 & branch_taken $end
$var wire 1 # clk $end
$var wire 1 $ rst $end
$var wire 32 ' rs2_val [31:0] $end
$var wire 5 ( rs2 [4:0] $end
$var wire 32 ) rs1_val [31:0] $end
$var wire 5 * rs1 [4:0] $end
$var wire 5 + rd [4:0] $end
$var wire 32 , pc_next [31:0] $end
$var wire 7 - opcode [6:0] $end
$var wire 32 . instr [31:0] $end
$var wire 32 / imm_s [31:0] $end
$var wire 32 0 imm_j [31:0] $end
$var wire 32 1 imm_i [31:0] $end
$var wire 32 2 imm_b [31:0] $end
$var wire 7 3 funct7 [6:0] $end
$var wire 3 4 funct3 [2:0] $end
$var wire 5 5 dmem_idx [4:0] $end
$var parameter 7 6 OP_BRANCH $end
$var parameter 7 7 OP_ITYPE $end
$var parameter 7 8 OP_JAL $end
$var parameter 7 9 OP_LOAD $end
$var parameter 7 : OP_RTYPE $end
$var parameter 7 ; OP_STORE $end
$var reg 32 < alu_out [31:0] $end
$var reg 32 = pc [31:0] $end
$var reg 32 > rf_wdata [31:0] $end
$var reg 1 ? rf_we $end
$var integer 32 @ i [31:0] $end
$scope module u_imem $end
$var wire 32 A addr [31:0] $end
$var wire 32 B instr [31:0] $end
$upscope $end
$scope module u_regfile $end
$var wire 1 # clk $end
$var wire 5 C rd_addr [4:0] $end
$var wire 32 D rd_data [31:0] $end
$var wire 5 E rs1_addr [4:0] $end
$var wire 5 F rs2_addr [4:0] $end
$var wire 1 ? we $end
$var wire 32 G rs2_data [31:0] $end
$var wire 32 H rs1_data [31:0] $end
$var integer 32 I i [31:0] $end
$upscope $end
$upscope $end
$upscope $end
$scope module tb_rv32_cpu $end
$scope module dut $end
$scope module u_regfile $end
$var reg 32 J \regs[1] [31:0] $end
$upscope $end
$upscope $end
$upscope $end
$scope module tb_rv32_cpu $end
$scope module dut $end
$scope module u_regfile $end
$var reg 32 K \regs[2] [31:0] $end
$upscope $end
$upscope $end
$upscope $end
$scope module tb_rv32_cpu $end
$scope module dut $end
$scope module u_regfile $end
$var reg 32 L \regs[3] [31:0] $end
$upscope $end
$upscope $end
$upscope $end
$scope module tb_rv32_cpu $end
$scope module dut $end
$scope module u_regfile $end
$var reg 32 M \regs[4] [31:0] $end
$upscope $end
$upscope $end
$upscope $end
$scope module tb_rv32_cpu $end
$scope module dut $end
$scope module u_regfile $end
$var reg 32 N \regs[5] [31:0] $end
$upscope $end
$upscope $end
$upscope $end
$scope module tb_rv32_cpu $end
$scope module dut $end
$scope module u_regfile $end
$var reg 32 O \regs[6] [31:0] $end
$upscope $end
$upscope $end
$upscope $end
$scope module tb_rv32_cpu $end
$scope module dut $end
$scope module u_regfile $end
$var reg 32 P \regs[7] [31:0] $end
$upscope $end
$upscope $end
$upscope $end
$scope module tb_rv32_cpu $end
$scope module dut $end
$scope module u_regfile $end
$var reg 32 Q \regs[8] [31:0] $end
$upscope $end
$upscope $end
$upscope $end
$scope module tb_rv32_cpu $end
$scope module dut $end
$scope module u_regfile $end
$var reg 32 R \regs[9] [31:0] $end
$upscope $end
$upscope $end
$upscope $end
$scope module tb_rv32_cpu $end
$scope module dut $end
$scope module u_regfile $end
$var reg 32 S \regs[10] [31:0] $end
$upscope $end
$upscope $end
$upscope $end
$scope module tb_rv32_cpu $end
$scope module dut $end
$scope module u_regfile $end
$var reg 32 T \regs[11] [31:0] $end
$upscope $end
$upscope $end
$upscope $end
$scope module tb_rv32_cpu $end
$scope module dut $end
$var reg 32 U \dmem[0] [31:0] $end
$upscope $end
$upscope $end
$scope module tb_rv32_cpu $end
$scope module dut $end
$var reg 32 V \dmem[1] [31:0] $end
$upscope $end
$upscope $end
$enddefinitions $end
$comment Show the parameter values. $end
$dumpall
b100011 ;
b110011 :
b11 9
b1101111 8
b10011 7
b1100011 6
$end
#0
$dumpvars
b0 V
b0 U
b0 T
b0 S
b0 R
b0 Q
b0 P
b0 O
b0 N
b0 M
b0 L
b0 K
b0 J
b100000 I
b0 H
b0 G
b101 F
b0 E
b101 D
b1 C
b10100000000000010010011 B
b0 A
b100000 @
1?
b101 >
b0 =
b101 <
b1 5
b0 4
b0 3
b100000000000 2
b101 1
b100000000100 0
b1 /
b10100000000000010010011 .
b10011 -
b100 ,
b1 +
b0 *
b0 )
b101 (
b0 '
0&
b1100 %
1$
1#
b10100000000000010010011 "
b0 !
$end
#5
0#
#10
b0 V
b0 U
b101 J
b100000 @
1#
#15
0#
#20
b101 J
b0 V
b0 U
b100000 @
1#
#22
0$
#25
0#
#30
b100000000110 0
b10 2
b111 <
b10 /
b111 1
b111 (
b111 F
b10 +
b10 C
b1000 ,
b11100000000000100010011 "
b11100000000000100010011 .
b11100000000000100010011 B
b111 >
b111 D
1?
b100 !
b100 =
b100 A
b101 J
1#
#35
0#
#40
b1000000000000010 0
b100000000010 2
b111 '
b111 G
b11 5
b11 /
b10 1
b101 )
b101 H
b1100 <
b10 (
b10 F
b1 *
b1 E
b11 +
b11 C
b110011 -
b1100 ,
b1000001000000110110011 "
b1000001000000110110011 .
b1000001000000110110011 B
b1100 >
b1100 D
1?
b111 K
b1000 !
b1000 =
b1000 A
1#
#45
0#
#50
b10000110000000000 0
b10000000100 2
b0 5
b101 '
b101 G
b111 )
b111 H
b10000000100 /
b10000000001 1
b10 <
b100000 3
b1 (
b1 F
b10 *
b10 E
b100 +
b100 C
b10000 ,
b1000000000100010000001000110011 "
b1000000000100010000001000110011 .
b1000000000100010000001000110011 B
b10 >
b10 D
1?
b1100 !
b1100 =
b1100 A
b1100 L
1#
#55
0#
#60
b10100000000010 0
b0 2
b1100 '
b1100 G
b0 5
b0 /
b11 1
b0 )
b0 H
b0 <
b0 3
b11 (
b11 F
b0 *
b0 E
b10 4
b0 +
b0 C
b100011 -
b10100 ,
b1100000010000000100011 "
b1100000010000000100011 .
b1100000010000000100011 B
b0 >
b0 D
0?
b10 M
b10000 !
b10000 =
b10000 A
1#
#65
0#
#70
b10000000000000 0
b100000000100 2
b101 /
b0 1
b0 '
b0 G
b1100 >
b1100 D
1?
b0 <
b0 (
b0 F
b101 +
b101 C
b11 -
b11000 ,
b10001010000011 "
b10001010000011 .
b10001010000011 B
b1100 U
b10100 !
b10100 =
b10100 A
1#
#75
0#
#80
b11000100000000100 0
b1000 2
1&
b1000 /
b101 1
b1100 '
b1100 G
b1100 )
b1100 H
b101 (
b101 F
b11 *
b11 E
b0 4
b1000 +
b1000 C
b1100011 -
b100000 ,
b10100011000010001100011 "
b10100011000010001100011 .
b10100011000010001100011 B
b0 >
b0 D
0?
b1100 N
b11000 !
b11000 =
b11000 A
1#
#85
0#
#90
b1010 0
b100000000110 2
b0 '
b0 G
0&
b10 5
b111 /
b1010 1
b0 )
b0 H
b1010 >
b1010 D
1?
b1010 <
b1010 (
b1010 F
b0 *
b0 E
b111 +
b111 C
b10011 -
b100100 ,
b101000000000001110010011 "
b101000000000001110010011 .
b101000000000001110010011 B
b100000 !
b100000 =
b100000 A
1#
#95
0#
#100
b100000001010 0
b1000 2
b1011 <
b1000 /
b1011 1
b1011 (
b1011 F
b1000 +
b1000 C
b101000 ,
b101100000000010000010011 "
b101100000000010000010011 .
b101100000000010000010011 B
b1011 >
b1011 D
1?
b1010 P
b100100 !
b100100 =
b100100 A
1#
#105
0#
#110
b111000000000001000 0
b100000001000 2
b1011 '
b1011 G
b101 5
b1001 /
b1000 1
b1010 )
b1010 H
b10101 <
b1000 (
b1000 F
b111 *
b111 E
b1001 +
b1001 C
b110011 -
b101100 ,
b100000111000010010110011 "
b100000111000010010110011 .
b100000111000010010110011 B
b10101 >
b10101 D
1?
b101000 !
b101000 =
b101000 A
b1011 Q
1#
#115
0#
#120
b1000010 0
b1001010 2
b111 '
b111 G
b10000 5
b1001010 /
b1000010 1
b0 )
b0 H
b1000010 <
b10 3
b10 (
b10 F
b0 *
b0 E
b1010 +
b1010 C
b10011 -
b110000 ,
b100001000000000010100010011 "
b100001000000000010100010011 .
b100001000000000010100010011 B
b1000010 >
b1000010 D
1?
b10101 R
b101100 !
b101100 =
b101100 A
1#
#125
0#
#130
b10000000001010 0
b100 2
b1000010 '
b1000010 G
b1 5
b100 /
b1010 1
b100 <
b0 3
b1010 (
b1010 F
b10 4
b100 +
b100 C
b100011 -
b110100 ,
b101000000010001000100011 "
b101000000010001000100011 .
b101000000010001000100011 B
b0 >
b0 D
0?
b110000 !
b110000 =
b110000 A
b1000010 S
1#
#135
0#
#140
b10000000000100 0
b100000001010 2
b10 '
b10 G
b1 5
b1011 /
b100 1
b1000010 >
b1000010 D
1?
b100 <
b100 (
b100 F
b1011 +
b1011 C
b11 -
b111000 ,
b10000000010010110000011 "
b10000000010010110000011 .
b10000000010010110000011 B
b1000010 V
b110100 !
b110100 =
b110100 A
1#
#145
0#
#150
b0 0
b0 2
b0 5
b0 /
b0 1
b0 '
b0 G
b0 <
b0 (
b0 F
b0 4
b0 +
b0 C
b1101111 -
b111000 ,
b1101111 "
b1101111 .
b1101111 B
b111100 >
b111100 D
1?
b111000 !
b111000 =
b111000 A
b1000010 T
1#
