packs/traffic-light-fsm/src/traffic_light.v
// SPDX-License-Identifier: CC-BY-4.0
// Copyright (c) 2026 Ferrite Engineering
//
// 3-state traffic-light FSM: RED -> GREEN -> YELLOW -> RED. Dwell-time
// counter holds each state for 30 cycles, so at the 100 MHz testbench
// clock each state lasts 300 ns and one full RED/GREEN/YELLOW cycle
// takes 900 ns.

`timescale 1ns / 1ns

module traffic_light (
    input  wire       clk,
    input  wire       rst_n,
    output reg  [1:0] state,
    output wire       red_light,
    output wire       green_light,
    output wire       yellow_light
);
    localparam [1:0] RED    = 2'b00;
    localparam [1:0] GREEN  = 2'b01;
    localparam [1:0] YELLOW = 2'b10;

    reg [4:0] dwell;

    always @(posedge clk or negedge rst_n) begin
        if (!rst_n) begin
            state <= RED;
            dwell <= 5'd0;
        end else if (dwell == 5'd29) begin
            dwell <= 5'd0;
            case (state)
                RED:     state <= GREEN;
                GREEN:   state <= YELLOW;
                YELLOW:  state <= RED;
                default: state <= RED;
            endcase
        end else begin
            dwell <= dwell + 5'd1;
        end
    end

    assign red_light    = (state == RED);
    assign green_light  = (state == GREEN);
    assign yellow_light = (state == YELLOW);
endmodule

packs/traffic-light-fsm/tb/tb_traffic_light.v
// SPDX-License-Identifier: CC-BY-4.0
// Copyright (c) 2026 Ferrite Engineering
//
// Testbench for the traffic-light FSM. 100 MHz clock with posedges at
// multiples of 10 ns, reset held until t=22 ns, then 3000 ns of free
// running — long enough for the FSM to make three full
// RED -> GREEN -> YELLOW -> RED cycles. Students measure the cycle
// period by placing markers on three R -> G transitions.

`timescale 1ns / 1ns

module tb_traffic_light;
    reg        clk;
    reg        rst_n;
    wire [1:0] state;
    wire       red_light;
    wire       green_light;
    wire       yellow_light;

    traffic_light dut (
        .clk         (clk),
        .rst_n       (rst_n),
        .state       (state),
        .red_light   (red_light),
        .green_light (green_light),
        .yellow_light(yellow_light)
    );

    initial clk = 1'b1;
    always #5 clk = ~clk;

    initial begin
        $dumpfile("fixtures/reference.vcd");
        $dumpvars(0, tb_traffic_light);

        rst_n = 1'b0;
        #22;
        rst_n = 1'b1;
        #2978;
        $finish;
    end
endmodule

packs/traffic-light-fsm/fixtures/reference.vcd
$date
	Sun May 31 14:31:48 2026
$end
$version
	Icarus Verilog
$end
$timescale
	1ns
$end
$scope module tb_traffic_light $end
$var wire 1 ! yellow_light $end
$var wire 2 " state [1:0] $end
$var wire 1 # red_light $end
$var wire 1 $ green_light $end
$var reg 1 % clk $end
$var reg 1 & rst_n $end
$scope module dut $end
$var wire 1 % clk $end
$var wire 1 & rst_n $end
$var wire 1 ! yellow_light $end
$var wire 1 # red_light $end
$var wire 1 $ green_light $end
$var parameter 2 ' GREEN $end
$var parameter 2 ( RED $end
$var parameter 2 ) YELLOW $end
$var reg 5 * dwell [4:0] $end
$var reg 2 + state [1:0] $end
$upscope $end
$upscope $end
$enddefinitions $end
$comment Show the parameter values. $end
$dumpall
b10 )
b0 (
b1 '
$end
#0
$dumpvars
b0 +
b0 *
0&
1%
0$
1#
b0 "
0!
$end
#5
0%
#10
1%
#15
0%
#20
1%
#22
1&
#25
0%
#30
b1 *
1%
#35
0%
#40
b10 *
1%
#45
0%
#50
b11 *
1%
#55
0%
#60
b100 *
1%
#65
0%
#70
b101 *
1%
#75
0%
#80
b110 *
1%
#85
0%
#90
b111 *
1%
#95
0%
#100
b1000 *
1%
#105
0%
#110
b1001 *
1%
#115
0%
#120
b1010 *
1%
#125
0%
#130
b1011 *
1%
#135
0%
#140
b1100 *
1%
#145
0%
#150
b1101 *
1%
#155
0%
#160
b1110 *
1%
#165
0%
#170
b1111 *
1%
#175
0%
#180
b10000 *
1%
#185
0%
#190
b10001 *
1%
#195
0%
#200
b10010 *
1%
#205
0%
#210
b10011 *
1%
#215
0%
#220
b10100 *
1%
#225
0%
#230
b10101 *
1%
#235
0%
#240
b10110 *
1%
#245
0%
#250
b10111 *
1%
#255
0%
#260
b11000 *
1%
#265
0%
#270
b11001 *
1%
#275
0%
#280
b11010 *
1%
#285
0%
#290
b11011 *
1%
#295
0%
#300
b11100 *
1%
#305
0%
#310
b11101 *
1%
#315
0%
#320
0#
1$
b1 "
b1 +
b0 *
1%
#325
0%
#330
b1 *
1%
#335
0%
#340
b10 *
1%
#345
0%
#350
b11 *
1%
#355
0%
#360
b100 *
1%
#365
0%
#370
b101 *
1%
#375
0%
#380
b110 *
1%
#385
0%
#390
b111 *
1%
#395
0%
#400
b1000 *
1%
#405
0%
#410
b1001 *
1%
#415
0%
#420
b1010 *
1%
#425
0%
#430
b1011 *
1%
#435
0%
#440
b1100 *
1%
#445
0%
#450
b1101 *
1%
#455
0%
#460
b1110 *
1%
#465
0%
#470
b1111 *
1%
#475
0%
#480
b10000 *
1%
#485
0%
#490
b10001 *
1%
#495
0%
#500
b10010 *
1%
#505
0%
#510
b10011 *
1%
#515
0%
#520
b10100 *
1%
#525
0%
#530
b10101 *
1%
#535
0%
#540
b10110 *
1%
#545
0%
#550
b10111 *
1%
#555
0%
#560
b11000 *
1%
#565
0%
#570
b11001 *
1%
#575
0%
#580
b11010 *
1%
#585
0%
#590
b11011 *
1%
#595
0%
#600
b11100 *
1%
#605
0%
#610
b11101 *
1%
#615
0%
#620
0$
1!
b10 "
b10 +
b0 *
1%
#625
0%
#630
b1 *
1%
#635
0%
#640
b10 *
1%
#645
0%
#650
b11 *
1%
#655
0%
#660
b100 *
1%
#665
0%
#670
b101 *
1%
#675
0%
#680
b110 *
1%
#685
0%
#690
b111 *
1%
#695
0%
#700
b1000 *
1%
#705
0%
#710
b1001 *
1%
#715
0%
#720
b1010 *
1%
#725
0%
#730
b1011 *
1%
#735
0%
#740
b1100 *
1%
#745
0%
#750
b1101 *
1%
#755
0%
#760
b1110 *
1%
#765
0%
#770
b1111 *
1%
#775
0%
#780
b10000 *
1%
#785
0%
#790
b10001 *
1%
#795
0%
#800
b10010 *
1%
#805
0%
#810
b10011 *
1%
#815
0%
#820
b10100 *
1%
#825
0%
#830
b10101 *
1%
#835
0%
#840
b10110 *
1%
#845
0%
#850
b10111 *
1%
#855
0%
#860
b11000 *
1%
#865
0%
#870
b11001 *
1%
#875
0%
#880
b11010 *
1%
#885
0%
#890
b11011 *
1%
#895
0%
#900
b11100 *
1%
#905
0%
#910
b11101 *
1%
#915
0%
#920
1#
0!
b0 "
b0 +
b0 *
1%
#925
0%
#930
b1 *
1%
#935
0%
#940
b10 *
1%
#945
0%
#950
b11 *
1%
#955
0%
#960
b100 *
1%
#965
0%
#970
b101 *
1%
#975
0%
#980
b110 *
1%
#985
0%
#990
b111 *
1%
#995
0%
#1000
b1000 *
1%
#1005
0%
#1010
b1001 *
1%
#1015
0%
#1020
b1010 *
1%
#1025
0%
#1030
b1011 *
1%
#1035
0%
#1040
b1100 *
1%
#1045
0%
#1050
b1101 *
1%
#1055
0%
#1060
b1110 *
1%
#1065
0%
#1070
b1111 *
1%
#1075
0%
#1080
b10000 *
1%
#1085
0%
#1090
b10001 *
1%
#1095
0%
#1100
b10010 *
1%
#1105
0%
#1110
b10011 *
1%
#1115
0%
#1120
b10100 *
1%
#1125
0%
#1130
b10101 *
1%
#1135
0%
#1140
b10110 *
1%
#1145
0%
#1150
b10111 *
1%
#1155
0%
#1160
b11000 *
1%
#1165
0%
#1170
b11001 *
1%
#1175
0%
#1180
b11010 *
1%
#1185
0%
#1190
b11011 *
1%
#1195
0%
#1200
b11100 *
1%
#1205
0%
#1210
b11101 *
1%
#1215
0%
#1220
0#
1$
b1 "
b1 +
b0 *
1%
#1225
0%
#1230
b1 *
1%
#1235
0%
#1240
b10 *
1%
#1245
0%
#1250
b11 *
1%
#1255
0%
#1260
b100 *
1%
#1265
0%
#1270
b101 *
1%
#1275
0%
#1280
b110 *
1%
#1285
0%
#1290
b111 *
1%
#1295
0%
#1300
b1000 *
1%
#1305
0%
#1310
b1001 *
1%
#1315
0%
#1320
b1010 *
1%
#1325
0%
#1330
b1011 *
1%
#1335
0%
#1340
b1100 *
1%
#1345
0%
#1350
b1101 *
1%
#1355
0%
#1360
b1110 *
1%
#1365
0%
#1370
b1111 *
1%
#1375
0%
#1380
b10000 *
1%
#1385
0%
#1390
b10001 *
1%
#1395
0%
#1400
b10010 *
1%
#1405
0%
#1410
b10011 *
1%
#1415
0%
#1420
b10100 *
1%
#1425
0%
#1430
b10101 *
1%
#1435
0%
#1440
b10110 *
1%
#1445
0%
#1450
b10111 *
1%
#1455
0%
#1460
b11000 *
1%
#1465
0%
#1470
b11001 *
1%
#1475
0%
#1480
b11010 *
1%
#1485
0%
#1490
b11011 *
1%
#1495
0%
#1500
b11100 *
1%
#1505
0%
#1510
b11101 *
1%
#1515
0%
#1520
0$
1!
b10 "
b10 +
b0 *
1%
#1525
0%
#1530
b1 *
1%
#1535
0%
#1540
b10 *
1%
#1545
0%
#1550
b11 *
1%
#1555
0%
#1560
b100 *
1%
#1565
0%
#1570
b101 *
1%
#1575
0%
#1580
b110 *
1%
#1585
0%
#1590
b111 *
1%
#1595
0%
#1600
b1000 *
1%
#1605
0%
#1610
b1001 *
1%
#1615
0%
#1620
b1010 *
1%
#1625
0%
#1630
b1011 *
1%
#1635
0%
#1640
b1100 *
1%
#1645
0%
#1650
b1101 *
1%
#1655
0%
#1660
b1110 *
1%
#1665
0%
#1670
b1111 *
1%
#1675
0%
#1680
b10000 *
1%
#1685
0%
#1690
b10001 *
1%
#1695
0%
#1700
b10010 *
1%
#1705
0%
#1710
b10011 *
1%
#1715
0%
#1720
b10100 *
1%
#1725
0%
#1730
b10101 *
1%
#1735
0%
#1740
b10110 *
1%
#1745
0%
#1750
b10111 *
1%
#1755
0%
#1760
b11000 *
1%
#1765
0%
#1770
b11001 *
1%
#1775
0%
#1780
b11010 *
1%
#1785
0%
#1790
b11011 *
1%
#1795
0%
#1800
b11100 *
1%
#1805
0%
#1810
b11101 *
1%
#1815
0%
#1820
1#
0!
b0 "
b0 +
b0 *
1%
#1825
0%
#1830
b1 *
1%
#1835
0%
#1840
b10 *
1%
#1845
0%
#1850
b11 *
1%
#1855
0%
#1860
b100 *
1%
#1865
0%
#1870
b101 *
1%
#1875
0%
#1880
b110 *
1%
#1885
0%
#1890
b111 *
1%
#1895
0%
#1900
b1000 *
1%
#1905
0%
#1910
b1001 *
1%
#1915
0%
#1920
b1010 *
1%
#1925
0%
#1930
b1011 *
1%
#1935
0%
#1940
b1100 *
1%
#1945
0%
#1950
b1101 *
1%
#1955
0%
#1960
b1110 *
1%
#1965
0%
#1970
b1111 *
1%
#1975
0%
#1980
b10000 *
1%
#1985
0%
#1990
b10001 *
1%
#1995
0%
#2000
b10010 *
1%
#2005
0%
#2010
b10011 *
1%
#2015
0%
#2020
b10100 *
1%
#2025
0%
#2030
b10101 *
1%
#2035
0%
#2040
b10110 *
1%
#2045
0%
#2050
b10111 *
1%
#2055
0%
#2060
b11000 *
1%
#2065
0%
#2070
b11001 *
1%
#2075
0%
#2080
b11010 *
1%
#2085
0%
#2090
b11011 *
1%
#2095
0%
#2100
b11100 *
1%
#2105
0%
#2110
b11101 *
1%
#2115
0%
#2120
0#
1$
b1 "
b1 +
b0 *
1%
#2125
0%
#2130
b1 *
1%
#2135
0%
#2140
b10 *
1%
#2145
0%
#2150
b11 *
1%
#2155
0%
#2160
b100 *
1%
#2165
0%
#2170
b101 *
1%
#2175
0%
#2180
b110 *
1%
#2185
0%
#2190
b111 *
1%
#2195
0%
#2200
b1000 *
1%
#2205
0%
#2210
b1001 *
1%
#2215
0%
#2220
b1010 *
1%
#2225
0%
#2230
b1011 *
1%
#2235
0%
#2240
b1100 *
1%
#2245
0%
#2250
b1101 *
1%
#2255
0%
#2260
b1110 *
1%
#2265
0%
#2270
b1111 *
1%
#2275
0%
#2280
b10000 *
1%
#2285
0%
#2290
b10001 *
1%
#2295
0%
#2300
b10010 *
1%
#2305
0%
#2310
b10011 *
1%
#2315
0%
#2320
b10100 *
1%
#2325
0%
#2330
b10101 *
1%
#2335
0%
#2340
b10110 *
1%
#2345
0%
#2350
b10111 *
1%
#2355
0%
#2360
b11000 *
1%
#2365
0%
#2370
b11001 *
1%
#2375
0%
#2380
b11010 *
1%
#2385
0%
#2390
b11011 *
1%
#2395
0%
#2400
b11100 *
1%
#2405
0%
#2410
b11101 *
1%
#2415
0%
#2420
0$
1!
b10 "
b10 +
b0 *
1%
#2425
0%
#2430
b1 *
1%
#2435
0%
#2440
b10 *
1%
#2445
0%
#2450
b11 *
1%
#2455
0%
#2460
b100 *
1%
#2465
0%
#2470
b101 *
1%
#2475
0%
#2480
b110 *
1%
#2485
0%
#2490
b111 *
1%
#2495
0%
#2500
b1000 *
1%
#2505
0%
#2510
b1001 *
1%
#2515
0%
#2520
b1010 *
1%
#2525
0%
#2530
b1011 *
1%
#2535
0%
#2540
b1100 *
1%
#2545
0%
#2550
b1101 *
1%
#2555
0%
#2560
b1110 *
1%
#2565
0%
#2570
b1111 *
1%
#2575
0%
#2580
b10000 *
1%
#2585
0%
#2590
b10001 *
1%
#2595
0%
#2600
b10010 *
1%
#2605
0%
#2610
b10011 *
1%
#2615
0%
#2620
b10100 *
1%
#2625
0%
#2630
b10101 *
1%
#2635
0%
#2640
b10110 *
1%
#2645
0%
#2650
b10111 *
1%
#2655
0%
#2660
b11000 *
1%
#2665
0%
#2670
b11001 *
1%
#2675
0%
#2680
b11010 *
1%
#2685
0%
#2690
b11011 *
1%
#2695
0%
#2700
b11100 *
1%
#2705
0%
#2710
b11101 *
1%
#2715
0%
#2720
1#
0!
b0 "
b0 +
b0 *
1%
#2725
0%
#2730
b1 *
1%
#2735
0%
#2740
b10 *
1%
#2745
0%
#2750
b11 *
1%
#2755
0%
#2760
b100 *
1%
#2765
0%
#2770
b101 *
1%
#2775
0%
#2780
b110 *
1%
#2785
0%
#2790
b111 *
1%
#2795
0%
#2800
b1000 *
1%
#2805
0%
#2810
b1001 *
1%
#2815
0%
#2820
b1010 *
1%
#2825
0%
#2830
b1011 *
1%
#2835
0%
#2840
b1100 *
1%
#2845
0%
#2850
b1101 *
1%
#2855
0%
#2860
b1110 *
1%
#2865
0%
#2870
b1111 *
1%
#2875
0%
#2880
b10000 *
1%
#2885
0%
#2890
b10001 *
1%
#2895
0%
#2900
b10010 *
1%
#2905
0%
#2910
b10011 *
1%
#2915
0%
#2920
b10100 *
1%
#2925
0%
#2930
b10101 *
1%
#2935
0%
#2940
b10110 *
1%
#2945
0%
#2950
b10111 *
1%
#2955
0%
#2960
b11000 *
1%
#2965
0%
#2970
b11001 *
1%
#2975
0%
#2980
b11010 *
1%
#2985
0%
#2990
b11011 *
1%
#2995
0%
#3000
b11100 *
1%
