packs/memory-controller/src/wb_memory.v
// SPDX-License-Identifier: CC-BY-4.0
// Copyright (c) 2026 Ferrite Engineering
//
// Wishbone B4 classic synchronous memory slave. 256 words x 32 bits.
// Byte-enable `sel` is honored for writes (per-byte mask). Reads are
// always full 32-bit.
//
// Handshake: ack is asserted for exactly one cycle, the cycle after
// cyc & stb are observed valid.

`timescale 1ns / 1ns

module wb_memory #(parameter ADDR_WIDTH = 8) (
    input  wire        clk,
    input  wire        rst,
    input  wire [31:0] wb_adr,
    input  wire [31:0] wb_dat_i,
    output reg  [31:0] wb_dat_o,
    input  wire        wb_we,
    input  wire [ 3:0] wb_sel,
    input  wire        wb_stb,
    input  wire        wb_cyc,
    output reg         wb_ack
);
    reg [31:0] mem [0:(1<<ADDR_WIDTH)-1];

    wire active = wb_cyc & wb_stb & ~wb_ack;
    wire [ADDR_WIDTH-1:0] word_addr = wb_adr[ADDR_WIDTH+1:2]; // 4-byte aligned

    always @(posedge clk) begin
        if (rst) begin
            wb_ack   <= 1'b0;
            wb_dat_o <= 32'h0000_0000;
        end else if (active) begin
            wb_ack <= 1'b1;
            if (wb_we) begin
                if (wb_sel[0]) mem[word_addr][ 7: 0] <= wb_dat_i[ 7: 0];
                if (wb_sel[1]) mem[word_addr][15: 8] <= wb_dat_i[15: 8];
                if (wb_sel[2]) mem[word_addr][23:16] <= wb_dat_i[23:16];
                if (wb_sel[3]) mem[word_addr][31:24] <= wb_dat_i[31:24];
            end else begin
                wb_dat_o <= mem[word_addr];
            end
        end else begin
            wb_ack <= 1'b0;
        end
    end
endmodule

packs/memory-controller/src/wb_master.v
// SPDX-License-Identifier: CC-BY-4.0
// Copyright (c) 2026 Ferrite Engineering
//
// Wishbone B4 classic master that automatically writes 8 known values
// to consecutive 32-bit word addresses, then reads them back and
// stores the result in `last_read`. Designed for visualization in a
// waveform viewer rather than for synthesis.
//
// Pattern: writes 0xCAFE_0000 .. 0xCAFE_0007 to word addresses 0..7
// (byte addresses 0x00 .. 0x1C), then reads them back in the same
// order.

`timescale 1ns / 1ns

module wb_master (
    input  wire        clk,
    input  wire        rst,
    output reg  [31:0] wb_adr,
    output reg  [31:0] wb_dat_o,
    input  wire [31:0] wb_dat_i,
    output reg         wb_we,
    output reg  [ 3:0] wb_sel,
    output reg         wb_stb,
    output reg         wb_cyc,
    input  wire        wb_ack,
    output reg  [31:0] last_read,
    output reg         done
);
    localparam [2:0] S_RESET     = 3'd0;
    localparam [2:0] S_WRITE     = 3'd1;
    localparam [2:0] S_WRITE_ACK = 3'd2;
    localparam [2:0] S_READ      = 3'd3;
    localparam [2:0] S_READ_ACK  = 3'd4;
    localparam [2:0] S_DONE      = 3'd5;

    reg [2:0] state;
    reg [3:0] idx;        // 0..7 plus one to terminate
    reg [3:0] next_idx;

    always @(posedge clk) begin
        if (rst) begin
            wb_adr    <= 32'h0;
            wb_dat_o  <= 32'h0;
            wb_we     <= 1'b0;
            wb_sel    <= 4'h0;
            wb_stb    <= 1'b0;
            wb_cyc    <= 1'b0;
            last_read <= 32'h0;
            done      <= 1'b0;
            state     <= S_WRITE;
            idx       <= 4'd0;
            next_idx  <= 4'd0;
        end else begin
            case (state)
                S_WRITE: begin
                    if (idx == 4'd8) begin
                        // All writes done; reset index for reads.
                        idx     <= 4'd0;
                        wb_cyc  <= 1'b0;
                        wb_stb  <= 1'b0;
                        wb_we   <= 1'b0;
                        state   <= S_READ;
                    end else begin
                        wb_adr   <= {24'h0, idx[2:0], 2'b00}; // word-aligned
                        wb_dat_o <= 32'hCAFE_0000 | {28'h0, idx[3:0]};
                        wb_we    <= 1'b1;
                        wb_sel   <= 4'hF;
                        wb_stb   <= 1'b1;
                        wb_cyc   <= 1'b1;
                        state    <= S_WRITE_ACK;
                    end
                end
                S_WRITE_ACK: begin
                    if (wb_ack) begin
                        wb_stb <= 1'b0;
                        wb_cyc <= 1'b0;
                        wb_we  <= 1'b0;
                        idx    <= idx + 4'd1;
                        state  <= S_WRITE;
                    end
                end
                S_READ: begin
                    if (idx == 4'd8) begin
                        wb_cyc <= 1'b0;
                        wb_stb <= 1'b0;
                        done   <= 1'b1;
                        state  <= S_DONE;
                    end else begin
                        wb_adr <= {24'h0, idx[2:0], 2'b00};
                        wb_we  <= 1'b0;
                        wb_sel <= 4'hF;
                        wb_stb <= 1'b1;
                        wb_cyc <= 1'b1;
                        state  <= S_READ_ACK;
                    end
                end
                S_READ_ACK: begin
                    if (wb_ack) begin
                        last_read <= wb_dat_i;
                        wb_stb    <= 1'b0;
                        wb_cyc    <= 1'b0;
                        idx       <= idx + 4'd1;
                        state     <= S_READ;
                    end
                end
                S_DONE: begin
                    wb_cyc <= 1'b0;
                    wb_stb <= 1'b0;
                end
                default: state <= S_DONE;
            endcase
        end
    end
endmodule

packs/memory-controller/tb/tb_mem.v
// SPDX-License-Identifier: CC-BY-4.0
// Copyright (c) 2026 Ferrite Engineering
//
// Drives the Wishbone B4 master + memory slave pair. 100 MHz clock,
// synchronous active-high reset.

`timescale 1ns / 1ns

module tb_mem;
    reg         clk;
    reg         rst;
    wire [31:0] wb_adr;
    wire [31:0] dat_master_to_slave;
    wire [31:0] dat_slave_to_master;
    wire        wb_we;
    wire [ 3:0] wb_sel;
    wire        wb_stb;
    wire        wb_cyc;
    wire        wb_ack;
    wire [31:0] last_read;
    wire        done;

    wb_master u_master (
        .clk      (clk),
        .rst      (rst),
        .wb_adr   (wb_adr),
        .wb_dat_o (dat_master_to_slave),
        .wb_dat_i (dat_slave_to_master),
        .wb_we    (wb_we),
        .wb_sel   (wb_sel),
        .wb_stb   (wb_stb),
        .wb_cyc   (wb_cyc),
        .wb_ack   (wb_ack),
        .last_read(last_read),
        .done     (done)
    );

    wb_memory #(.ADDR_WIDTH(8)) u_mem (
        .clk     (clk),
        .rst     (rst),
        .wb_adr  (wb_adr),
        .wb_dat_i(dat_master_to_slave),
        .wb_dat_o(dat_slave_to_master),
        .wb_we   (wb_we),
        .wb_sel  (wb_sel),
        .wb_stb  (wb_stb),
        .wb_cyc  (wb_cyc),
        .wb_ack  (wb_ack)
    );

    initial clk = 1'b1;
    always #5 clk = ~clk;

    initial begin
        $dumpfile("fixtures/reference.vcd");
        $dumpvars(0, tb_mem);

        rst = 1'b1;
        #22;
        rst = 1'b0;
        #978;        // 1000 ns total — long enough to write+read 8 words
        $finish;
    end
endmodule

packs/memory-controller/fixtures/reference.vcd
$date
	Sun May 31 14:47:18 2026
$end
$version
	Icarus Verilog
$end
$timescale
	1ns
$end
$scope module tb_mem $end
$var wire 1 ! wb_we $end
$var wire 1 " wb_stb $end
$var wire 4 # wb_sel [3:0] $end
$var wire 1 $ wb_cyc $end
$var wire 32 % wb_adr [31:0] $end
$var wire 1 & wb_ack $end
$var wire 32 ' last_read [31:0] $end
$var wire 1 ( done $end
$var wire 32 ) dat_slave_to_master [31:0] $end
$var wire 32 * dat_master_to_slave [31:0] $end
$var reg 1 + clk $end
$var reg 1 , rst $end
$scope module u_master $end
$var wire 1 + clk $end
$var wire 1 , rst $end
$var wire 32 - wb_dat_i [31:0] $end
$var wire 1 & wb_ack $end
$var parameter 3 . S_DONE $end
$var parameter 3 / S_READ $end
$var parameter 3 0 S_READ_ACK $end
$var parameter 3 1 S_RESET $end
$var parameter 3 2 S_WRITE $end
$var parameter 3 3 S_WRITE_ACK $end
$var reg 1 ( done $end
$var reg 4 4 idx [3:0] $end
$var reg 32 5 last_read [31:0] $end
$var reg 4 6 next_idx [3:0] $end
$var reg 3 7 state [2:0] $end
$var reg 32 8 wb_adr [31:0] $end
$var reg 1 $ wb_cyc $end
$var reg 32 9 wb_dat_o [31:0] $end
$var reg 4 : wb_sel [3:0] $end
$var reg 1 " wb_stb $end
$var reg 1 ! wb_we $end
$upscope $end
$scope module u_mem $end
$var wire 1 ; active $end
$var wire 1 + clk $end
$var wire 1 , rst $end
$var wire 32 < wb_adr [31:0] $end
$var wire 1 $ wb_cyc $end
$var wire 32 = wb_dat_i [31:0] $end
$var wire 4 > wb_sel [3:0] $end
$var wire 1 " wb_stb $end
$var wire 1 ! wb_we $end
$var wire 8 ? word_addr [7:0] $end
$var parameter 32 @ ADDR_WIDTH $end
$var reg 1 & wb_ack $end
$var reg 32 A wb_dat_o [31:0] $end
$upscope $end
$upscope $end
$enddefinitions $end
$comment Show the parameter values. $end
$dumpall
b1000 @
b10 3
b1 2
b0 1
b100 0
b11 /
b101 .
$end
#0
$dumpvars
b0 A
b0 ?
b0 >
b0 =
b0 <
0;
b0 :
b0 9
b0 8
b1 7
b0 6
b0 5
b0 4
b0 -
1,
1+
b0 *
b0 )
0(
b0 '
0&
b0 %
0$
b0 #
0"
0!
$end
#5
0+
#10
1+
#15
0+
#20
1+
#22
0,
#25
0+
#30
1;
b10 7
1$
1"
b1111 #
b1111 :
b1111 >
1!
b11001010111111100000000000000000 *
b11001010111111100000000000000000 9
b11001010111111100000000000000000 =
1+
#35
0+
#40
0;
1&
1+
#45
0+
#50
0&
b1 7
b1 4
0!
0$
0"
1+
#55
0+
#60
1;
b1 ?
b10 7
1$
1"
1!
b11001010111111100000000000000001 *
b11001010111111100000000000000001 9
b11001010111111100000000000000001 =
b100 %
b100 8
b100 <
1+
#65
0+
#70
0;
1&
1+
#75
0+
#80
b1 7
b10 4
0!
0$
0"
0&
1+
#85
0+
#90
1;
b10 ?
b10 7
1$
1"
1!
b11001010111111100000000000000010 *
b11001010111111100000000000000010 9
b11001010111111100000000000000010 =
b1000 %
b1000 8
b1000 <
1+
#95
0+
#100
0;
1&
1+
#105
0+
#110
0&
b1 7
b11 4
0!
0$
0"
1+
#115
0+
#120
1;
b11 ?
b10 7
1$
1"
1!
b11001010111111100000000000000011 *
b11001010111111100000000000000011 9
b11001010111111100000000000000011 =
b1100 %
b1100 8
b1100 <
1+
#125
0+
#130
0;
1&
1+
#135
0+
#140
b1 7
b100 4
0!
0$
0"
0&
1+
#145
0+
#150
1;
b100 ?
b10 7
1$
1"
1!
b11001010111111100000000000000100 *
b11001010111111100000000000000100 9
b11001010111111100000000000000100 =
b10000 %
b10000 8
b10000 <
1+
#155
0+
#160
0;
1&
1+
#165
0+
#170
0&
b1 7
b101 4
0!
0$
0"
1+
#175
0+
#180
1;
b101 ?
b10 7
1$
1"
1!
b11001010111111100000000000000101 *
b11001010111111100000000000000101 9
b11001010111111100000000000000101 =
b10100 %
b10100 8
b10100 <
1+
#185
0+
#190
0;
1&
1+
#195
0+
#200
b1 7
b110 4
0!
0$
0"
0&
1+
#205
0+
#210
1;
b110 ?
b10 7
1$
1"
1!
b11001010111111100000000000000110 *
b11001010111111100000000000000110 9
b11001010111111100000000000000110 =
b11000 %
b11000 8
b11000 <
1+
#215
0+
#220
0;
1&
1+
#225
0+
#230
0&
b1 7
b111 4
0!
0$
0"
1+
#235
0+
#240
1;
b111 ?
b10 7
1$
1"
1!
b11001010111111100000000000000111 *
b11001010111111100000000000000111 9
b11001010111111100000000000000111 =
b11100 %
b11100 8
b11100 <
1+
#245
0+
#250
0;
1&
1+
#255
0+
#260
b1 7
b1000 4
0!
0$
0"
0&
1+
#265
0+
#270
b11 7
b0 4
1+
#275
0+
#280
1;
b0 ?
b100 7
1$
1"
b0 %
b0 8
b0 <
1+
#285
0+
#290
0;
b11001010111111100000000000000000 )
b11001010111111100000000000000000 -
b11001010111111100000000000000000 A
1&
1+
#295
0+
#300
b11 7
b1 4
0$
0"
b11001010111111100000000000000000 '
b11001010111111100000000000000000 5
0&
1+
#305
0+
#310
1;
b1 ?
b100 7
1$
1"
b100 %
b100 8
b100 <
1+
#315
0+
#320
0;
b11001010111111100000000000000001 )
b11001010111111100000000000000001 -
b11001010111111100000000000000001 A
1&
1+
#325
0+
#330
0&
b11 7
b10 4
0$
0"
b11001010111111100000000000000001 '
b11001010111111100000000000000001 5
1+
#335
0+
#340
1;
b10 ?
b100 7
1$
1"
b1000 %
b1000 8
b1000 <
1+
#345
0+
#350
0;
b11001010111111100000000000000010 )
b11001010111111100000000000000010 -
b11001010111111100000000000000010 A
1&
1+
#355
0+
#360
b11 7
b11 4
0$
0"
b11001010111111100000000000000010 '
b11001010111111100000000000000010 5
0&
1+
#365
0+
#370
1;
b11 ?
b100 7
1$
1"
b1100 %
b1100 8
b1100 <
1+
#375
0+
#380
0;
b11001010111111100000000000000011 )
b11001010111111100000000000000011 -
b11001010111111100000000000000011 A
1&
1+
#385
0+
#390
0&
b11 7
b100 4
0$
0"
b11001010111111100000000000000011 '
b11001010111111100000000000000011 5
1+
#395
0+
#400
1;
b100 ?
b100 7
1$
1"
b10000 %
b10000 8
b10000 <
1+
#405
0+
#410
0;
b11001010111111100000000000000100 )
b11001010111111100000000000000100 -
b11001010111111100000000000000100 A
1&
1+
#415
0+
#420
b11 7
b101 4
0$
0"
b11001010111111100000000000000100 '
b11001010111111100000000000000100 5
0&
1+
#425
0+
#430
1;
b101 ?
b100 7
1$
1"
b10100 %
b10100 8
b10100 <
1+
#435
0+
#440
0;
b11001010111111100000000000000101 )
b11001010111111100000000000000101 -
b11001010111111100000000000000101 A
1&
1+
#445
0+
#450
0&
b11 7
b110 4
0$
0"
b11001010111111100000000000000101 '
b11001010111111100000000000000101 5
1+
#455
0+
#460
1;
b110 ?
b100 7
1$
1"
b11000 %
b11000 8
b11000 <
1+
#465
0+
#470
0;
b11001010111111100000000000000110 )
b11001010111111100000000000000110 -
b11001010111111100000000000000110 A
1&
1+
#475
0+
#480
b11 7
b111 4
0$
0"
b11001010111111100000000000000110 '
b11001010111111100000000000000110 5
0&
1+
#485
0+
#490
1;
b111 ?
b100 7
1$
1"
b11100 %
b11100 8
b11100 <
1+
#495
0+
#500
0;
b11001010111111100000000000000111 )
b11001010111111100000000000000111 -
b11001010111111100000000000000111 A
1&
1+
#505
0+
#510
0&
b11 7
b1000 4
0$
0"
b11001010111111100000000000000111 '
b11001010111111100000000000000111 5
1+
#515
0+
#520
b101 7
1(
1+
