packs/spi-bringup/src/spi_master.v
`timescale 1ns/1ns
// SPI mode-0 master (CPOL=0, CPHA=0): sample on rising SCLK, shift on falling.
// Sub-module shift_reg makes the datapath navigable in NetCrux.
module shift_reg (
    input clk, load, shift, input [7:0] din, input msb_in,
    output [7:0] dout, output msb
);
    reg [7:0] q;
    always @(posedge clk) if (load) q <= din; else if (shift) q <= {q[6:0], msb_in};
    assign dout = q; assign msb = q[7];
endmodule

module spi_master #(parameter DIV = 2) (
    input clk, rst_n, start, input [7:0] tx_byte, input miso,
    output reg sclk, output reg cs_n, output mosi, output reg done, output [7:0] rx_byte
);
    localparam IDLE=0, RUN=1;
    reg state; reg [3:0] cnt; reg [$clog2(DIV):0] dv; reg sclk_en;
    wire [7:0] txq, rxq;
    wire rise = (state==RUN) && (dv==0) && (sclk==1'b0);
    wire fall = (state==RUN) && (dv==0) && (sclk==1'b1);
    shift_reg u_tx (.clk(clk), .load(start & (state==IDLE)), .shift(fall), .din(tx_byte), .msb_in(1'b0), .dout(txq), .msb(mosi));
    shift_reg u_rx (.clk(clk), .load(1'b0), .shift(rise), .din(8'h00), .msb_in(miso), .dout(rxq), .msb());
    assign rx_byte = rxq;
    always @(posedge clk or negedge rst_n) begin
        if (!rst_n) begin state<=IDLE; sclk<=0; cs_n<=1; done<=0; cnt<=0; dv<=0; end
        else begin done<=0;
            case (state)
                IDLE: begin sclk<=0; cs_n<=1; if (start) begin cs_n<=0; cnt<=0; dv<=DIV-1; state<=RUN; end end
                RUN:  if (dv==0) begin dv<=DIV-1; sclk<=~sclk;
                          if (sclk==1'b1) begin if (cnt==4'd8) begin state<=IDLE; cs_n<=1; done<=1; end else cnt<=cnt+1; end
                      end else dv<=dv-1;
            endcase
        end
    end
endmodule

packs/spi-bringup/tb/tb_spi.v
`timescale 1ns/1ns
module tb_spi;
  reg clk=0, rst_n=0, start=0; reg [7:0] tx_byte;
  wire sclk, cs_n, mosi, done; wire [7:0] rx_byte;
  reg miso;
  spi_master #(.DIV(2)) dut (.clk(clk),.rst_n(rst_n),.start(start),.tx_byte(tx_byte),
                             .miso(miso),.sclk(sclk),.cs_n(cs_n),.mosi(mosi),.done(done),.rx_byte(rx_byte));
  always #5 clk=~clk;

  // Loopback slave: MISO echoes MOSI, so a correct master receives what it sent.
  always @(*) miso = mosi;

  task xfer(input [127:0] nm, input [7:0] b);
    begin
      @(negedge clk); tx_byte=b; start=1; @(negedge clk); start=0;
      #4000;                          // plenty of time for an 8-bit mode-0 transfer
      if (rx_byte===b) $display("RESULT %0s PASS", nm);
      else             $display("RESULT %0s FAIL sent=%02x got=%02x", nm, b, rx_byte);
    end
  endtask

  initial begin
    $dumpfile("fixtures/reference.vcd"); $dumpvars(0, tb_spi);
    #20 rst_n=1; #40;
    xfer("loopback_0x3C", 8'h3C);
    xfer("loopback_0xA5", 8'hA5);
    xfer("loopback_0xFF", 8'hFF);
    #100 $finish;
  end
endmodule

packs/spi-bringup/fixtures/reference.vcd
$date
	Fri Jul 24 11:51:22 2026
$end
$version
	Icarus Verilog
$end
$timescale
	1ns
$end
$scope module tb_spi $end
$var wire 1 ! sclk $end
$var wire 8 " rx_byte [7:0] $end
$var wire 1 # mosi $end
$var wire 1 $ done $end
$var wire 1 % cs_n $end
$var reg 1 & clk $end
$var reg 1 ' miso $end
$var reg 1 ( rst_n $end
$var reg 1 ) start $end
$var reg 8 * tx_byte [7:0] $end
$scope module dut $end
$var wire 1 & clk $end
$var wire 1 + fall $end
$var wire 1 ' miso $end
$var wire 1 , rise $end
$var wire 1 ( rst_n $end
$var wire 8 - rx_byte [7:0] $end
$var wire 1 ) start $end
$var wire 8 . tx_byte [7:0] $end
$var wire 8 / txq [7:0] $end
$var wire 8 0 rxq [7:0] $end
$var wire 1 # mosi $end
$var parameter 32 1 DIV $end
$var parameter 32 2 IDLE $end
$var parameter 32 3 RUN $end
$var reg 4 4 cnt [3:0] $end
$var reg 1 % cs_n $end
$var reg 1 $ done $end
$var reg 2 5 dv [1:0] $end
$var reg 1 ! sclk $end
$var reg 1 6 state $end
$scope module u_rx $end
$var wire 1 & clk $end
$var wire 8 7 din [7:0] $end
$var wire 8 8 dout [7:0] $end
$var wire 1 9 load $end
$var wire 1 ' msb_in $end
$var wire 1 , shift $end
$var wire 1 : msb $end
$var reg 8 ; q [7:0] $end
$upscope $end
$scope module u_tx $end
$var wire 1 & clk $end
$var wire 8 < din [7:0] $end
$var wire 8 = dout [7:0] $end
$var wire 1 > load $end
$var wire 1 ? msb_in $end
$var wire 1 + shift $end
$var wire 1 # msb $end
$var reg 8 @ q [7:0] $end
$upscope $end
$upscope $end
$scope task xfer $end
$var reg 8 A b [7:0] $end
$var reg 128 B nm [127:0] $end
$upscope $end
$upscope $end
$enddefinitions $end
$comment Show the parameter values. $end
$dumpall
b1 3
b0 2
b10 1
$end
#0
$dumpvars
bx B
bx A
bx @
0?
0>
bx =
bx <
bx ;
x:
09
bx 8
b0 7
x6
bx 5
bx 4
bx 0
bx /
bx .
bx -
x,
x+
bx *
0)
0(
x'
0&
x%
x$
x#
bx "
x!
$end
#5
0+
0,
b0 5
b0 4
0$
1%
0!
06
1&
#10
0&
#15
1&
#20
0&
1(
#25
1&
#30
0&
#35
1&
#40
0&
#45
1&
#50
0&
#55
1&
#60
1>
1)
b111100 *
b111100 .
b111100 <
0&
b111100 A
b1101100011011110110111101110000011000100110000101100011011010110101111100110000011110000011001101000011 B
#65
0'
0>
0#
b111100 /
b111100 =
b111100 @
16
b1 5
0%
1&
#70
0)
0&
#75
1,
b0 5
1&
#80
0&
#85
0,
bx0 "
bx0 -
bx0 0
bx0 8
bx0 ;
1!
b1 5
1&
#90
0&
#95
1+
b0 5
1&
#100
0&
#105
0+
b1111000 /
b1111000 =
b1111000 @
b1 4
0!
b1 5
1&
#110
0&
#115
1,
b0 5
1&
#120
0&
#125
0,
bx00 "
bx00 -
bx00 0
bx00 8
bx00 ;
1!
b1 5
1&
#130
0&
#135
1+
b0 5
1&
#140
0&
#145
1'
0+
1#
b11110000 /
b11110000 =
b11110000 @
b10 4
0!
b1 5
1&
#150
0&
#155
1,
b0 5
1&
#160
0&
#165
0,
bx001 "
bx001 -
bx001 0
bx001 8
bx001 ;
1!
b1 5
1&
#170
0&
#175
1+
b0 5
1&
#180
0&
#185
0+
b11100000 /
b11100000 =
b11100000 @
b11 4
0!
b1 5
1&
#190
0&
#195
1,
b0 5
1&
#200
0&
#205
0,
bx0011 "
bx0011 -
bx0011 0
bx0011 8
bx0011 ;
1!
b1 5
1&
#210
0&
#215
1+
b0 5
1&
#220
0&
#225
0+
b11000000 /
b11000000 =
b11000000 @
b100 4
0!
b1 5
1&
#230
0&
#235
1,
b0 5
1&
#240
0&
#245
0,
bx00111 "
bx00111 -
bx00111 0
bx00111 8
bx00111 ;
1!
b1 5
1&
#250
0&
#255
1+
b0 5
1&
#260
0&
#265
0+
b10000000 /
b10000000 =
b10000000 @
b101 4
0!
b1 5
1&
#270
0&
#275
1,
b0 5
1&
#280
0&
#285
0,
bx001111 "
bx001111 -
bx001111 0
bx001111 8
bx001111 ;
1!
b1 5
1&
#290
0&
#295
1+
b0 5
1&
#300
0&
#305
0'
0+
0#
b0 /
b0 =
b0 @
b110 4
0!
b1 5
1&
#310
0&
#315
1,
b0 5
1&
#320
0&
#325
0,
bx0011110 "
bx0011110 -
bx0011110 0
bx0011110 8
bx0011110 ;
1!
b1 5
1&
#330
0&
#335
1+
b0 5
1&
#340
0&
#345
0+
b111 4
0!
b1 5
1&
#350
0&
#355
1,
b0 5
1&
#360
0&
#365
0,
0:
b111100 "
b111100 -
b111100 0
b111100 8
b111100 ;
1!
b1 5
1&
#370
0&
#375
1+
b0 5
1&
#380
0&
#385
0+
b1000 4
0!
b1 5
1&
#390
0&
#395
1,
b0 5
1&
#400
0&
#405
0,
b1111000 "
b1111000 -
b1111000 0
b1111000 8
b1111000 ;
1!
b1 5
1&
#410
0&
#415
1+
b0 5
1&
#420
0&
#425
0+
1$
1%
06
0!
b1 5
1&
#430
0&
#435
0$
1&
