packs/uart-verification/src/uart_tx.v
`timescale 1ns/1ns
// UART transmitter, 8N1. Deliberately correct — this pack is about verification
// flow (a failing test that leads to a waveform), so the "bug" lives in the
// testbench's expectation on one case, mirroring a real spec-vs-impl mismatch.
module uart_tx #(parameter CLKS_PER_BIT = 4) (
    input        clk, rst_n, start,
    input  [7:0] data,
    output reg   tx, busy
);
    localparam IDLE=0, STARTB=1, DATA=2, STOPB=3;
    reg [1:0] state; reg [2:0] bitc; reg [$clog2(CLKS_PER_BIT):0] clkc; reg [7:0] sh;
    always @(posedge clk or negedge rst_n) begin
        if (!rst_n) begin state<=IDLE; tx<=1'b1; busy<=1'b0; clkc<=0; bitc<=0; sh<=0; end
        else case (state)
            IDLE:   begin tx<=1'b1; busy<=1'b0; clkc<=0; bitc<=0;
                          if (start) begin sh<=data; busy<=1'b1; state<=STARTB; end end
            STARTB: begin tx<=1'b0;
                          if (clkc==CLKS_PER_BIT-1) begin clkc<=0; state<=DATA; end else clkc<=clkc+1; end
            DATA:   begin tx<=sh[0];
                          if (clkc==CLKS_PER_BIT-1) begin clkc<=0; sh<=sh>>1;
                              if (bitc==3'd7) state<=STOPB; else bitc<=bitc+1; end else clkc<=clkc+1; end
            STOPB:  begin tx<=1'b1;
                          if (clkc==CLKS_PER_BIT-1) begin clkc<=0; state<=IDLE; end else clkc<=clkc+1; end
        endcase
    end
endmodule

packs/uart-verification/tb/tb_uart.v
`timescale 1ns/1ns
module tb_uart;
  reg clk=0, rst_n=0, start=0; reg [7:0] data; wire tx, busy;
  localparam CPB=4;
  uart_tx #(.CLKS_PER_BIT(CPB)) dut (.clk(clk),.rst_n(rst_n),.start(start),.data(data),.tx(tx),.busy(busy));
  always #5 clk=~clk;   // 10ns period; one bit = CPB*10 = 40ns

  reg [7:0] rx; integer k;
  // Deterministic fixed-delay capture: pulse start, skip the start bit, then
  // sample each of 8 data bits at its centre. No wait() -> cannot hang.
  task send_and_capture(input [7:0] d);
    begin
      @(negedge clk); data=d; start=1; @(negedge clk); start=0;
      #(CPB*10);            // consume the start bit
      #(CPB*10/2);          // move to centre of bit0
      for (k=0;k<8;k=k+1) begin rx[k]=tx; #(CPB*10); end
      #(CPB*10*2);          // let it return to idle before the next byte
    end
  endtask
  task check(input [127:0] nm, input [7:0] sent, input [7:0] want);
    begin
      send_and_capture(sent);
      if (rx===want) $display("RESULT %0s PASS", nm);
      else           $display("RESULT %0s FAIL sent=%02x got=%02x want=%02x", nm, sent, rx, want);
    end
  endtask
  initial begin
    $dumpfile("fixtures/reference.vcd"); $dumpvars(0, tb_uart);
    #20 rst_n=1; #40;
    check("tx_0x55", 8'h55, 8'h55);
    check("tx_0xA3", 8'hA3, 8'hA3);
    check("tx_0xFF", 8'hFF, 8'h00);   // BAD EXPECTATION: wants 0x00 for 0xFF -> FAIL by design
    #100 $finish;
  end
endmodule

packs/uart-verification/fixtures/reference.vcd
$date
	Fri Jul 24 11:47:13 2026
$end
$version
	Icarus Verilog
$end
$timescale
	1ns
$end
$scope module tb_uart $end
$var wire 1 ! tx $end
$var wire 1 " busy $end
$var parameter 32 # CPB $end
$var reg 1 $ clk $end
$var reg 8 % data [7:0] $end
$var reg 1 & rst_n $end
$var reg 8 ' rx [7:0] $end
$var reg 1 ( start $end
$var integer 32 ) k [31:0] $end
$scope module dut $end
$var wire 1 $ clk $end
$var wire 8 * data [7:0] $end
$var wire 1 & rst_n $end
$var wire 1 ( start $end
$var parameter 32 + CLKS_PER_BIT $end
$var parameter 32 , DATA $end
$var parameter 32 - IDLE $end
$var parameter 32 . STARTB $end
$var parameter 32 / STOPB $end
$var reg 3 0 bitc [2:0] $end
$var reg 1 " busy $end
$var reg 3 1 clkc [2:0] $end
$var reg 8 2 sh [7:0] $end
$var reg 2 3 state [1:0] $end
$var reg 1 ! tx $end
$upscope $end
$scope task check $end
$var reg 128 4 nm [127:0] $end
$var reg 8 5 sent [7:0] $end
$var reg 8 6 want [7:0] $end
$upscope $end
$scope task send_and_capture $end
$var reg 8 7 d [7:0] $end
$upscope $end
$upscope $end
$enddefinitions $end
$comment Show the parameter values. $end
$dumpall
b11 /
b1 .
b0 -
b10 ,
b100 +
b100 #
$end
#0
$dumpvars
bx 7
bx 6
bx 5
bx 4
bx 3
bx 2
bx 1
bx 0
bx *
bx )
0(
bx '
0&
bx %
0$
x"
x!
$end
#5
b0 2
b0 0
b0 1
0"
1!
b0 3
1$
#10
0$
#15
1$
#20
0$
1&
#25
1$
#30
0$
#35
1$
#40
0$
#45
1$
#50
0$
#55
1$
#60
1(
b1010101 %
b1010101 *
0$
b1010101 7
b1010101 6
b1010101 5
b1110100011110000101111100110000011110000011010100110101 4
#65
b1 3
1"
b1010101 2
1$
#70
0(
0$
#75
b1 1
0!
1$
#80
0$
#85
b10 1
1$
#90
0$
#95
b11 1
1$
#100
0$
#105
b10 3
b0 1
1$
#110
0$
#115
b1 1
1!
1$
#120
0$
#125
b10 1
1$
#130
0$
bx1 '
b0 )
#135
b11 1
1$
#140
0$
#145
b1 0
b101010 2
b0 1
1$
#150
0$
#155
b1 1
0!
1$
#160
0$
#165
b10 1
1$
#170
0$
bx01 '
b1 )
#175
b11 1
1$
#180
0$
#185
b10 0
b10101 2
b0 1
1$
#190
0$
#195
b1 1
1!
1$
#200
0$
#205
b10 1
1$
#210
0$
bx101 '
b10 )
#215
b11 1
1$
#220
0$
#225
b11 0
b1010 2
b0 1
1$
#230
0$
#235
b1 1
0!
1$
#240
0$
#245
b10 1
1$
#250
0$
bx0101 '
b11 )
#255
b11 1
1$
#260
0$
#265
b100 0
b101 2
b0 1
1$
#270
0$
#275
b1 1
1!
1$
#280
0$
#285
b10 1
1$
#290
0$
bx10101 '
b100 )
#295
b11 1
1$
#300
0$
#305
b101 0
b10 2
b0 1
1$
#310
0$
#315
b1 1
0!
1$
#320
0$
#325
b10 1
1$
#330
0$
bx010101 '
b101 )
#335
b11 1
1$
#340
0$
#345
b110 0
b1 2
b0 1
1$
#350
0$
#355
b1 1
1!
1$
#360
0$
#365
b10 1
1$
#370
0$
bx1010101 '
b110 )
#375
b11 1
1$
#380
0$
#385
b111 0
b0 2
b0 1
1$
#390
0$
#395
b1 1
0!
1$
#400
0$
#405
b10 1
1$
#410
0$
b1010101 '
b111 )
#415
b11 1
1$
#420
0$
#425
b11 3
b0 1
1$
#430
0$
#435
b1 1
1!
1$
#440
0$
#445
b10 1
1$
#450
0$
b1000 )
#455
b11 1
1$
#460
0$
#465
b0 3
b0 1
1$
#470
0$
#475
b0 0
0"
1$
#480
0$
#485
1$
#490
0$
#495
1$
#500
0$
#505
1$
#510
0$
#515
1$
#520
0$
#525
1$
#530
1(
b10100011 %
b10100011 *
0$
b10100011 7
b10100011 6
b10100011 5
b1110100011110000101111100110000011110000100000100110011 4
#535
b1 3
1"
b10100011 2
1$
#540
0(
0$
#545
b1 1
0!
1$
#550
0$
#555
b10 1
1$
#560
0$
#565
b11 1
1$
#570
0$
#575
b10 3
b0 1
1$
#580
0$
#585
b1 1
1!
1$
#590
0$
#595
b10 1
1$
#600
0$
b0 )
#605
b11 1
1$
#610
0$
#615
b1 0
b1010001 2
b0 1
1$
#620
0$
#625
b1 1
1$
#630
0$
#635
b10 1
1$
#640
0$
b1010111 '
b1 )
#645
b11 1
1$
#650
0$
#655
b10 0
b101000 2
b0 1
1$
#660
0$
#665
b1 1
0!
1$
#670
0$
#675
b10 1
1$
#680
0$
b1010011 '
b10 )
#685
b11 1
1$
#690
0$
#695
b11 0
b10100 2
b0 1
1$
#700
0$
#705
b1 1
1$
#710
0$
#715
b10 1
1$
#720
0$
b11 )
#725
b11 1
1$
#730
0$
#735
b100 0
b1010 2
b0 1
1$
#740
0$
#745
b1 1
1$
#750
0$
#755
b10 1
1$
#760
0$
b1000011 '
b100 )
#765
b11 1
1$
#770
0$
#775
b101 0
b101 2
b0 1
1$
#780
0$
#785
b1 1
1!
1$
#790
0$
#795
b10 1
1$
#800
0$
b1100011 '
b101 )
#805
b11 1
1$
#810
0$
#815
b110 0
b10 2
b0 1
1$
#820
0$
#825
b1 1
0!
1$
#830
0$
#835
b10 1
1$
#840
0$
b100011 '
b110 )
#845
b11 1
1$
#850
0$
#855
b111 0
b1 2
b0 1
1$
#860
0$
#865
b1 1
1!
1$
#870
0$
#875
b10 1
1$
#880
0$
b10100011 '
b111 )
#885
b11 1
1$
#890
0$
#895
b11 3
b0 2
b0 1
1$
#900
0$
#905
b1 1
1$
#910
0$
#915
b10 1
1$
#920
0$
b1000 )
#925
b11 1
1$
#930
0$
#935
b0 3
b0 1
1$
#940
0$
#945
b0 0
0"
1$
#950
0$
#955
1$
#960
0$
#965
1$
#970
0$
#975
1$
#980
0$
#985
1$
#990
0$
#995
1$
#1000
1(
b11111111 %
b11111111 *
0$
b11111111 7
b0 6
b11111111 5
b1110100011110000101111100110000011110000100011001000110 4
#1005
b1 3
1"
b11111111 2
1$
#1010
0(
0$
#1015
b1 1
0!
1$
#1020
0$
#1025
b10 1
1$
#1030
0$
#1035
b11 1
1$
#1040
0$
#1045
b10 3
b0 1
1$
#1050
0$
#1055
b1 1
1!
1$
#1060
0$
#1065
b10 1
1$
#1070
0$
b0 )
#1075
b11 1
1$
#1080
0$
#1085
b1 0
b1111111 2
b0 1
1$
#1090
0$
#1095
b1 1
1$
#1100
0$
#1105
b10 1
1$
#1110
0$
b1 )
#1115
b11 1
1$
#1120
0$
#1125
b10 0
b111111 2
b0 1
1$
#1130
0$
#1135
b1 1
1$
#1140
0$
#1145
b10 1
1$
#1150
0$
b10100111 '
b10 )
#1155
b11 1
1$
#1160
0$
#1165
b11 0
b11111 2
b0 1
1$
#1170
0$
#1175
b1 1
1$
#1180
0$
#1185
b10 1
1$
#1190
0$
b10101111 '
b11 )
#1195
b11 1
1$
#1200
0$
#1205
b100 0
b1111 2
b0 1
1$
#1210
0$
#1215
b1 1
1$
#1220
0$
#1225
b10 1
1$
#1230
0$
b10111111 '
b100 )
#1235
b11 1
1$
#1240
0$
#1245
b101 0
b111 2
b0 1
1$
#1250
0$
#1255
b1 1
1$
#1260
0$
#1265
b10 1
1$
#1270
0$
b101 )
#1275
b11 1
1$
#1280
0$
#1285
b110 0
b11 2
b0 1
1$
#1290
0$
#1295
b1 1
1$
#1300
0$
#1305
b10 1
1$
#1310
0$
b11111111 '
b110 )
#1315
b11 1
1$
#1320
0$
#1325
b111 0
b1 2
b0 1
1$
#1330
0$
#1335
b1 1
1$
#1340
0$
#1345
b10 1
1$
#1350
0$
b111 )
#1355
b11 1
1$
#1360
0$
#1365
b11 3
b0 2
b0 1
1$
#1370
0$
#1375
b1 1
1$
#1380
0$
#1385
b10 1
1$
#1390
0$
b1000 )
#1395
b11 1
1$
#1400
0$
#1405
b0 3
b0 1
1$
#1410
0$
#1415
b0 0
0"
1$
