packs/stage-showcase-basys3/src/basys3_demo.v
// SPDX-License-Identifier: CC-BY-4.0
// Copyright (c) 2026 Ferrite Engineering
//
// Digilent Basys 3 board demo. Drives 4 LEDs from 4 switches (direct
// passthrough), and drives a 4-digit common-anode 7-segment display
// with a 4-bit counter that increments on each rising edge of any of
// 4 push buttons.
//
// Targeting the WaveCrux Stage panel, not real hardware -- the
// design is deliberately tiny and the 7-segment encoder uses the
// standard Basys 3 active-low segment polarity.

`timescale 1ns / 1ns

module basys3_demo (
    input  wire        clk,
    input  wire        rst_n,
    input  wire [ 3:0] sw,        // SW[3:0]
    input  wire [ 3:0] btn,       // BTN[3:0] -- any rising edge increments
    output wire [ 3:0] led,       // LED[3:0]
    output reg  [ 6:0] seg,       // CG..CA, active low (Basys 3 convention)
    output wire [ 3:0] an         // anodes; we drive a single digit (an[0]=0) for simplicity
);
    // ── Switch passthrough ──────────────────────────────────────────
    assign led = sw;

    // ── Single active digit (rightmost) ────────────────────────────
    assign an = 4'b1110;

    // ── Button edge detector ────────────────────────────────────────
    reg [3:0] btn_prev;
    wire any_rising_edge = |(btn & ~btn_prev);

    // ── Internal 4-bit count ────────────────────────────────────────
    reg [3:0] count;

    always @(posedge clk or negedge rst_n) begin
        if (!rst_n) begin
            btn_prev <= 4'b0000;
            count    <= 4'd0;
        end else begin
            btn_prev <= btn;
            if (any_rising_edge) count <= count + 4'd1;
        end
    end

    // ── 4-bit -> 7-segment encoder (active-low, hexadecimal) ────────
    always @(*) begin
        case (count)
            4'h0: seg = 7'b1000000;
            4'h1: seg = 7'b1111001;
            4'h2: seg = 7'b0100100;
            4'h3: seg = 7'b0110000;
            4'h4: seg = 7'b0011001;
            4'h5: seg = 7'b0010010;
            4'h6: seg = 7'b0000010;
            4'h7: seg = 7'b1111000;
            4'h8: seg = 7'b0000000;
            4'h9: seg = 7'b0010000;
            4'hA: seg = 7'b0001000;
            4'hB: seg = 7'b0000011;
            4'hC: seg = 7'b1000110;
            4'hD: seg = 7'b0100001;
            4'hE: seg = 7'b0000110;
            4'hF: seg = 7'b0001110;
            default: seg = 7'b1111111;
        endcase
    end
endmodule

packs/stage-showcase-basys3/tb/tb_basys3.v
// SPDX-License-Identifier: CC-BY-4.0
// Copyright (c) 2026 Ferrite Engineering
//
// Drives the Basys 3 demo design with a sequence of switch flips and
// button presses, intended to look great when scrubbed in the WaveCrux
// Stage panel hosting the Basys 3 board widget.
//
// Timeline (approximate):
//   t=22       reset releases
//   t=100      sw <- 4'h5
//   t=300      btn[0] pressed (count -> 1)
//   t=600      btn[1] pressed (count -> 2)
//   t=900      sw <- 4'hA, btn[2] pressed (count -> 3)
//   t=1200     btn[3] pressed (count -> 4)
//   t=1500     btn[0] pressed again (count -> 5)
//   t=2000     sw <- 4'hF
//   t=2500     btn[0] pressed (count -> 6)
//   t=3000     finish

`timescale 1ns / 1ns

module tb_basys3;
    reg        clk;
    reg        rst_n;
    reg  [3:0] sw;
    reg  [3:0] btn;
    wire [3:0] led;
    wire [6:0] seg;
    wire [3:0] an;

    basys3_demo dut (
        .clk  (clk),
        .rst_n(rst_n),
        .sw   (sw),
        .btn  (btn),
        .led  (led),
        .seg  (seg),
        .an   (an)
    );

    initial clk = 1'b1;
    always #5 clk = ~clk;     // 100 MHz

    task press(input [3:0] mask);
        begin
            btn = btn | mask;
            #10;
            btn = btn & ~mask;
        end
    endtask

    initial begin
        $dumpfile("fixtures/reference.vcd");
        $dumpvars(0, tb_basys3);

        rst_n = 1'b0;
        sw    = 4'h0;
        btn   = 4'h0;
        #22;
        rst_n = 1'b1;

        #78;        sw = 4'h5;        // t=100
        #200;       press(4'b0001);   // t=300, count -> 1
        #290;       press(4'b0010);   // t=600, count -> 2
        #290;       sw = 4'hA; press(4'b0100);   // t=900, count -> 3
        #290;       press(4'b1000);   // t=1200, count -> 4
        #290;       press(4'b0001);   // t=1500, count -> 5
        #490;       sw = 4'hF;        // t=2000
        #490;       press(4'b0001);   // t=2500, count -> 6
        #500;
        $finish;
    end
endmodule

packs/stage-showcase-basys3/fixtures/reference.vcd
$date
	Sun May 31 15:04:28 2026
$end
$version
	Icarus Verilog
$end
$timescale
	1ns
$end
$scope module tb_basys3 $end
$var wire 4 ! an [3:0] $end
$var wire 7 " seg [6:0] $end
$var wire 4 # led [3:0] $end
$var reg 4 $ btn [3:0] $end
$var reg 1 % clk $end
$var reg 1 & rst_n $end
$var reg 4 ' sw [3:0] $end
$scope module dut $end
$var wire 4 ( an [3:0] $end
$var wire 4 ) btn [3:0] $end
$var wire 1 % clk $end
$var wire 4 * led [3:0] $end
$var wire 1 & rst_n $end
$var wire 4 + sw [3:0] $end
$var wire 1 , any_rising_edge $end
$var reg 4 - btn_prev [3:0] $end
$var reg 4 . count [3:0] $end
$var reg 7 / seg [6:0] $end
$upscope $end
$scope task press $end
$var reg 4 0 mask [3:0] $end
$upscope $end
$upscope $end
$enddefinitions $end
$comment Show the parameter values. $end
$dumpall
$end
#0
$dumpvars
bx 0
b1000000 /
b0 .
b0 -
0,
b0 +
b0 *
b0 )
b1110 (
b0 '
0&
1%
b0 $
b0 #
b1000000 "
b1110 !
$end
#5
0%
#10
1%
#15
0%
#20
1%
#22
1&
#25
0%
#30
1%
#35
0%
#40
1%
#45
0%
#50
1%
#55
0%
#60
1%
#65
0%
#70
1%
#75
0%
#80
1%
#85
0%
#90
1%
#95
0%
#100
1%
b101 #
b101 *
b101 '
b101 +
#105
0%
#110
1%
#115
0%
#120
1%
#125
0%
#130
1%
#135
0%
#140
1%
#145
0%
#150
1%
#155
0%
#160
1%
#165
0%
#170
1%
#175
0%
#180
1%
#185
0%
#190
1%
#195
0%
#200
1%
#205
0%
#210
1%
#215
0%
#220
1%
#225
0%
#230
1%
#235
0%
#240
1%
#245
0%
#250
1%
#255
0%
#260
1%
#265
0%
#270
1%
#275
0%
#280
1%
#285
0%
#290
1%
#295
0%
#300
b1111001 "
b1111001 /
b1 .
b1 -
0,
1%
b1 $
b1 )
b1 0
#305
0%
#310
b0 -
1%
b0 $
b0 )
#315
0%
#320
1%
#325
0%
#330
1%
#335
0%
#340
1%
#345
0%
#350
1%
#355
0%
#360
1%
#365
0%
#370
1%
#375
0%
#380
1%
#385
0%
#390
1%
#395
0%
#400
1%
#405
0%
#410
1%
#415
0%
#420
1%
#425
0%
#430
1%
#435
0%
#440
1%
#445
0%
#450
1%
#455
0%
#460
1%
#465
0%
#470
1%
#475
0%
#480
1%
#485
0%
#490
1%
#495
0%
#500
1%
#505
0%
#510
1%
#515
0%
#520
1%
#525
0%
#530
1%
#535
0%
#540
1%
#545
0%
#550
1%
#555
0%
#560
1%
#565
0%
#570
1%
#575
0%
#580
1%
#585
0%
#590
1%
#595
0%
#600
b100100 "
b100100 /
b10 .
b10 -
0,
1%
b10 $
b10 )
b10 0
#605
0%
#610
b0 -
1%
b0 $
b0 )
#615
0%
#620
1%
#625
0%
#630
1%
#635
0%
#640
1%
#645
0%
#650
1%
#655
0%
#660
1%
#665
0%
#670
1%
#675
0%
#680
1%
#685
0%
#690
1%
#695
0%
#700
1%
#705
0%
#710
1%
#715
0%
#720
1%
#725
0%
#730
1%
#735
0%
#740
1%
#745
0%
#750
1%
#755
0%
#760
1%
#765
0%
#770
1%
#775
0%
#780
1%
#785
0%
#790
1%
#795
0%
#800
1%
#805
0%
#810
1%
#815
0%
#820
1%
#825
0%
#830
1%
#835
0%
#840
1%
#845
0%
#850
1%
#855
0%
#860
1%
#865
0%
#870
1%
#875
0%
#880
1%
#885
0%
#890
1%
#895
0%
#900
b110000 "
b110000 /
b11 .
b100 -
0,
1%
b100 $
b100 )
b100 0
b1010 #
b1010 *
b1010 '
b1010 +
#905
0%
#910
b0 -
1%
b0 $
b0 )
