packs/debug-hunt/src/counter_buggy.v
// SPDX-License-Identifier: CC-BY-4.0
// Copyright (c) 2026 Ferrite Engineering
//
// Buggy implementation of an 8-bit synchronous counter. Looks
// suspiciously similar to the golden version — but contains a single-
// character bug. **Spoiler: the bug is on the enable-test line.**
//
// Do NOT consult `counter_golden.v` until after you have first tried
// to find the bug from the waveform diff alone.

`timescale 1ns / 1ns

module counter (
    input  wire       clk,
    input  wire       rst_n,
    input  wire       enable,
    output reg  [7:0] count
);
    always @(posedge clk or negedge rst_n) begin
        if (!rst_n)        count <= 8'd0;
        else if (~enable)  count <= count + 8'd1;   // <-- BUG
    end
endmodule

packs/debug-hunt/tb/tb_counter_buggy.v
// SPDX-License-Identifier: CC-BY-4.0
// Copyright (c) 2026 Ferrite Engineering
//
// Same stimulus as tb_counter_golden, but binds the *buggy* counter
// and dumps to fixtures/buggy.vcd. Identical stimulus + same VCD
// signal names is essential for the waveform diff to align.

`timescale 1ns / 1ns

module tb_counter_buggy;
    reg       clk;
    reg       rst_n;
    reg       enable;
    wire [7:0] count;

    counter dut (
        .clk   (clk),
        .rst_n (rst_n),
        .enable(enable),
        .count (count)
    );

    initial clk = 1'b1;
    always #5 clk = ~clk;

    initial begin
        $dumpfile("fixtures/buggy.vcd");
        $dumpvars(0, tb_counter_buggy);

        rst_n  = 1'b0;
        enable = 1'b0;
        #22;
        rst_n  = 1'b1;
        enable = 1'b1;
        #178;
        enable = 1'b0;
        #100;
        enable = 1'b1;
        #200;
        $finish;
    end
endmodule

packs/debug-hunt/fixtures/buggy.vcd
$date
	Sun May 31 15:01:00 2026
$end
$version
	Icarus Verilog
$end
$timescale
	1ns
$end
$scope module tb_counter_buggy $end
$var wire 8 ! count [7:0] $end
$var reg 1 " clk $end
$var reg 1 # enable $end
$var reg 1 $ rst_n $end
$scope module dut $end
$var wire 1 " clk $end
$var wire 1 # enable $end
$var wire 1 $ rst_n $end
$var reg 8 % count [7:0] $end
$upscope $end
$upscope $end
$enddefinitions $end
$comment Show the parameter values. $end
$dumpall
$end
#0
$dumpvars
b0 %
0$
0#
1"
b0 !
$end
#5
0"
#10
1"
#15
0"
#20
1"
#22
1#
1$
#25
0"
#30
1"
#35
0"
#40
1"
#45
0"
#50
1"
#55
0"
#60
1"
#65
0"
#70
1"
#75
0"
#80
1"
#85
0"
#90
1"
#95
0"
#100
1"
#105
0"
#110
1"
#115
0"
#120
1"
#125
0"
#130
1"
#135
0"
#140
1"
#145
0"
#150
1"
#155
0"
#160
1"
#165
0"
#170
1"
#175
0"
#180
1"
#185
0"
#190
1"
#195
0"
#200
b1 !
b1 %
1"
0#
#205
0"
#210
b10 !
b10 %
1"
#215
0"
#220
b11 !
b11 %
1"
#225
0"
#230
b100 !
b100 %
1"
#235
0"
#240
b101 !
b101 %
1"
#245
0"
#250
b110 !
b110 %
1"
#255
0"
#260
b111 !
b111 %
1"
#265
0"
#270
b1000 !
b1000 %
1"
#275
0"
#280
b1001 !
b1001 %
1"
#285
0"
#290
b1010 !
b1010 %
1"
#295
0"
#300
1"
1#
