packs/debug-hunt/src/counter_buggy.v
// SPDX-License-Identifier: CC-BY-4.0
// Copyright (c) 2026 Ferrite Engineering
//
// Buggy implementation of an 8-bit synchronous counter. Looks
// suspiciously similar to the golden version — but contains a single-
// character bug. **Spoiler: the bug is on the enable-test line.**
//
// Do NOT consult `counter_golden.v` until after you have first tried
// to find the bug from the waveform diff alone.

`timescale 1ns / 1ns

module counter (
    input  wire       clk,
    input  wire       rst_n,
    input  wire       enable,
    output reg  [7:0] count
);
    always @(posedge clk or negedge rst_n) begin
        if (!rst_n)        count <= 8'd0;
        else if (~enable)  count <= count + 8'd1;   // <-- BUG
    end
endmodule

packs/debug-hunt/tb/tb_counter_golden.v
// SPDX-License-Identifier: CC-BY-4.0
// Copyright (c) 2026 Ferrite Engineering
//
// Stimulus for the golden counter. 100 MHz clock, reset until t=22 ns,
// `enable` toggles partway through to exercise both behaviours.

`timescale 1ns / 1ns

module tb_counter_golden;
    reg       clk;
    reg       rst_n;
    reg       enable;
    wire [7:0] count;

    counter dut (
        .clk   (clk),
        .rst_n (rst_n),
        .enable(enable),
        .count (count)
    );

    initial clk = 1'b1;
    always #5 clk = ~clk;

    initial begin
        $dumpfile("fixtures/golden.vcd");
        $dumpvars(0, tb_counter_golden);

        rst_n  = 1'b0;
        enable = 1'b0;
        #22;
        rst_n  = 1'b1;
        enable = 1'b1;
        #178;            // count from 0x01 to ~0x12 with enable=1
        enable = 1'b0;
        #100;            // hold for 100 ns; counter should NOT advance
        enable = 1'b1;
        #200;            // resume counting
        $finish;
    end
endmodule

packs/debug-hunt/fixtures/golden.vcd
$date
	Fri Jul 24 11:40:46 2026
$end
$version
	Icarus Verilog
$end
$timescale
	1ns
$end
$scope module tb_counter_golden $end
$var wire 8 ! count [7:0] $end
$var reg 1 " clk $end
$var reg 1 # enable $end
$var reg 1 $ rst_n $end
$scope module dut $end
$var wire 1 " clk $end
$var wire 1 # enable $end
$var wire 1 $ rst_n $end
$var reg 8 % count [7:0] $end
$upscope $end
$upscope $end
$enddefinitions $end
$comment Show the parameter values. $end
$dumpall
$end
#0
$dumpvars
b0 %
0$
0#
1"
b0 !
$end
#5
0"
#10
1"
#15
0"
#20
1"
#22
1#
1$
#25
0"
#30
b1 !
b1 %
1"
#35
0"
#40
b10 !
b10 %
1"
#45
0"
#50
b11 !
b11 %
1"
#55
0"
#60
b100 !
b100 %
1"
#65
0"
#70
b101 !
b101 %
1"
#75
0"
#80
b110 !
b110 %
1"
#85
0"
#90
b111 !
b111 %
1"
#95
0"
#100
b1000 !
b1000 %
1"
#105
0"
#110
b1001 !
b1001 %
1"
#115
0"
#120
b1010 !
b1010 %
1"
#125
0"
#130
b1011 !
b1011 %
1"
#135
0"
#140
b1100 !
b1100 %
1"
#145
0"
#150
b1101 !
b1101 %
1"
#155
0"
#160
b1110 !
b1110 %
1"
#165
0"
#170
b1111 !
b1111 %
1"
#175
0"
#180
b10000 !
b10000 %
1"
#185
0"
#190
b10001 !
b10001 %
1"
#195
0"
#200
1"
0#
#205
0"
#210
1"
#215
0"
#220
1"
#225
0"
#230
1"
#235
0"
#240
1"
#245
0"
#250
1"
#255
0"
#260
1"
#265
0"
#270
1"
#275
0"
#280
1"
#285
0"
#290
1"
#295
0"
#300
b10010 !
b10010 %
1"
1#
#305
0"
#310
b10011 !
b10011 %
1"
#315
0"
#320
b10100 !
b10100 %
1"
#325
0"
#330
b10101 !
b10101 %
1"
#335
0"
#340
b10110 !
b10110 %
1"
#345
0"
#350
b10111 !
b10111 %
1"
#355
0"
#360
b11000 !
b11000 %
1"
#365
0"
#370
b11001 !
b11001 %
1"
#375
0"
#380
b11010 !
b11010 %
1"
#385
0"
#390
b11011 !
b11011 %
1"
#395
0"
#400
b11100 !
b11100 %
1"
#405
0"
#410
b11101 !
b11101 %
1"
#415
0"
#420
b11110 !
b11110 %
1"
#425
0"
#430
b11111 !
b11111 %
1"
#435
0"
#440
b100000 !
b100000 %
1"
#445
0"
#450
b100001 !
b100001 %
1"
#455
0"
#460
b100010 !
b100010 %
1"
#465
0"
#470
b100011 !
b100011 %
1"
#475
0"
#480
b100100 !
b100100 %
1"
#485
0"
#490
b100101 !
b100101 %
1"
#495
0"
#500
b100110 !
b100110 %
1"
