packs/axi4-lite-peripheral/src/axil_register_peripheral.v
// SPDX-License-Identifier: CC-BY-4.0
// Copyright (c) 2026 Ferrite Engineering
//
// Minimal AXI4-Lite register peripheral. Eight 32-bit registers
// mapped at word offsets 0x00..0x1C (byte addresses 0x00, 0x04, ...,
// 0x1C). Any access beyond the mapped range returns SLVERR
// (BRESP / RRESP = 2'b10).
//
// Tightly-coupled handshakes:
//   * AWREADY and WREADY are tied high; the slave always accepts
//     address+data on the cycle they are presented.
//   * The write response (BVALID) is asserted one cycle after the
//     write completes; BREADY must be high to clear it.
//   * Read response (RVALID) is asserted one cycle after the read
//     address is accepted; RREADY must be high to clear it.

`timescale 1ns / 1ns

module axil_register_peripheral (
    input  wire        aclk,
    input  wire        aresetn,

    // Write address channel
    input  wire [31:0] awaddr,
    input  wire        awvalid,
    output wire        awready,

    // Write data channel
    input  wire [31:0] wdata,
    input  wire [ 3:0] wstrb,
    input  wire        wvalid,
    output wire        wready,

    // Write response channel
    output reg  [ 1:0] bresp,
    output reg         bvalid,
    input  wire        bready,

    // Read address channel
    input  wire [31:0] araddr,
    input  wire        arvalid,
    output wire        arready,

    // Read data channel
    output reg  [31:0] rdata,
    output reg  [ 1:0] rresp,
    output reg         rvalid,
    input  wire        rready
);
    localparam [1:0] RESP_OKAY   = 2'b00;
    localparam [1:0] RESP_SLVERR = 2'b10;

    reg [31:0] regs [0:7];

    assign awready = 1'b1;
    assign wready  = 1'b1;
    assign arready = ~rvalid;     // accept new address only when last R is consumed

    wire        write_handshake = awvalid & wvalid;
    wire [31:0] write_addr      = awaddr;
    wire        addr_in_range_w = (write_addr[31:5] == 27'h0);
    wire [ 2:0] word_idx_w      = write_addr[4:2];

    wire        read_handshake  = arvalid & arready;
    wire        addr_in_range_r = (araddr[31:5] == 27'h0);
    wire [ 2:0] word_idx_r      = araddr[4:2];

    integer i;
    always @(posedge aclk) begin
        if (!aresetn) begin
            for (i = 0; i < 8; i = i + 1) regs[i] <= 32'h0;
            bresp  <= 2'b00;
            bvalid <= 1'b0;
            rdata  <= 32'h0;
            rresp  <= 2'b00;
            rvalid <= 1'b0;
        end else begin
            // Write side
            if (write_handshake && !bvalid) begin
                if (addr_in_range_w) begin
                    if (wstrb[0]) regs[word_idx_w][ 7: 0] <= wdata[ 7: 0];
                    if (wstrb[1]) regs[word_idx_w][15: 8] <= wdata[15: 8];
                    if (wstrb[2]) regs[word_idx_w][23:16] <= wdata[23:16];
                    if (wstrb[3]) regs[word_idx_w][31:24] <= wdata[31:24];
                    bresp <= RESP_OKAY;
                end else begin
                    bresp <= RESP_SLVERR;
                end
                bvalid <= 1'b1;
            end else if (bvalid && bready) begin
                bvalid <= 1'b0;
            end

            // Read side
            if (read_handshake) begin
                if (addr_in_range_r) begin
                    rdata <= regs[word_idx_r];
                    rresp <= RESP_OKAY;
                end else begin
                    rdata <= 32'hDEAD_BEEF;     // sentinel for unmapped reads
                    rresp <= RESP_SLVERR;
                end
                rvalid <= 1'b1;
            end else if (rvalid && rready) begin
                rvalid <= 1'b0;
            end
        end
    end
endmodule

packs/axi4-lite-peripheral/src/axil_master.v
// SPDX-License-Identifier: CC-BY-4.0
// Copyright (c) 2026 Ferrite Engineering
//
// Minimal AXI4-Lite master. After reset releases, it executes a fixed
// sequence:
//   1. WRITE addr=0x00 data=0xA0A0_0000     (in range, expect OKAY)
//   2. WRITE addr=0x04 data=0xB1B1_1111     (in range, expect OKAY)
//   3. WRITE addr=0xFC data=0xDEAD_C0DE     (out of range, expect SLVERR)
//   4. READ  addr=0x00                       (in range, expect OKAY, data=0xA0A0_0000)
//   5. READ  addr=0x80                       (out of range, expect SLVERR)
// then asserts done.

`timescale 1ns / 1ns

module axil_master (
    input  wire        aclk,
    input  wire        aresetn,

    output reg  [31:0] awaddr,
    output reg         awvalid,
    input  wire        awready,

    output reg  [31:0] wdata,
    output reg  [ 3:0] wstrb,
    output reg         wvalid,
    input  wire        wready,

    input  wire [ 1:0] bresp,
    input  wire        bvalid,
    output reg         bready,

    output reg  [31:0] araddr,
    output reg         arvalid,
    input  wire        arready,

    input  wire [31:0] rdata,
    input  wire [ 1:0] rresp,
    input  wire        rvalid,
    output reg         rready,

    output reg  [ 1:0] last_bresp,
    output reg  [ 1:0] last_rresp,
    output reg  [31:0] last_rdata,
    output reg         done
);
    localparam [3:0]
        S_IDLE       = 4'd0,
        S_WR1_REQ    = 4'd1,
        S_WR1_RESP   = 4'd2,
        S_WR2_REQ    = 4'd3,
        S_WR2_RESP   = 4'd4,
        S_WR3_REQ    = 4'd5,
        S_WR3_RESP   = 4'd6,
        S_RD1_REQ    = 4'd7,
        S_RD1_RESP   = 4'd8,
        S_RD2_REQ    = 4'd9,
        S_RD2_RESP   = 4'd10,
        S_DONE       = 4'd11;

    reg [3:0] state;

    task do_write_req(input [31:0] addr, input [31:0] data);
        begin
            awaddr  <= addr;
            awvalid <= 1'b1;
            wdata   <= data;
            wstrb   <= 4'hF;
            wvalid  <= 1'b1;
        end
    endtask

    task do_read_req(input [31:0] addr);
        begin
            araddr  <= addr;
            arvalid <= 1'b1;
        end
    endtask

    always @(posedge aclk) begin
        if (!aresetn) begin
            awaddr     <= 32'h0;
            awvalid    <= 1'b0;
            wdata      <= 32'h0;
            wstrb      <= 4'h0;
            wvalid     <= 1'b0;
            bready     <= 1'b0;
            araddr     <= 32'h0;
            arvalid    <= 1'b0;
            rready     <= 1'b0;
            last_bresp <= 2'b00;
            last_rresp <= 2'b00;
            last_rdata <= 32'h0;
            done       <= 1'b0;
            state      <= S_WR1_REQ;
        end else begin
            // Default deassertions; specific states override
            bready <= 1'b0;
            rready <= 1'b0;

            case (state)
                S_WR1_REQ: begin
                    do_write_req(32'h0000_0000, 32'hA0A0_0000);
                    if (awvalid && awready && wvalid && wready) begin
                        // Both address and data accepted in the same cycle.
                        awvalid <= 1'b0;
                        wvalid  <= 1'b0;
                        bready  <= 1'b1;
                        state   <= S_WR1_RESP;
                    end
                end
                S_WR1_RESP: begin
                    bready <= 1'b1;
                    if (bvalid && bready) begin
                        last_bresp <= bresp;
                        bready     <= 1'b0;
                        state      <= S_WR2_REQ;
                    end
                end

                S_WR2_REQ: begin
                    do_write_req(32'h0000_0004, 32'hB1B1_1111);
                    if (awvalid && awready && wvalid && wready) begin
                        awvalid <= 1'b0;
                        wvalid  <= 1'b0;
                        bready  <= 1'b1;
                        state   <= S_WR2_RESP;
                    end
                end
                S_WR2_RESP: begin
                    bready <= 1'b1;
                    if (bvalid && bready) begin
                        last_bresp <= bresp;
                        bready     <= 1'b0;
                        state      <= S_WR3_REQ;
                    end
                end

                S_WR3_REQ: begin
                    do_write_req(32'h0000_00FC, 32'hDEAD_C0DE); // unmapped
                    if (awvalid && awready && wvalid && wready) begin
                        awvalid <= 1'b0;
                        wvalid  <= 1'b0;
                        bready  <= 1'b1;
                        state   <= S_WR3_RESP;
                    end
                end
                S_WR3_RESP: begin
                    bready <= 1'b1;
                    if (bvalid && bready) begin
                        last_bresp <= bresp;
                        bready     <= 1'b0;
                        state      <= S_RD1_REQ;
                    end
                end

                S_RD1_REQ: begin
                    do_read_req(32'h0000_0000);
                    if (arvalid && arready) begin
                        arvalid <= 1'b0;
                        rready  <= 1'b1;
                        state   <= S_RD1_RESP;
                    end
                end
                S_RD1_RESP: begin
                    rready <= 1'b1;
                    if (rvalid && rready) begin
                        last_rresp <= rresp;
                        last_rdata <= rdata;
                        rready     <= 1'b0;
                        state      <= S_RD2_REQ;
                    end
                end

                S_RD2_REQ: begin
                    do_read_req(32'h0000_0080); // unmapped
                    if (arvalid && arready) begin
                        arvalid <= 1'b0;
                        rready  <= 1'b1;
                        state   <= S_RD2_RESP;
                    end
                end
                S_RD2_RESP: begin
                    rready <= 1'b1;
                    if (rvalid && rready) begin
                        last_rresp <= rresp;
                        last_rdata <= rdata;
                        rready     <= 1'b0;
                        state      <= S_DONE;
                    end
                end

                S_DONE: begin
                    done <= 1'b1;
                end

                default: state <= S_DONE;
            endcase
        end
    end
endmodule

packs/axi4-lite-peripheral/tb/tb_axil.v
// SPDX-License-Identifier: CC-BY-4.0
// Copyright (c) 2026 Ferrite Engineering
//
// AXI4-Lite master + register peripheral testbench. 100 MHz aclk,
// active-low aresetn.

`timescale 1ns / 1ns

module tb_axil;
    reg         aclk;
    reg         aresetn;

    wire [31:0] awaddr;
    wire        awvalid;
    wire        awready;
    wire [31:0] wdata;
    wire [ 3:0] wstrb;
    wire        wvalid;
    wire        wready;
    wire [ 1:0] bresp;
    wire        bvalid;
    wire        bready;
    wire [31:0] araddr;
    wire        arvalid;
    wire        arready;
    wire [31:0] rdata;
    wire [ 1:0] rresp;
    wire        rvalid;
    wire        rready;

    wire [ 1:0] last_bresp;
    wire [ 1:0] last_rresp;
    wire [31:0] last_rdata;
    wire        done;

    axil_master u_master (
        .aclk      (aclk),
        .aresetn   (aresetn),
        .awaddr    (awaddr),
        .awvalid   (awvalid),
        .awready   (awready),
        .wdata     (wdata),
        .wstrb     (wstrb),
        .wvalid    (wvalid),
        .wready    (wready),
        .bresp     (bresp),
        .bvalid    (bvalid),
        .bready    (bready),
        .araddr    (araddr),
        .arvalid   (arvalid),
        .arready   (arready),
        .rdata     (rdata),
        .rresp     (rresp),
        .rvalid    (rvalid),
        .rready    (rready),
        .last_bresp(last_bresp),
        .last_rresp(last_rresp),
        .last_rdata(last_rdata),
        .done      (done)
    );

    axil_register_peripheral u_slave (
        .aclk   (aclk),
        .aresetn(aresetn),
        .awaddr (awaddr),
        .awvalid(awvalid),
        .awready(awready),
        .wdata  (wdata),
        .wstrb  (wstrb),
        .wvalid (wvalid),
        .wready (wready),
        .bresp  (bresp),
        .bvalid (bvalid),
        .bready (bready),
        .araddr (araddr),
        .arvalid(arvalid),
        .arready(arready),
        .rdata  (rdata),
        .rresp  (rresp),
        .rvalid (rvalid),
        .rready (rready)
    );

    initial aclk = 1'b1;
    always #5 aclk = ~aclk;

    initial begin
        $dumpfile("fixtures/reference.vcd");
        $dumpvars(0, tb_axil);

        aresetn = 1'b0;
        #22;
        aresetn = 1'b1;
        #978;
        $finish;
    end
endmodule

packs/axi4-lite-peripheral/fixtures/reference.vcd
$date
	Sun May 31 14:51:40 2026
$end
$version
	Icarus Verilog
$end
$timescale
	1ns
$end
$scope module tb_axil $end
$var wire 1 ! awready $end
$var wire 1 " wready $end
$var wire 1 # wvalid $end
$var wire 4 $ wstrb [3:0] $end
$var wire 32 % wdata [31:0] $end
$var wire 1 & rvalid $end
$var wire 2 ' rresp [1:0] $end
$var wire 1 ( rready $end
$var wire 32 ) rdata [31:0] $end
$var wire 2 * last_rresp [1:0] $end
$var wire 32 + last_rdata [31:0] $end
$var wire 2 , last_bresp [1:0] $end
$var wire 1 - done $end
$var wire 1 . bvalid $end
$var wire 2 / bresp [1:0] $end
$var wire 1 0 bready $end
$var wire 1 1 awvalid $end
$var wire 32 2 awaddr [31:0] $end
$var wire 1 3 arvalid $end
$var wire 1 4 arready $end
$var wire 32 5 araddr [31:0] $end
$var reg 1 6 aclk $end
$var reg 1 7 aresetn $end
$scope module u_master $end
$var wire 1 6 aclk $end
$var wire 1 7 aresetn $end
$var wire 1 ! awready $end
$var wire 1 " wready $end
$var wire 1 & rvalid $end
$var wire 2 8 rresp [1:0] $end
$var wire 32 9 rdata [31:0] $end
$var wire 1 . bvalid $end
$var wire 2 : bresp [1:0] $end
$var wire 1 4 arready $end
$var parameter 4 ; S_DONE $end
$var parameter 4 < S_IDLE $end
$var parameter 4 = S_RD1_REQ $end
$var parameter 4 > S_RD1_RESP $end
$var parameter 4 ? S_RD2_REQ $end
$var parameter 4 @ S_RD2_RESP $end
$var parameter 4 A S_WR1_REQ $end
$var parameter 4 B S_WR1_RESP $end
$var parameter 4 C S_WR2_REQ $end
$var parameter 4 D S_WR2_RESP $end
$var parameter 4 E S_WR3_REQ $end
$var parameter 4 F S_WR3_RESP $end
$var reg 32 G araddr [31:0] $end
$var reg 1 3 arvalid $end
$var reg 32 H awaddr [31:0] $end
$var reg 1 1 awvalid $end
$var reg 1 0 bready $end
$var reg 1 - done $end
$var reg 2 I last_bresp [1:0] $end
$var reg 32 J last_rdata [31:0] $end
$var reg 2 K last_rresp [1:0] $end
$var reg 1 ( rready $end
$var reg 4 L state [3:0] $end
$var reg 32 M wdata [31:0] $end
$var reg 4 N wstrb [3:0] $end
$var reg 1 # wvalid $end
$scope task do_read_req $end
$var reg 32 O addr [31:0] $end
$upscope $end
$scope task do_write_req $end
$var reg 32 P addr [31:0] $end
$var reg 32 Q data [31:0] $end
$upscope $end
$upscope $end
$scope module u_slave $end
$var wire 1 6 aclk $end
$var wire 32 R araddr [31:0] $end
$var wire 1 7 aresetn $end
$var wire 1 4 arready $end
$var wire 1 3 arvalid $end
$var wire 32 S awaddr [31:0] $end
$var wire 1 ! awready $end
$var wire 1 1 awvalid $end
$var wire 1 0 bready $end
$var wire 1 T read_handshake $end
$var wire 1 ( rready $end
$var wire 32 U wdata [31:0] $end
$var wire 1 " wready $end
$var wire 32 V write_addr [31:0] $end
$var wire 1 W write_handshake $end
$var wire 4 X wstrb [3:0] $end
$var wire 1 # wvalid $end
$var wire 3 Y word_idx_w [2:0] $end
$var wire 3 Z word_idx_r [2:0] $end
$var wire 1 [ addr_in_range_w $end
$var wire 1 \ addr_in_range_r $end
$var parameter 2 ] RESP_OKAY $end
$var parameter 2 ^ RESP_SLVERR $end
$var reg 2 _ bresp [1:0] $end
$var reg 1 . bvalid $end
$var reg 32 ` rdata [31:0] $end
$var reg 2 a rresp [1:0] $end
$var reg 1 & rvalid $end
$var integer 32 b i [31:0] $end
$upscope $end
$upscope $end
$enddefinitions $end
$comment Show the parameter values. $end
$dumpall
b10 ^
b0 ]
b110 F
b101 E
b100 D
b11 C
b10 B
b1 A
b1010 @
b1001 ?
b1000 >
b111 =
b0 <
b1011 ;
$end
#0
$dumpvars
b1000 b
b0 a
b0 `
b0 _
1\
1[
b0 Z
b0 Y
b0 X
0W
b0 V
b0 U
0T
b0 S
b0 R
bx Q
bx P
bx O
b0 N
b0 M
b1 L
b0 K
b0 J
b0 I
b0 H
b0 G
b0 :
b0 9
b0 8
07
16
b0 5
14
03
b0 2
01
00
b0 /
0.
0-
b0 ,
b0 +
b0 *
b0 )
0(
b0 '
0&
b0 %
b0 $
0#
1"
1!
$end
#5
06
#10
b1000 b
16
#15
06
#20
b1000 b
16
#22
17
#25
06
#30
1W
1#
b1111 $
b1111 N
b1111 X
b10100000101000000000000000000000 %
b10100000101000000000000000000000 M
b10100000101000000000000000000000 U
11
b10100000101000000000000000000000 Q
b0 P
16
#35
06
#40
0W
b10 L
10
0#
01
1.
16
#45
06
#50
0.
b11 L
00
16
#55
06
#60
1W
b1 Y
1#
b10110001101100010001000100010001 %
b10110001101100010001000100010001 M
b10110001101100010001000100010001 U
11
b100 V
b100 2
b100 H
b100 S
b10110001101100010001000100010001 Q
b100 P
16
#65
06
#70
0W
b100 L
10
0#
01
1.
16
#75
06
#80
0.
b101 L
00
16
#85
06
#90
1W
0[
b111 Y
1#
b11011110101011011100000011011110 %
b11011110101011011100000011011110 M
b11011110101011011100000011011110 U
11
b11111100 V
b11111100 2
b11111100 H
b11111100 S
b11011110101011011100000011011110 Q
b11111100 P
16
#95
06
#100
0W
b110 L
10
0#
01
1.
b10 /
b10 :
b10 _
16
#105
06
#110
0.
b111 L
b10 ,
b10 I
00
16
#115
06
#120
1T
13
b0 O
16
#125
06
#130
0T
04
b1000 L
1(
03
1&
b10100000101000000000000000000000 )
b10100000101000000000000000000000 9
b10100000101000000000000000000000 `
16
#135
06
#140
14
0&
b1001 L
b10100000101000000000000000000000 +
b10100000101000000000000000000000 J
0(
16
#145
06
#150
1T
0\
13
b10000000 5
b10000000 G
b10000000 R
b10000000 O
16
#155
06
#160
0T
04
b1010 L
1(
03
1&
b10 '
b10 8
b10 a
b11011110101011011011111011101111 )
b11011110101011011011111011101111 9
b11011110101011011011111011101111 `
16
#165
06
#170
14
0&
b1011 L
b11011110101011011011111011101111 +
b11011110101011011011111011101111 J
b10 *
b10 K
0(
16
#175
06
#180
1-
16
