packs/verification-methodology-capstone/src/alu8.v
module alu8 (input [7:0] a, b, input [1:0] op, output reg [7:0] y);
  always @(*) case(op) 2'd0:y=a+b; 2'd1:y=a-b; 2'd2:y=a&b; default:y=a|b; endcase
endmodule

packs/verification-methodology-capstone/src/reg4.v
`timescale 1ns/1ns
// Register-mapped ALU peripheral. Write operands to regs, write an opcode to
// CTRL, read the result. Integrates a decoder, a register file and an ALU — a
// small but complete unit for a full verification-methodology pass.

module reg4 (input clk, rst_n, we, input [7:0] d, output reg [7:0] q);
  always @(posedge clk or negedge rst_n) if(!rst_n) q<=8'h0; else if(we) q<=d;
endmodule

packs/verification-methodology-capstone/src/decoder.v
module decoder (input [7:0] addr, output sel_a, sel_b, sel_ctrl);
  assign sel_a    = (addr[7:4]==4'h0);
  assign sel_b    = (addr[7:4]==4'h1);
  assign sel_ctrl = (addr[7:4]==4'h2);
endmodule

packs/verification-methodology-capstone/src/alu_periph.v
module alu_periph (
    input clk, rst_n, we, input [7:0] addr, wdata, output [7:0] result
);
  wire sel_a, sel_b, sel_ctrl;
  wire [7:0] opa, opb, ctrl;
  reg  [7:0] spare;                     // UNUSED scratch (a lint finding)

  decoder u_dec (.addr(addr), .sel_a(sel_a), .sel_b(sel_b), .sel_ctrl(sel_ctrl));
  reg4 u_ra   (.clk(clk), .rst_n(rst_n), .we(we&sel_a),    .d(wdata), .q(opa));
  reg4 u_rb   (.clk(clk), .rst_n(rst_n), .we(we&sel_b),    .d(wdata), .q(opb));
  reg4 u_ctrl (.clk(clk), .rst_n(rst_n), .we(we&sel_ctrl), .d(wdata), .q(ctrl));
  alu8 u_alu  (.a(opa), .b(opb), .op(ctrl[1:0]), .y(result));
endmodule

packs/verification-methodology-capstone/tb/tb_alu_periph.v
`timescale 1ns/1ns
module tb_alu_periph;
  reg clk=0, rst_n=0, we=0; reg [7:0] addr, wdata; wire [7:0] result;
  alu_periph dut (.clk(clk),.rst_n(rst_n),.we(we),.addr(addr),.wdata(wdata),.result(result));
  always #5 clk=~clk;

  task wr(input [7:0] a, input [7:0] d);
    begin @(negedge clk); addr=a; wdata=d; we=1; @(negedge clk); we=0; end
  endtask
  task op_check(input [127:0] nm, input [7:0] a, b, input [7:0] opcode, input [7:0] want);
    begin
      wr(8'h00, a); wr(8'h10, b); wr(8'h20, opcode); #20;
      if (result===want) $display("RESULT %0s PASS", nm);
      else               $display("RESULT %0s FAIL a=%0d b=%0d op=%0d got=%0d want=%0d", nm, a, b, opcode, result, want);
    end
  endtask

  initial begin
    $dumpfile("fixtures/reference.vcd"); $dumpvars(0, tb_alu_periph);
    #20 rst_n=1; #20;
    op_check("add", 8'd10, 8'd7, 8'd0, 8'd17);
    op_check("sub", 8'd20, 8'd6, 8'd1, 8'd14);
    op_check("and", 8'hF0, 8'h3C, 8'd2, 8'h30);
    op_check("or",  8'hF0, 8'h0C, 8'd3, 8'hFC);
    #40 $finish;
  end
endmodule

packs/verification-methodology-capstone/fixtures/reference.vcd
$date
	Fri Jul 24 11:54:37 2026
$end
$version
	Icarus Verilog
$end
$timescale
	1ns
$end
$scope module tb_alu_periph $end
$var wire 8 ! result [7:0] $end
$var reg 8 " addr [7:0] $end
$var reg 1 # clk $end
$var reg 1 $ rst_n $end
$var reg 8 % wdata [7:0] $end
$var reg 1 & we $end
$scope module dut $end
$var wire 8 ' addr [7:0] $end
$var wire 1 # clk $end
$var wire 1 $ rst_n $end
$var wire 8 ( wdata [7:0] $end
$var wire 1 & we $end
$var wire 1 ) sel_ctrl $end
$var wire 1 * sel_b $end
$var wire 1 + sel_a $end
$var wire 8 , result [7:0] $end
$var wire 8 - opb [7:0] $end
$var wire 8 . opa [7:0] $end
$var wire 8 / ctrl [7:0] $end
$scope module u_alu $end
$var wire 2 0 op [1:0] $end
$var wire 8 1 b [7:0] $end
$var wire 8 2 a [7:0] $end
$var reg 8 3 y [7:0] $end
$upscope $end
$scope module u_ctrl $end
$var wire 1 # clk $end
$var wire 8 4 d [7:0] $end
$var wire 1 $ rst_n $end
$var wire 1 5 we $end
$var reg 8 6 q [7:0] $end
$upscope $end
$scope module u_dec $end
$var wire 8 7 addr [7:0] $end
$var wire 1 ) sel_ctrl $end
$var wire 1 * sel_b $end
$var wire 1 + sel_a $end
$upscope $end
$scope module u_ra $end
$var wire 1 # clk $end
$var wire 8 8 d [7:0] $end
$var wire 1 $ rst_n $end
$var wire 1 9 we $end
$var reg 8 : q [7:0] $end
$upscope $end
$scope module u_rb $end
$var wire 1 # clk $end
$var wire 8 ; d [7:0] $end
$var wire 1 $ rst_n $end
$var wire 1 < we $end
$var reg 8 = q [7:0] $end
$upscope $end
$upscope $end
$scope task op_check $end
$var reg 8 > a [7:0] $end
$var reg 8 ? b [7:0] $end
$var reg 128 @ nm [127:0] $end
$var reg 8 A opcode [7:0] $end
$var reg 8 B want [7:0] $end
$upscope $end
$scope task wr $end
$var reg 8 C a [7:0] $end
$var reg 8 D d [7:0] $end
$upscope $end
$upscope $end
$enddefinitions $end
$comment Show the parameter values. $end
$dumpall
$end
#0
$dumpvars
bx D
bx C
bx B
bx A
bx @
bx ?
bx >
bx =
0<
bx ;
bx :
09
bx 8
bx 7
bx 6
05
bx 4
bx 3
bx 2
bx 1
bx 0
bx /
bx .
bx -
bx ,
x+
x*
x)
bx (
bx '
0&
bx %
0$
0#
bx "
bx !
$end
#5
b0 !
b0 ,
b0 3
b0 0
b0 .
b0 2
b0 :
b0 -
b0 1
b0 =
b0 /
b0 6
1#
#10
0#
#15
1#
#20
0#
1$
#25
1#
#30
0#
#35
1#
#40
19
1+
0*
0)
1&
b1010 %
b1010 (
b1010 4
b1010 8
b1010 ;
b0 "
b0 '
b0 7
0#
b1010 D
b0 C
b10001 B
b0 A
b111 ?
b1010 >
b11000010110010001100100 @
#45
b1010 !
b1010 ,
b1010 3
b1010 .
b1010 2
b1010 :
1#
#50
09
b111 D
b10000 C
0&
0#
#55
1#
#60
1<
0+
1*
1&
b111 %
b111 (
b111 4
b111 8
b111 ;
b10000 "
b10000 '
b10000 7
0#
#65
b10001 !
b10001 ,
b10001 3
b111 -
b111 1
b111 =
1#
#70
0<
b0 D
b100000 C
0&
0#
#75
1#
#80
15
0*
1)
1&
b0 %
b0 (
b0 4
b0 8
b0 ;
b100000 "
b100000 '
b100000 7
0#
#85
1#
#90
05
0&
0#
#95
1#
#100
0#
#105
1#
#110
19
1+
0)
1&
b10100 %
b10100 (
b10100 4
b10100 8
b10100 ;
b0 "
b0 '
b0 7
0#
b10100 D
b0 C
b1110 B
b1 A
b110 ?
b10100 >
b11100110111010101100010 @
#115
b11011 !
b11011 ,
b11011 3
b10100 .
b10100 2
b10100 :
1#
#120
09
b110 D
b10000 C
0&
0#
#125
1#
#130
1<
0+
1*
1&
b110 %
b110 (
b110 4
b110 8
b110 ;
b10000 "
b10000 '
b10000 7
0#
#135
b11010 !
b11010 ,
b11010 3
b110 -
b110 1
b110 =
1#
#140
0<
b1 D
b100000 C
0&
0#
#145
1#
#150
15
0*
1)
1&
b1 %
b1 (
b1 4
b1 8
b1 ;
b100000 "
b100000 '
b100000 7
0#
#155
b1110 !
b1110 ,
b1110 3
b1 0
b1 /
b1 6
1#
#160
05
0&
0#
#165
1#
#170
0#
#175
1#
#180
19
1+
0)
1&
b11110000 %
b11110000 (
b11110000 4
b11110000 8
b11110000 ;
b0 "
b0 '
b0 7
0#
b11110000 D
b0 C
b110000 B
b10 A
b111100 ?
b11110000 >
b11000010110111001100100 @
#185
b11101010 !
b11101010 ,
b11101010 3
b11110000 .
b11110000 2
b11110000 :
1#
#190
09
b111100 D
b10000 C
0&
0#
#195
1#
#200
1<
0+
1*
1&
b111100 %
b111100 (
b111100 4
b111100 8
b111100 ;
b10000 "
b10000 '
b10000 7
0#
#205
b10110100 !
b10110100 ,
b10110100 3
b111100 -
b111100 1
b111100 =
1#
#210
0<
b10 D
b100000 C
0&
0#
#215
1#
#220
15
0*
1)
1&
b10 %
b10 (
b10 4
b10 8
b10 ;
b100000 "
b100000 '
b100000 7
0#
#225
b110000 !
b110000 ,
b110000 3
b10 0
b10 /
b10 6
1#
#230
05
0&
0#
#235
1#
#240
0#
#245
1#
#250
19
1+
0)
1&
b11110000 %
b11110000 (
b11110000 4
b11110000 8
b11110000 ;
b0 "
b0 '
b0 7
0#
b11110000 D
b0 C
b11111100 B
b11 A
b1100 ?
b110111101110010 @
#255
1#
#260
09
b1100 D
b10000 C
0&
0#
#265
1#
#270
1<
0+
1*
1&
b1100 %
b1100 (
b1100 4
b1100 8
b1100 ;
b10000 "
b10000 '
b10000 7
0#
#275
b0 !
b0 ,
b0 3
b1100 -
b1100 1
b1100 =
1#
#280
0<
b11 D
b100000 C
0&
0#
#285
1#
#290
15
0*
1)
1&
b11 %
b11 (
b11 4
b11 8
b11 ;
b100000 "
b100000 '
b100000 7
0#
#295
b11111100 !
b11111100 ,
b11111100 3
b11 0
b11 /
b11 6
1#
#300
05
0&
0#
