packs/shift-register-patterns/src/lfsr5.v
// SPDX-License-Identifier: CC-BY-4.0
// Copyright (c) 2026 Ferrite Engineering
//
// 5-bit maximum-length linear-feedback shift register. The taps are
// state[4] and state[2], implementing the primitive polynomial
// x^5 + x^3 + 1. Initial state on reset is 5'b00001; the period is 31.

`timescale 1ns / 1ns

module lfsr5 (
    input  wire       clk,
    input  wire       rst_n,
    output reg  [4:0] state
);
    wire feedback = state[4] ^ state[2];

    always @(posedge clk or negedge rst_n) begin
        if (!rst_n) state <= 5'b00001;
        else        state <= {state[3:0], feedback};
    end
endmodule

packs/shift-register-patterns/src/shift_reg.v
// SPDX-License-Identifier: CC-BY-4.0
// Copyright (c) 2026 Ferrite Engineering
//
// 8-bit shift register. New data enters at q[0]; old data drops out
// from q[7]. Serial-out `sout` mirrors q[7].

`timescale 1ns / 1ns

module shift_reg (
    input  wire       clk,
    input  wire       rst_n,
    input  wire       sin,
    output reg  [7:0] q,
    output wire       sout
);
    always @(posedge clk or negedge rst_n) begin
        if (!rst_n) q <= 8'd0;
        else        q <= {q[6:0], sin};
    end
    assign sout = q[7];
endmodule

packs/shift-register-patterns/tb/tb_shift.v
// SPDX-License-Identifier: CC-BY-4.0
// Copyright (c) 2026 Ferrite Engineering
//
// Drives the shift register and the LFSR side-by-side from a common
// 100 MHz clock. The shift register receives the known 8-bit pattern
// 10110100 (MSB first) one bit per cycle starting at posedge t=30.
// The LFSR runs continuously and completes its 31-state cycle in
// 310 ns, repeating cleanly over the 3 us simulation.

`timescale 1ns / 1ns

module tb_shift;
    reg        clk;
    reg        rst_n;
    reg        sin;
    wire [7:0] q;
    wire       sout;
    wire [4:0] lfsr_state;

    shift_reg u_shift (
        .clk  (clk),
        .rst_n(rst_n),
        .sin  (sin),
        .q    (q),
        .sout (sout)
    );

    lfsr5 u_lfsr (
        .clk  (clk),
        .rst_n(rst_n),
        .state(lfsr_state)
    );

    initial clk = 1'b1;
    always #5 clk = ~clk;

    initial begin
        $dumpfile("fixtures/reference.vcd");
        $dumpvars(0, tb_shift);

        rst_n = 1'b0;
        sin   = 1'b0;
        #22;
        rst_n = 1'b1;

        // sin is sampled on each posedge starting at t=30. Set each
        // bit between posedges so the value is stable at sample time.
        // Pattern: 10110100 (MSB first).
        #3;          sin = 1'b1;   // stable for posedge at t=30
        #10;         sin = 1'b0;   // stable for posedge at t=40
        #10;         sin = 1'b1;   // posedge at t=50
        #10;         sin = 1'b1;   // posedge at t=60
        #10;         sin = 1'b0;   // posedge at t=70
        #10;         sin = 1'b1;   // posedge at t=80
        #10;         sin = 1'b0;   // posedge at t=90
        #10;         sin = 1'b0;   // posedge at t=100
        #10;         sin = 1'b0;   // idle from posedge t=110 onward

        // Continue running until t=3000 ns to give the LFSR multiple
        // full 31-cycle periods.
        #2895;
        $finish;
    end
endmodule

packs/shift-register-patterns/fixtures/reference.vcd
$date
	Sun May 31 14:35:24 2026
$end
$version
	Icarus Verilog
$end
$timescale
	1ns
$end
$scope module tb_shift $end
$var wire 1 ! sout $end
$var wire 8 " q [7:0] $end
$var wire 5 # lfsr_state [4:0] $end
$var reg 1 $ clk $end
$var reg 1 % rst_n $end
$var reg 1 & sin $end
$scope module u_lfsr $end
$var wire 1 $ clk $end
$var wire 1 ' feedback $end
$var wire 1 % rst_n $end
$var reg 5 ( state [4:0] $end
$upscope $end
$scope module u_shift $end
$var wire 1 $ clk $end
$var wire 1 % rst_n $end
$var wire 1 & sin $end
$var wire 1 ! sout $end
$var reg 8 ) q [7:0] $end
$upscope $end
$upscope $end
$enddefinitions $end
$comment Show the parameter values. $end
$dumpall
$end
#0
$dumpvars
b0 )
b1 (
0'
0&
0%
1$
b1 #
b0 "
0!
$end
#5
0$
#10
1$
#15
0$
#20
1$
#22
1%
#25
1&
0$
#30
b10 #
b10 (
b1 "
b1 )
1$
#35
0$
0&
#40
1'
b10 "
b10 )
b100 #
b100 (
1$
#45
0$
1&
#50
0'
b1001 #
b1001 (
b101 "
b101 )
1$
#55
0$
#60
1'
b1011 "
b1011 )
b10010 #
b10010 (
1$
#65
0$
0&
#70
b101 #
b101 (
b10110 "
b10110 )
1$
#75
0$
1&
#80
0'
b101101 "
b101101 )
b1011 #
b1011 (
1$
#85
0$
0&
#90
b10110 #
b10110 (
b1011010 "
b1011010 )
1$
#95
0$
#100
1'
1!
b10110100 "
b10110100 )
b1100 #
b1100 (
1$
#105
0$
#110
0!
b11001 #
b11001 (
b1101000 "
b1101000 )
1$
#115
0$
#120
1!
b11010000 "
b11010000 )
b10011 #
b10011 (
1$
#125
0$
#130
b111 #
b111 (
b10100000 "
b10100000 )
1$
#135
0$
#140
0!
b1000000 "
b1000000 )
b1111 #
b1111 (
1$
#145
0$
#150
0'
1!
b11111 #
b11111 (
b10000000 "
b10000000 )
1$
#155
0$
#160
0!
b0 "
b0 )
b11110 #
b11110 (
1$
#165
0$
#170
b11100 #
b11100 (
1$
#175
0$
#180
1'
b11000 #
b11000 (
1$
#185
0$
#190
b10001 #
b10001 (
1$
#195
0$
#200
0'
b11 #
b11 (
1$
#205
0$
#210
1'
b110 #
b110 (
1$
#215
0$
#220
b1101 #
b1101 (
1$
#225
0$
#230
b11011 #
b11011 (
1$
#235
0$
#240
0'
b10111 #
b10111 (
1$
#245
0$
#250
1'
b1110 #
b1110 (
1$
#255
0$
#260
0'
b11101 #
b11101 (
1$
#265
0$
#270
1'
b11010 #
b11010 (
1$
#275
0$
#280
0'
b10101 #
b10101 (
1$
#285
0$
#290
b1010 #
b1010 (
1$
#295
0$
#300
b10100 #
b10100 (
1$
#305
0$
#310
b1000 #
b1000 (
1$
#315
0$
#320
1'
b10000 #
b10000 (
1$
#325
0$
#330
0'
b1 #
b1 (
1$
#335
0$
#340
b10 #
b10 (
1$
#345
0$
#350
1'
b100 #
b100 (
1$
#355
0$
#360
0'
b1001 #
b1001 (
1$
#365
0$
#370
1'
b10010 #
b10010 (
1$
#375
0$
#380
b101 #
b101 (
1$
#385
0$
#390
0'
b1011 #
b1011 (
1$
#395
0$
#400
b10110 #
b10110 (
1$
#405
0$
#410
1'
b1100 #
b1100 (
1$
#415
0$
#420
b11001 #
b11001 (
1$
#425
0$
#430
b10011 #
b10011 (
1$
#435
0$
#440
b111 #
b111 (
1$
#445
0$
#450
b1111 #
b1111 (
1$
#455
0$
#460
0'
b11111 #
b11111 (
1$
#465
0$
#470
b11110 #
b11110 (
1$
#475
0$
#480
b11100 #
b11100 (
1$
#485
0$
#490
1'
b11000 #
b11000 (
1$
#495
0$
#500
b10001 #
b10001 (
1$
#505
0$
#510
0'
b11 #
b11 (
1$
#515
0$
#520
1'
b110 #
b110 (
1$
#525
0$
#530
b1101 #
b1101 (
1$
#535
0$
#540
b11011 #
b11011 (
1$
#545
0$
#550
0'
b10111 #
b10111 (
1$
#555
0$
#560
1'
b1110 #
b1110 (
1$
#565
0$
#570
0'
b11101 #
b11101 (
1$
#575
0$
#580
1'
b11010 #
b11010 (
1$
#585
0$
#590
0'
b10101 #
b10101 (
1$
#595
0$
#600
b1010 #
b1010 (
1$
#605
0$
#610
b10100 #
b10100 (
1$
#615
0$
#620
b1000 #
b1000 (
1$
#625
0$
#630
1'
b10000 #
b10000 (
1$
#635
0$
#640
0'
b1 #
b1 (
1$
#645
0$
#650
b10 #
b10 (
1$
#655
0$
#660
1'
b100 #
b100 (
1$
#665
0$
#670
0'
b1001 #
b1001 (
1$
#675
0$
#680
1'
b10010 #
b10010 (
1$
#685
0$
#690
b101 #
b101 (
1$
#695
0$
#700
0'
b1011 #
b1011 (
1$
#705
0$
#710
b10110 #
b10110 (
1$
#715
0$
#720
1'
b1100 #
b1100 (
1$
#725
0$
#730
b11001 #
b11001 (
1$
#735
0$
#740
b10011 #
b10011 (
1$
#745
0$
#750
b111 #
b111 (
1$
#755
0$
#760
b1111 #
b1111 (
1$
#765
0$
#770
0'
b11111 #
b11111 (
1$
#775
0$
#780
b11110 #
b11110 (
1$
#785
0$
#790
b11100 #
b11100 (
1$
#795
0$
#800
1'
b11000 #
b11000 (
1$
#805
0$
#810
b10001 #
b10001 (
1$
#815
0$
#820
0'
b11 #
b11 (
1$
#825
0$
#830
1'
b110 #
b110 (
1$
#835
0$
#840
b1101 #
b1101 (
1$
#845
0$
#850
b11011 #
b11011 (
1$
#855
0$
#860
0'
b10111 #
b10111 (
1$
#865
0$
#870
1'
b1110 #
b1110 (
1$
#875
0$
#880
0'
b11101 #
b11101 (
1$
#885
0$
#890
1'
b11010 #
b11010 (
1$
#895
0$
#900
0'
b10101 #
b10101 (
1$
#905
0$
#910
b1010 #
b1010 (
1$
#915
0$
#920
b10100 #
b10100 (
1$
#925
0$
#930
b1000 #
b1000 (
1$
#935
0$
#940
1'
b10000 #
b10000 (
1$
#945
0$
#950
0'
b1 #
b1 (
1$
#955
0$
#960
b10 #
b10 (
1$
#965
0$
#970
1'
b100 #
b100 (
1$
#975
0$
#980
0'
b1001 #
b1001 (
1$
#985
0$
#990
1'
b10010 #
b10010 (
1$
#995
0$
#1000
b101 #
b101 (
1$
#1005
0$
#1010
0'
b1011 #
b1011 (
1$
#1015
0$
#1020
b10110 #
b10110 (
1$
#1025
0$
#1030
1'
b1100 #
b1100 (
1$
#1035
0$
#1040
b11001 #
b11001 (
1$
#1045
0$
#1050
b10011 #
b10011 (
1$
#1055
0$
#1060
b111 #
b111 (
1$
#1065
0$
#1070
b1111 #
b1111 (
1$
#1075
0$
#1080
0'
b11111 #
b11111 (
1$
#1085
0$
#1090
b11110 #
b11110 (
1$
#1095
0$
#1100
b11100 #
b11100 (
1$
#1105
0$
#1110
1'
b11000 #
b11000 (
1$
#1115
0$
#1120
b10001 #
b10001 (
1$
#1125
0$
#1130
0'
b11 #
b11 (
1$
#1135
0$
#1140
1'
b110 #
b110 (
1$
#1145
0$
#1150
b1101 #
b1101 (
1$
#1155
0$
#1160
b11011 #
b11011 (
1$
#1165
0$
#1170
0'
b10111 #
b10111 (
1$
#1175
0$
#1180
1'
b1110 #
b1110 (
1$
#1185
0$
#1190
0'
b11101 #
b11101 (
1$
#1195
0$
#1200
1'
b11010 #
b11010 (
1$
#1205
0$
#1210
0'
b10101 #
b10101 (
1$
#1215
0$
#1220
b1010 #
b1010 (
1$
#1225
0$
#1230
b10100 #
b10100 (
1$
#1235
0$
#1240
b1000 #
b1000 (
1$
#1245
0$
#1250
1'
b10000 #
b10000 (
1$
#1255
0$
#1260
0'
b1 #
b1 (
1$
#1265
0$
#1270
b10 #
b10 (
1$
#1275
0$
#1280
1'
b100 #
b100 (
1$
#1285
0$
#1290
0'
b1001 #
b1001 (
1$
#1295
0$
#1300
1'
b10010 #
b10010 (
1$
#1305
0$
#1310
b101 #
b101 (
1$
#1315
0$
#1320
0'
b1011 #
b1011 (
1$
#1325
0$
#1330
b10110 #
b10110 (
1$
#1335
0$
#1340
1'
b1100 #
b1100 (
1$
#1345
0$
#1350
b11001 #
b11001 (
1$
#1355
0$
#1360
b10011 #
b10011 (
1$
#1365
0$
#1370
b111 #
b111 (
1$
#1375
0$
#1380
b1111 #
b1111 (
1$
#1385
0$
#1390
0'
b11111 #
b11111 (
1$
#1395
0$
#1400
b11110 #
b11110 (
1$
#1405
0$
#1410
b11100 #
b11100 (
1$
#1415
0$
#1420
1'
b11000 #
b11000 (
1$
#1425
0$
#1430
b10001 #
b10001 (
1$
#1435
0$
#1440
0'
b11 #
b11 (
1$
#1445
0$
#1450
1'
b110 #
b110 (
1$
#1455
0$
#1460
b1101 #
b1101 (
1$
#1465
0$
#1470
b11011 #
b11011 (
1$
#1475
0$
#1480
0'
b10111 #
b10111 (
1$
#1485
0$
#1490
1'
b1110 #
b1110 (
1$
#1495
0$
#1500
0'
b11101 #
b11101 (
1$
#1505
0$
#1510
1'
b11010 #
b11010 (
1$
#1515
0$
#1520
0'
b10101 #
b10101 (
1$
#1525
0$
#1530
b1010 #
b1010 (
1$
#1535
0$
#1540
b10100 #
b10100 (
1$
#1545
0$
#1550
b1000 #
b1000 (
1$
#1555
0$
#1560
1'
b10000 #
b10000 (
1$
#1565
0$
#1570
0'
b1 #
b1 (
1$
#1575
0$
#1580
b10 #
b10 (
1$
#1585
0$
#1590
1'
b100 #
b100 (
1$
#1595
0$
#1600
0'
b1001 #
b1001 (
1$
#1605
0$
#1610
1'
b10010 #
b10010 (
1$
#1615
0$
#1620
b101 #
b101 (
1$
#1625
0$
#1630
0'
b1011 #
b1011 (
1$
#1635
0$
#1640
b10110 #
b10110 (
1$
#1645
0$
#1650
1'
b1100 #
b1100 (
1$
#1655
0$
#1660
b11001 #
b11001 (
1$
#1665
0$
#1670
b10011 #
b10011 (
1$
#1675
0$
#1680
b111 #
b111 (
1$
#1685
0$
#1690
b1111 #
b1111 (
1$
#1695
0$
#1700
0'
b11111 #
b11111 (
1$
#1705
0$
#1710
b11110 #
b11110 (
1$
#1715
0$
#1720
b11100 #
b11100 (
1$
#1725
0$
#1730
1'
b11000 #
b11000 (
1$
#1735
0$
#1740
b10001 #
b10001 (
1$
#1745
0$
#1750
0'
b11 #
b11 (
1$
#1755
0$
#1760
1'
b110 #
b110 (
1$
#1765
0$
#1770
b1101 #
b1101 (
1$
#1775
0$
#1780
b11011 #
b11011 (
1$
#1785
0$
#1790
0'
b10111 #
b10111 (
1$
#1795
0$
#1800
1'
b1110 #
b1110 (
1$
#1805
0$
#1810
0'
b11101 #
b11101 (
1$
#1815
0$
#1820
1'
b11010 #
b11010 (
1$
#1825
0$
#1830
0'
b10101 #
b10101 (
1$
#1835
0$
#1840
b1010 #
b1010 (
1$
#1845
0$
#1850
b10100 #
b10100 (
1$
#1855
0$
#1860
b1000 #
b1000 (
1$
#1865
0$
#1870
1'
b10000 #
b10000 (
1$
#1875
0$
#1880
0'
b1 #
b1 (
1$
#1885
0$
#1890
b10 #
b10 (
1$
#1895
0$
#1900
1'
b100 #
b100 (
1$
#1905
0$
#1910
0'
b1001 #
b1001 (
1$
#1915
0$
#1920
1'
b10010 #
b10010 (
1$
#1925
0$
#1930
b101 #
b101 (
1$
#1935
0$
#1940
0'
b1011 #
b1011 (
1$
#1945
0$
#1950
b10110 #
b10110 (
1$
#1955
0$
#1960
1'
b1100 #
b1100 (
1$
#1965
0$
#1970
b11001 #
b11001 (
1$
#1975
0$
#1980
b10011 #
b10011 (
1$
#1985
0$
#1990
b111 #
b111 (
1$
#1995
0$
#2000
b1111 #
b1111 (
1$
#2005
0$
#2010
0'
b11111 #
b11111 (
1$
#2015
0$
#2020
b11110 #
b11110 (
1$
#2025
0$
#2030
b11100 #
b11100 (
1$
#2035
0$
#2040
1'
b11000 #
b11000 (
1$
#2045
0$
#2050
b10001 #
b10001 (
1$
#2055
0$
#2060
0'
b11 #
b11 (
1$
#2065
0$
#2070
1'
b110 #
b110 (
1$
#2075
0$
#2080
b1101 #
b1101 (
1$
#2085
0$
#2090
b11011 #
b11011 (
1$
#2095
0$
#2100
0'
b10111 #
b10111 (
1$
#2105
0$
#2110
1'
b1110 #
b1110 (
1$
#2115
0$
#2120
0'
b11101 #
b11101 (
1$
#2125
0$
#2130
1'
b11010 #
b11010 (
1$
#2135
0$
#2140
0'
b10101 #
b10101 (
1$
#2145
0$
#2150
b1010 #
b1010 (
1$
#2155
0$
#2160
b10100 #
b10100 (
1$
#2165
0$
#2170
b1000 #
b1000 (
1$
#2175
0$
#2180
1'
b10000 #
b10000 (
1$
#2185
0$
#2190
0'
b1 #
b1 (
1$
#2195
0$
#2200
b10 #
b10 (
1$
#2205
0$
#2210
1'
b100 #
b100 (
1$
#2215
0$
#2220
0'
b1001 #
b1001 (
1$
#2225
0$
#2230
1'
b10010 #
b10010 (
1$
#2235
0$
#2240
b101 #
b101 (
1$
#2245
0$
#2250
0'
b1011 #
b1011 (
1$
#2255
0$
#2260
b10110 #
b10110 (
1$
#2265
0$
#2270
1'
b1100 #
b1100 (
1$
#2275
0$
#2280
b11001 #
b11001 (
1$
#2285
0$
#2290
b10011 #
b10011 (
1$
#2295
0$
#2300
b111 #
b111 (
1$
#2305
0$
#2310
b1111 #
b1111 (
1$
#2315
0$
#2320
0'
b11111 #
b11111 (
1$
#2325
0$
#2330
b11110 #
b11110 (
1$
#2335
0$
#2340
b11100 #
b11100 (
1$
#2345
0$
#2350
1'
b11000 #
b11000 (
1$
#2355
0$
#2360
b10001 #
b10001 (
1$
#2365
0$
#2370
0'
b11 #
b11 (
1$
#2375
0$
#2380
1'
b110 #
b110 (
1$
#2385
0$
#2390
b1101 #
b1101 (
1$
#2395
0$
#2400
b11011 #
b11011 (
1$
#2405
0$
#2410
0'
b10111 #
b10111 (
1$
#2415
0$
#2420
1'
b1110 #
b1110 (
1$
#2425
0$
#2430
0'
b11101 #
b11101 (
1$
#2435
0$
#2440
1'
b11010 #
b11010 (
1$
#2445
0$
#2450
0'
b10101 #
b10101 (
1$
#2455
0$
#2460
b1010 #
b1010 (
1$
#2465
0$
#2470
b10100 #
b10100 (
1$
#2475
0$
#2480
b1000 #
b1000 (
1$
#2485
0$
#2490
1'
b10000 #
b10000 (
1$
#2495
0$
#2500
0'
b1 #
b1 (
1$
#2505
0$
#2510
b10 #
b10 (
1$
#2515
0$
#2520
1'
b100 #
b100 (
1$
#2525
0$
#2530
0'
b1001 #
b1001 (
1$
#2535
0$
#2540
1'
b10010 #
b10010 (
1$
#2545
0$
#2550
b101 #
b101 (
1$
#2555
0$
#2560
0'
b1011 #
b1011 (
1$
#2565
0$
#2570
b10110 #
b10110 (
1$
#2575
0$
#2580
1'
b1100 #
b1100 (
1$
#2585
0$
#2590
b11001 #
b11001 (
1$
#2595
0$
#2600
b10011 #
b10011 (
1$
#2605
0$
#2610
b111 #
b111 (
1$
#2615
0$
#2620
b1111 #
b1111 (
1$
#2625
0$
#2630
0'
b11111 #
b11111 (
1$
#2635
0$
#2640
b11110 #
b11110 (
1$
#2645
0$
#2650
b11100 #
b11100 (
1$
#2655
0$
#2660
1'
b11000 #
b11000 (
1$
#2665
0$
#2670
b10001 #
b10001 (
1$
#2675
0$
#2680
0'
b11 #
b11 (
1$
#2685
0$
#2690
1'
b110 #
b110 (
1$
#2695
0$
#2700
b1101 #
b1101 (
1$
#2705
0$
#2710
b11011 #
b11011 (
1$
#2715
0$
#2720
0'
b10111 #
b10111 (
1$
#2725
0$
#2730
1'
b1110 #
b1110 (
1$
#2735
0$
#2740
0'
b11101 #
b11101 (
1$
#2745
0$
#2750
1'
b11010 #
b11010 (
1$
#2755
0$
#2760
0'
b10101 #
b10101 (
1$
#2765
0$
#2770
b1010 #
b1010 (
1$
#2775
0$
#2780
b10100 #
b10100 (
1$
#2785
0$
#2790
b1000 #
b1000 (
1$
#2795
0$
#2800
1'
b10000 #
b10000 (
1$
#2805
0$
#2810
0'
b1 #
b1 (
1$
#2815
0$
#2820
b10 #
b10 (
1$
#2825
0$
#2830
1'
b100 #
b100 (
1$
#2835
0$
#2840
0'
b1001 #
b1001 (
1$
#2845
0$
#2850
1'
b10010 #
b10010 (
1$
#2855
0$
#2860
b101 #
b101 (
1$
#2865
0$
#2870
0'
b1011 #
b1011 (
1$
#2875
0$
#2880
b10110 #
b10110 (
1$
#2885
0$
#2890
1'
b1100 #
b1100 (
1$
#2895
0$
#2900
b11001 #
b11001 (
1$
#2905
0$
#2910
b10011 #
b10011 (
1$
#2915
0$
#2920
b111 #
b111 (
1$
#2925
0$
#2930
b1111 #
b1111 (
1$
#2935
0$
#2940
0'
b11111 #
b11111 (
1$
#2945
0$
#2950
b11110 #
b11110 (
1$
#2955
0$
#2960
b11100 #
b11100 (
1$
#2965
0$
#2970
1'
b11000 #
b11000 (
1$
#2975
0$
#2980
b10001 #
b10001 (
1$
#2985
0$
#2990
0'
b11 #
b11 (
1$
#2995
0$
#3000
1'
b110 #
b110 (
1$
