packs/cdc-soc-capstone/src/consumer.v
module consumer (input clk_b, rst_n, req_sync, input [7:0] data_bus, output reg [7:0] captured);
  always @(posedge clk_b or negedge rst_n)
    if (!rst_n) captured<=0;
    else if (req_sync) captured<=data_bus;   // captures the UNsynchronised bus
endmodule

packs/cdc-soc-capstone/src/sync2.v
module sync2 (input clk, rst_n, d, output q);
  reg meta, ff;
  always @(posedge clk or negedge rst_n) if(!rst_n) {meta,ff}<=0; else {ff,meta}<={meta,d};
  assign q = ff;
endmodule

packs/cdc-soc-capstone/src/producer.v
`timescale 1ns/1ns
// A two-clock-domain SoC fragment: a producer counts in clk_a; a request bit is
// safely double-flopped into clk_b, but an 8-bit data word crosses UNsynchronised
// — a deliberate CDC hazard for manual analysis. (The free toolchain has no CDC
// engine; identifying this crossing is a student methodology deliverable.)

module producer (input clk_a, rst_n, output reg req, output reg [7:0] data);
  reg [7:0] cnt;
  always @(posedge clk_a or negedge rst_n)
    if (!rst_n) begin cnt<=0; req<=0; data<=0; end
    else begin cnt<=cnt+1; data<=cnt; req<=cnt[3]; end   // data changes every clk_a
endmodule

packs/cdc-soc-capstone/src/soc_top.v
module soc_top (input clk_a, clk_b, rst_n, output [7:0] captured);
  wire req; wire [7:0] data; wire req_sync;
  producer u_prod (.clk_a(clk_a), .rst_n(rst_n), .req(req), .data(data));
  sync2    u_sync (.clk(clk_b), .rst_n(rst_n), .d(req), .q(req_sync));       // req: SAFE (2-flop)
  consumer u_cons (.clk_b(clk_b), .rst_n(rst_n), .req_sync(req_sync),
                   .data_bus(data), .captured(captured));                     // data: HAZARD
endmodule

packs/cdc-soc-capstone/tb/tb_soc.v
`timescale 1ns/1ns
module tb_soc;
  reg clk_a=0, clk_b=0, rst_n=0; wire [7:0] captured;
  soc_top dut (.clk_a(clk_a), .clk_b(clk_b), .rst_n(rst_n), .captured(captured));
  always #5  clk_a=~clk_a;   // 100 MHz-ish
  always #7  clk_b=~clk_b;   // asynchronous, slower — a real clock-domain pair

  // The regression checks the SAFE path: after reset, the synchronized request
  // eventually causes SOME capture (the sync2 handshake works). It does NOT
  // assert the captured DATA value — that is exactly the unreliable, CDC-hazard
  // path the student must analyse by hand.
  reg [7:0] first_cap; integer seen;
  initial begin
    $dumpfile("fixtures/reference.vcd"); $dumpvars(0, tb_soc);
    #20 rst_n=1;
    seen=0; first_cap=0;
    #400;
    if (captured!==8'hxx) begin $display("RESULT sync_handshake_captures PASS"); end
    else                       $display("RESULT sync_handshake_captures FAIL");
    // A second check: the safe request bit is a clean two-flop synchronised value
    // (no metastable X on req_sync in steady state).
    if (dut.req_sync===1'b0 || dut.req_sync===1'b1) $display("RESULT req_is_two_flop_clean PASS");
    else                                            $display("RESULT req_is_two_flop_clean FAIL");
    #20 $finish;
  end
endmodule

packs/cdc-soc-capstone/fixtures/reference.vcd
$date
	Fri Jul 24 11:57:34 2026
$end
$version
	Icarus Verilog
$end
$timescale
	1ns
$end
$scope module tb_soc $end
$var wire 8 ! captured [7:0] $end
$var reg 1 " clk_a $end
$var reg 1 # clk_b $end
$var reg 8 $ first_cap [7:0] $end
$var reg 1 % rst_n $end
$var integer 32 & seen [31:0] $end
$scope module dut $end
$var wire 1 " clk_a $end
$var wire 1 # clk_b $end
$var wire 1 % rst_n $end
$var wire 1 ' req_sync $end
$var wire 1 ( req $end
$var wire 8 ) data [7:0] $end
$var wire 8 * captured [7:0] $end
$scope module u_cons $end
$var wire 1 # clk_b $end
$var wire 1 % rst_n $end
$var wire 1 ' req_sync $end
$var wire 8 + data_bus [7:0] $end
$var reg 8 , captured [7:0] $end
$upscope $end
$scope module u_prod $end
$var wire 1 " clk_a $end
$var wire 1 % rst_n $end
$var reg 8 - cnt [7:0] $end
$var reg 8 . data [7:0] $end
$var reg 1 ( req $end
$upscope $end
$scope module u_sync $end
$var wire 1 # clk $end
$var wire 1 ( d $end
$var wire 1 ' q $end
$var wire 1 % rst_n $end
$var reg 1 / ff $end
$var reg 1 0 meta $end
$upscope $end
$upscope $end
$upscope $end
$enddefinitions $end
$comment Show the parameter values. $end
$dumpall
$end
#0
$dumpvars
x0
x/
bx .
bx -
bx ,
bx +
bx *
bx )
x(
x'
bx &
0%
bx $
0#
0"
bx !
$end
#5
b0 )
b0 +
b0 .
0(
b0 -
1"
#7
00
0'
0/
b0 !
b0 *
b0 ,
1#
#10
0"
#14
0#
#15
1"
#20
0"
b0 $
b0 &
1%
#21
1#
#25
b1 -
1"
#28
0#
#30
0"
#35
b1 )
b1 +
b1 .
b10 -
1"
1#
#40
0"
#42
0#
#45
b10 )
b10 +
b10 .
b11 -
1"
#49
1#
#50
0"
#55
b11 )
b11 +
b11 .
b100 -
1"
#56
0#
#60
0"
#63
1#
#65
b100 )
b100 +
b100 .
b101 -
1"
#70
0"
0#
#75
b101 )
b101 +
b101 .
b110 -
1"
#77
1#
#80
0"
#84
0#
#85
b110 )
b110 +
b110 .
b111 -
1"
#90
0"
#91
1#
#95
b111 )
b111 +
b111 .
b1000 -
1"
#98
0#
#100
0"
#105
1(
b1000 )
b1000 +
b1000 .
b1001 -
1"
1#
#110
0"
#112
0#
#115
b1001 )
b1001 +
b1001 .
b1010 -
1"
#119
10
1#
#120
0"
#125
b1010 )
b1010 +
b1010 .
b1011 -
1"
#126
0#
#130
0"
#133
1'
1/
1#
#135
b1011 )
b1011 +
b1011 .
b1100 -
1"
#140
0"
0#
#145
b1100 )
b1100 +
b1100 .
b1101 -
1"
#147
b1100 !
b1100 *
b1100 ,
1#
#150
0"
#154
0#
#155
b1101 )
b1101 +
b1101 .
b1110 -
1"
#160
0"
#161
b1101 !
b1101 *
b1101 ,
1#
#165
b1110 )
b1110 +
b1110 .
b1111 -
1"
#168
0#
#170
0"
#175
b1111 )
b1111 +
b1111 .
b10000 -
b1110 !
b1110 *
b1110 ,
1"
1#
#180
0"
#182
0#
#185
0(
b10000 )
b10000 +
b10000 .
b10001 -
1"
#189
b10000 !
b10000 *
b10000 ,
00
1#
#190
0"
#195
b10001 )
b10001 +
b10001 .
b10010 -
1"
#196
0#
#200
0"
#203
0'
0/
b10001 !
b10001 *
b10001 ,
1#
#205
b10010 )
b10010 +
b10010 .
b10011 -
1"
#210
0"
0#
#215
b10011 )
b10011 +
b10011 .
b10100 -
1"
#217
1#
#220
0"
#224
0#
#225
b10100 )
b10100 +
b10100 .
b10101 -
1"
#230
0"
#231
1#
#235
b10101 )
b10101 +
b10101 .
b10110 -
1"
#238
0#
#240
0"
#245
b10110 )
b10110 +
b10110 .
b10111 -
1"
1#
#250
0"
#252
0#
#255
b10111 )
b10111 +
b10111 .
b11000 -
1"
#259
1#
#260
0"
#265
1(
b11000 )
b11000 +
b11000 .
b11001 -
1"
#266
0#
#270
0"
#273
10
1#
#275
b11001 )
b11001 +
b11001 .
b11010 -
1"
#280
0"
0#
#285
b11010 )
b11010 +
b11010 .
b11011 -
1"
#287
1'
1/
1#
#290
0"
#294
0#
#295
b11011 )
b11011 +
b11011 .
b11100 -
1"
#300
0"
#301
b11011 !
b11011 *
b11011 ,
1#
#305
b11100 )
b11100 +
b11100 .
b11101 -
1"
#308
0#
#310
0"
#315
b11101 )
b11101 +
b11101 .
b11110 -
b11100 !
b11100 *
b11100 ,
1"
1#
#320
0"
#322
0#
#325
b11110 )
b11110 +
b11110 .
b11111 -
1"
#329
b11110 !
b11110 *
b11110 ,
1#
#330
0"
#335
b11111 )
b11111 +
b11111 .
b100000 -
1"
#336
0#
#340
0"
#343
b11111 !
b11111 *
b11111 ,
1#
#345
0(
b100000 )
b100000 +
b100000 .
b100001 -
1"
#350
0"
0#
#355
b100001 )
b100001 +
b100001 .
b100010 -
1"
#357
b100001 !
b100001 *
b100001 ,
00
1#
#360
0"
#364
0#
#365
b100010 )
b100010 +
b100010 .
b100011 -
1"
#370
0"
#371
0'
0/
b100010 !
b100010 *
b100010 ,
1#
#375
b100011 )
b100011 +
b100011 .
b100100 -
1"
#378
0#
#380
0"
#385
b100100 )
b100100 +
b100100 .
b100101 -
1"
1#
#390
0"
#392
0#
#395
b100101 )
b100101 +
b100101 .
b100110 -
1"
#399
1#
#400
0"
#405
b100110 )
b100110 +
b100110 .
b100111 -
1"
#406
0#
#410
0"
#413
1#
#415
b100111 )
b100111 +
b100111 .
b101000 -
1"
#420
0"
0#
#425
1(
b101000 )
b101000 +
b101000 .
b101001 -
1"
#427
10
1#
#430
0"
#434
0#
#435
b101001 )
b101001 +
b101001 .
b101010 -
1"
